Workbook
Name An: IF(CLEVER=TRUE,MIN(80,choix_an+29),choix_an+29)
Name An_calcul: [0]!choix_an_calcul+29
Name Cep_biomasse: 1
Name Cep_fossiles: 1
Name Cep_géothermie: 1
Name ConvC02C: (12+16*2)/12
Name ConvCO2C: (12+16*2)/12
Name ConvGWhVersTep: 86
Name ConvVPMLenMtep: 0.806
Name DiesterTep: 0.000807
Name EssenceTep: 0.000786
Name F_choix: IF(#REF!="S",IF(sobriété=TRUE,#REF!,#REF!),IF(#REF!="E",IF(efficacité=TRUE,#REF!,#REF!),IF(#REF!="EN",IF(ENR=TRUE,#REF!,#REF!),#REF!)))
Name G: 1000000000
Name GazoleTep: 0.000845
Name GNVTep: 0.000811
Name k: 1000
Name KérozèneTep: 0.000828
Name M: 1000000
Name Mtep_TWh: 11.628
Name MtepenTWh: 0.086
Name Nh_an: 8760
Name P: PI()/180
Name PCI_PCS_biomasse: IF(#REF!=1,1,PCS_biomasse)
Name PCI_PCS_charbon: IF(#REF!=1,1,PCS_charbon)
Name PCI_PCS_dechets: IF(PCS_PCI=1,1,PCS_dechets)
Name PCI_PCS_gaz: IF(#REF!=1,1,PCS_GN)
Name PCI_PCS_H2: IF(#REF!=1,1,PCS_H2)
Name PCI_PCS_petrole: IF(#REF!=1,1,PCS_petrole)
Name PCS_biomasse: 1.09
Name PCS_biomasse_solide: 1.09
Name PCS_charbon: 1.052
Name PCS_dechets: 1.064
Name PCS_fioul: 1.075
Name PCS_gaz: 1.111
Name PCS_GN: 1.111
Name PCS_GPL: 1.087
Name PCS_H2: 141860/119930
Name PCS_PCI: IF(#REF!=TRUE,2,#REF!)
Name PCS_PCI_biomasse: IF(PCS_PCI=1,PCS_biomasse,1)
Name PCS_PCI_charbon: IF(PCS_PCI=1,PCS_charbon,1)
Name PCS_PCI_dechets: IF(PCS_PCI=1,PCS_dechets,1)
Name PCS_PCI_gaz: IF(PCS_PCI=1,PCS_GN,1)
Name PCS_PCI_GPL: IF(PCS_PCI=1,PCS_GPL,1)
Name PCS_PCI_H2: IF(PCS_PCI=1,PCS_H2,1)
Name PCS_PCI_petrole: IF(PCS_PCI=1,PCS_petrole,1)
Name PCS_petrole: 1.075
Name pi: PI()
Name SHAB_SHON: 1
Name T: 10^12
Name TepTWh: 11.63*10^-6
Name TWh_GJ: 3600000
Name year_simulated: Constants!$B$2

Sheet Légende - Sources

Sheet ACCUEIL
A1: Descriptif des pages
A4: Nom | B4: Descriptif | C4: Indexation
A5: Data_EOLES | B5: feuille avec toutes les données de nW utiles à EOLES
A6: traitement_nW_EOLES | B6: Calculs intermédiaires pour données exploitables avec EOLES
A7: create_demand_param | B7: Constantes du problème pour la pipeline de construction de la demande horaire
A8: Constants | B8: constantes du problème non repertoriées ailleurs | C8: n
A9: Costs | B9: coûts des différentes technologies | C9: tech
A10: fuel_prices | B10: coût des ressources fossiles (natural_gas et coal) | C10: tech
A11: tech_parameters | B11: paramètres techniques des différentes technologies | C11: tech
A12: reserve | B12: paramètres techniques des marchés de réserve | C12: reserve
A13: exist_cap | B13: capacités de production existantes (en puissance) | C13: areas, tech
A14: exist_en_cap | B14: capacités de production existantes (en énergie) | C14: areas, tech
A15: min_cap | B15: capacités de production existantes (en puissance) | C15: areas, tech
A16: min_en_cap | B16: capacités de production existantes (en énergie) | C16: areas, tech
A17: max_cap | B17: capacités de production existantes (en puissance) | C17: areas, tech
A18: max_en_cap | B18: capacités de production existantes (en énergie) | C18: areas, tech
A19: links | B19: capacités d'interconnexions entre les pays | C19: areas, areas
... A21: demand_EU | B21: demandes globales par pays pour chaque vecteur (élec et gaz) | C21: areas, vectors

Sheet Data_EOLES
A1: Catégorie EOLES | B1: Usage EOLES | C1: Code EOLES | D1: Secteur | E1: Profil | F1: Libellé | G1: Unité | H1: Code SnW27 | I1: Module SnW27 | J1: 2019 | K1: =J1+1 -> 2020 | L1: =K1+1 -> 2021 | M1: =L1+1 -> 2022 | N1: =M1+1 -> 2023 | O1: =N1+1 -> 2024 | P1: =O1+1 -> 2025 | Q1: =P1+1 -> 2026 | R1: =Q1+1 -> 2027 | ... BI1: =BH1+1 -> 2070 | BJ1: Libellé dans BDD indicateurs | BK1: Pour somme demande élec
A2: Courbe de charge elec | B2: donnée nécessitant un traitement dans traitement_nW_EOLES | C2: demand_elec_res_heat | D2: Résidentiel | E2: Thermosensible chaud | F2: Conso d'élec pour chauffage résidentiel (effet joule + électricité des PAC) | G2: TWh/an | H2: elccfreschf | I2: bâtiment_démographie_v2.6 | J2: 48.47084 | K2: 44.72675 | L2: 45.52188 | M2: 41.8848 | N2: 38.35691 | O2: 37.0631 | P2: 36.91469 | Q2: 36.77802 | R2: 36.66374 | S2: 36.57943 | T2: 36.5349 | U2: 36.54035 | V2: 36.57321 | W2: 36.66549 | X2: 36.80986 | Y2: 36.99546 | Z2: 37.20951 | AA2: 37.42921 | AB2: 37.6157 | AC2: 37.72222 | AD2: 37.7096 | AE2: 37.55723 | AF2: 37.26582 | AG2: 36.85582 | AH2: 36.3602 | AI2: 35.81675 | AJ2: 34.84306 | AK2: 33.72558 | AL2: 32.65873 | AM2: 31.64907 | AN2: 30.6911 | AO2: 29.77571 | AP2: 29.26579 | AQ2: 28.81425 | AR2: 28.42498 | AS2: 28.09388 | AT2: 27.99908 | AU2: 27.91781 | AV2: 27.82532 | AW2: 27.75478 | AX2: 27.68513 | AY2: 27.61632 | AZ2: 27.54848 | BA2: 27.48176 | BB2: 27.41638 | BC2: 27.35258 | BD2: 27.29059 | BE2: 27.23068 | BF2: 27.17308 | BG2: 27.11812 | BH2: 27.06633 | BI2: 27.01697 | BJ2: Consommation finale d'électricité pour le chauffage des locaux | BK2: TRUE
A3: Courbe de charge elec | B3: donnée nécessitant un traitement dans traitement_nW_EOLES | C3: demand_elec_res_cool | D3: Résidentiel | E3: Thermosensible froid | F3: Conso d'élec pour clim résidentiel | G3: TWh/an | H3: elccfrescli | I3: bâtiment_démographie_v2.6 | J3: 2.63834 | K3: 2.81314 | L3: 2.7415 | M3: 2.66986 | N3: 2.59822 | O3: 2.52658 | P3: 2.45494 | Q3: 2.38329 | R3: 2.31165 | S3: 2.24001 | T3: 2.16837 | U3: 2.09673 | V3: 2.15077 | W3: 2.20482 | X3: 2.25886 | Y3: 2.3129 | Z3: 2.36694 | AA3: 2.42099 | AB3: 2.47503 | AC3: 2.52907 | AD3: 2.58311 | AE3: 2.63716 | AF3: 2.70747 | AG3: 2.77778 | AH3: 2.84809 | AI3: 2.9184 | AJ3: 2.98872 | AK3: 3.05903 | AL3: 3.12934 | AM3: 3.19965 | AN3: 3.26996 | AO3: =6+3.34028 -> 9.34028 | AP3: 3.34028 | AQ3: 3.34028 | AR3: 3.34028 | AS3: 3.34028 | AT3: 3.34028 | AU3: 3.34028 | AV3: 3.34028 | AW3: 3.34028 | AX3: 3.34028 | AY3: 3.34028 | AZ3: 3.34028 | BA3: 3.34028 | BB3: 3.34028 | BC3: 3.34028 | BD3: 3.34028 | BE3: 3.34028 | BF3: 3.34028 | BG3: 3.34028 | BH3: 3.34028 | BI3: 3.34028 | BJ3: #N/A | BK3: TRUE
A4: Courbe de charge elec | B4: donnée non utilisée mais vérif de cohérence sur cet onglet | C4: demand_elec | D4: Résidentiel | E4: Flexible | F4: Eau chaude sanitaire résidentiel | G4: TWh/an | H4: elccfresecs | I4: bâtiment_démographie_v2.6 | J4: 23.54842 | K4: 24.15811 | L4: 24.00329 | M4: 23.87498 | N4: 23.74596 | O4: 23.61225 | P4: 23.43499 | Q4: 23.25899 | R4: 23.06652 | S4: 22.85036 | T4: 22.60113 | U4: 22.30644 | V4: 21.95166 | W4: 21.51912 | X4: 20.98907 | Y4: 20.34663 | Z4: 19.58952 | AA4: 18.72964 | AB4: 17.78878 | AC4: 16.79572 | AD4: 15.78491 | AE4: 14.79282 | AF4: 13.85359 | AG4: 12.99359 | AH4: 12.23018 | AI4: 11.57133 | AJ4: 11.01671 | AK4: 10.55947 | AL4: 10.18833 | AM4: 9.88982 | AN4: 9.64988 | AO4: 9.4551 | AP4: 9.29372 | AQ4: 9.15603 | AR4: 9.0344 | AS4: 8.92321 | AT4: 8.81862 | AU4: 8.71816 | AV4: 8.62029 | AW4: 8.52415 | AX4: 8.42928 | AY4: 8.33555 | AZ4: 8.24293 | BA4: 8.15137 | BB4: 8.06095 | BC4: 7.97174 | BD4: 7.88376 | BE4: 7.79706 | BF4: 7.71161 | BG4: 7.62741 | BH4: 7.54443 | BI4: 7.46245 | BJ4: Consommation finale d'électricité pour l'eau chaude sanitaire | BK4: TRUE
A5: Courbe de charge elec | B5: donnée non utilisée mais vérif de cohérence sur cet onglet | C5: demand_elec | D5: Résidentiel | E5: Base | F5: Cuisson résidentiel | G5: TWh/an | H5: elccfrescui | I5: bâtiment_démographie_v2.6 | J5: 11.43404 | K5: 11.49283 | L5: 11.49989 | M5: 11.54846 | N5: 11.54021 | O5: 11.54129 | P5: 11.54815 | Q5: 11.54849 | R5: 11.54848 | S5: 11.54954 | T5: 11.55082 | U5: 11.55067 | V5: 11.56449 | W5: 11.57161 | X5: 11.57451 | Y5: 11.57351 | Z5: 11.56722 | AA5: 11.55051 | AB5: 11.53024 | AC5: 11.50576 | AD5: 11.47782 | AE5: 11.44568 | AF5: 11.41174 | AG5: 11.37752 | AH5: 11.33698 | AI5: 11.29355 | AJ5: 11.25397 | AK5: 11.19814 | AL5: 11.13958 | AM5: 11.07856 | AN5: 11.01599 | AO5: 10.95011 | AP5: 10.86319 | AQ5: 10.77684 | AR5: 10.69197 | AS5: 10.60695 | AT5: 10.52402 | AU5: 10.4556 | AV5: 10.38962 | AW5: 10.33228 | AX5: 10.2715 | AY5: 10.21387 | AZ5: 10.20199 | BA5: 10.19091 | BB5: 10.18092 | BC5: 10.1723 | BD5: 10.16536 | BE5: 10.1604 | BF5: 10.15773 | BG5: 10.1577 | BH5: 10.16065 | BI5: 10.16587 | BJ5: Consommation électrique finale pour la cuisson domestique | BK5: TRUE
A6: Courbe de charge elec | B6: donnée non utilisée mais vérif de cohérence sur cet onglet | C6: demand_elec | D6: Résidentiel | E6: Base | F6: Eclairage et équipements domestiques résidentiel | G6: TWh/an | H6: elecfresels | I6: bâtiment_démographie_v2.6 | J6: 61.46746 | K6: 60.49832 | L6: 59.46206 | M6: 58.22864 | N6: 57.27204 | O6: 56.35774 | P6: 55.69386 | Q6: 54.9437 | R6: 54.32433 | S6: 53.57981 | T6: 52.90193 | U6: 52.14314 | V6: 51.39607 | W6: 50.61336 | X6: 49.73607 | Y6: 48.89056 | Z6: 48.03674 | AA6: 47.2159 | AB6: 46.39659 | AC6: 45.59354 | AD6: 44.7931 | AE6: 43.98136 | AF6: 43.28281 | AG6: 42.5638 | AH6: 41.858 | AI6: 41.17545 | AJ6: 40.47455 | AK6: 39.85535 | AL6: 39.25918 | AM6: 38.65958 | AN6: 38.0836 | AO6: 37.51643 | AP6: 37.11088 | AQ6: 36.73396 | AR6: 36.3857 | AS6: 36.04544 | AT6: 35.73098 | AU6: 35.42412 | AV6: 35.12693 | AW6: 34.84289 | AX6: 34.57394 | AY6: 34.31166 | AZ6: 34.437 | BA6: 34.56435 | BB6: 34.69471 | BC6: 34.82915 | BD6: 34.96878 | BE6: 34.95351 | BF6: 34.94589 | BG6: 34.94708 | BH6: 34.95829 | BI6: 34.97717 | BJ6: Électricité spécifique | BK6: TRUE
A7: Courbe de charge elec | B7: donnée non utilisée mais vérif de cohérence sur cet onglet | C7: demand_elec | D7: Résidentiel | E7: Base | F7: Autre élec spécifique résidentiel (ventilation, portes auto, ascenseurs etc.) | G7: TWh/an | H7: elccfresbmg | I7: bâtiment_démographie_v2.6 | J7: 12.31708 | K7: 12.08928 | L7: 11.90191 | M7: 11.71528 | N7: 11.48913 | O7: 11.26854 | P7: 11.05675 | Q7: 10.83909 | R7: 10.62517 | S7: 10.41785 | T7: 10.22151 | U7: 10.0415 | V7: 9.94382 | W7: 9.8859 | X7: 9.87377 | Y7: 9.90752 | Z7: 9.9802 | AA7: 10.0807 | AB7: 10.20109 | AC7: 10.33705 | AD7: 10.48493 | AE7: 10.64278 | AF7: 10.80621 | AG7: 10.97841 | AH7: 11.15873 | AI7: 11.34493 | AJ7: 11.53984 | AK7: 11.74112 | AL7: 11.75829 | AM7: 11.78032 | AN7: 11.80378 | AO7: 11.8218 | AP7: 11.87645 | AQ7: 11.92889 | AR7: 11.97892 | AS7: 12.02639 | AT7: 12.0712 | AU7: 12.18622 | AV7: 12.28619 | AW7: 12.35609 | AX7: 12.42094 | AY7: 12.48109 | AZ7: 12.46781 | BA7: 12.45538 | BB7: 12.44415 | BC7: 12.43447 | BD7: 12.42673 | BE7: 12.42131 | BF7: 12.4186 | BG7: 12.41902 | BH7: 12.423 | BI7: 12.42971 | BJ7: #N/A | BK7: TRUE
A8: Courbe de charge elec | B8: donnée nécessitant un traitement dans traitement_nW_EOLES | C8: demand_elec_res | D8: Résidentiel | F8: TOTAL | G8: TWh/an | H8: elccfres | I8: bâtiment_démographie_v2.6 | J8: 159.87619 | K8: 155.77842 | L8: 155.13052 | M8: 149.92202 | N8: 145.00248 | O8: 142.3695 | P8: 141.10338 | Q8: 139.75159 | R8: 138.53989 | S8: 137.21699 | T8: 135.97866 | U8: 134.67883 | V8: 133.58002 | W8: 132.46029 | X8: 131.24214 | Y8: 130.02658 | Z8: 128.75012 | AA8: 127.42694 | AB8: 126.00742 | AC8: 124.48337 | AD8: 122.83348 | AE8: 121.05702 | AF8: 119.32763 | AG8: 117.54692 | AH8: 115.79219 | AI8: 114.12042 | AJ8: 112.11685 | AK8: 110.13868 | AL8: 108.13344 | AM8: 106.25701 | AN8: 104.51431 | AO8: 102.85942 | AP8: 101.75032 | AQ8: 100.75025 | AR8: 99.85624 | AS8: 99.03614 | AT8: 98.48418 | AU8: 98.04218 | AV8: 97.58863 | AW8: 97.15046 | AX8: 96.72106 | AY8: 96.29877 | AZ8: 96.23847 | BA8: 96.18404 | BB8: 96.13739 | BC8: 96.10052 | BD8: 96.0755 | BE8: 95.90322 | BF8: 95.7472 | BG8: 95.60961 | BH8: 95.49297 | BI8: 95.39246
A9: Courbe de charge elec | B9: donnée non utilisée mais vérif de cohérence sur cet onglet | C9: demand_elec | D9: Résidentiel | F9: DELTA TOTAL vs. somme | G9: TWh/an | J9: =J8-SUM(J2:J7) -> 1e-05 | K9: =K8-SUM(K2:K7) -> -1e-05 | L9: =L8-SUM(L2:L7) -> -1e-05 | M9: =M8-SUM(M2:M7) -> 0 | N9: =N8-SUM(N2:N7) -> 1e-05 | O9: =O8-SUM(O2:O7) -> 0 | P9: =P8-SUM(P2:P7) -> 0 | Q9: =Q8-SUM(Q2:Q7) -> 1e-05 | ... BI9: =BI8-SUM(BI2:BI7) -> 1e-05
A11: Courbe de charge elec | B11: donnée nécessitant un traitement dans traitement_nW_EOLES | C11: demand_elec_ter_heat | D11: Tertiaire | E11: Thermosensible chaud | F11: Conso d'élec pour chauffage tertiaire (effet joule + électricité des PAC) | G11: TWh/an | H11: elccfterchf | I11: bâtiment_démographie_v2.6 | J11: 23.74654 | K11: 23.49369 | L11: 23.57614 | M11: 22.11833 | N11: 20.9132 | O11: 20.8733 | P11: 20.83607 | Q11: 20.80356 | R11: 20.77722 | S11: 20.75703 | T11: 20.73991 | U11: 20.7173 | V11: 20.66716 | W11: 20.57812 | X11: 20.43439 | Y11: 20.23017 | Z11: 19.97013 | AA11: 19.6635 | AB11: 19.31066 | AC11: 18.86838 | AD11: 18.39653 | AE11: 17.89397 | AF11: 17.35949 | AG11: 16.79237 | AH11: 16.19292 | AI11: 15.56331 | AJ11: 14.90783 | AK11: 14.23456 | AL11: 13.55445 | AM11: 12.88005 | AN11: 12.22418 | AO11: 11.59836 | AP11: 11.01158 | AQ11: 10.46973 | AR11: 9.97562 | AS11: 9.52937 | AT11: 9.12905 | AU11: 8.7713 | AV11: 8.45187 | AW11: 8.16603 | AX11: 7.90898 | AY11: 7.67608 | AZ11: 7.46309 | BA11: 7.26625 | BB11: 7.08237 | BC11: 6.90883 | BD11: 6.74264 | BE11: 6.57972 | BF11: 6.42208 | BG11: 6.27472 | BH11: 6.15613 | BI11: 6.0352 | BJ11: #N/A | BK11: TRUE
A12: Courbe de charge elec | B12: donnée nécessitant un traitement dans traitement_nW_EOLES | C12: demand_elec_ter_cool | D12: Tertiaire | E12: Thermosensible froid | F12: Conso d'élec pour clim tertiaire | G12: TWh/an | H12: elccftercli | I12: bâtiment_démographie_v2.6 | J12: 13.5157 | K12: 13.4038 | L12: 15.46657 | M12: 15.52641 | N12: 15.58476 | O12: 15.63895 | P12: 15.68799 | Q12: 15.732 | R12: 15.77105 | S12: 15.80526 | T12: 15.8348 | U12: 15.85965 | V12: 15.87989 | W12: 15.89563 | X12: 15.90682 | Y12: 15.91348 | Z12: 15.9156 | AA12: 15.91325 | AB12: 15.90645 | AC12: 15.89525 | AD12: 15.87972 | AE12: 15.85992 | AF12: 15.836 | AG12: 15.80805 | AH12: 15.77617 | AI12: 15.74047 | AJ12: 15.70113 | AK12: 15.65821 | AL12: 15.6117 | AM12: 15.5617 | AN12: 15.5083 | AO12: 15.45151 | AP12: 15.58463 | AQ12: 15.71498 | AR12: 15.84244 | AS12: 15.96692 | AT12: 16.08841 | AU12: 16.20691 | AV12: 16.32247 | AW12: 16.4351 | AX12: 16.54484 | AY12: 16.65179 | AZ12: 16.75605 | BA12: 16.85758 | BB12: 16.95647 | BC12: 17.05278 | BD12: 17.14651 | BE12: 17.23769 | BF12: 17.32629 | BG12: 17.41227 | BH12: 17.49561 | BI12: 17.57547 | BJ12: #N/A | BK12: TRUE
A13: Courbe de charge elec | B13: donnée non utilisée mais vérif de cohérence sur cet onglet | C13: demand_elec | D13: Tertiaire | E13: Flexible | F13: Eau chaude sanitaire tertiaire | G13: TWh/an | H13: elccfterecs | I13: bâtiment_démographie_v2.6 | J13: 9.26042 | K13: 8.851 | L13: 8.79514 | M13: 8.80224 | N13: 8.74277 | O13: 8.68158 | P13: 8.6169 | Q13: 8.54716 | R13: 8.46988 | S13: 8.38149 | T13: 8.27729 | U13: 8.15142 | V13: 7.99754 | W13: 7.80983 | X13: 7.58432 | Y13: 7.32049 | Z13: 7.0223 | AA13: 6.69836 | AB13: 6.36071 | AC13: 6.02283 | AD13: 5.69739 | AE13: 5.39455 | AF13: 5.12109 | AG13: 4.88035 | AH13: 4.67279 | AI13: 4.49675 | AJ13: 4.34925 | AK13: 4.22649 | AL13: 4.12442 | AM13: 4.03909 | AN13: 3.96683 | AO13: 3.90441 | AP13: 3.8491 | AQ13: 3.79877 | AR13: 3.75174 | AS13: 3.70681 | AT13: 3.66318 | AU13: 3.62032 | AV13: 3.57792 | AW13: 3.53581 | AX13: 3.49389 | AY13: 3.45216 | AZ13: 3.41061 | BA13: 3.36925 | BB13: 3.32809 | BC13: 3.28716 | BD13: 3.24648 | BE13: 3.20605 | BF13: 3.16588 | BG13: 3.12598 | BH13: 3.08634 | BI13: 3.04682 | BJ13: #N/A | BK13: TRUE
A14: Courbe de charge elec | B14: donnée non utilisée mais vérif de cohérence sur cet onglet | C14: demand_elec | D14: Tertiaire | E14: Base | F14: Cuisson tertiaire | G14: TWh/an | H14: elccftercui | I14: bâtiment_démographie_v2.6 | J14: 5.3257 | K14: 5.4472 | L14: 5.56632 | M14: 5.69366 | N14: 5.81351 | O14: 5.92378 | P14: 6.00527 | Q14: 6.08499 | R14: 6.14619 | S14: 6.19721 | T14: 6.24646 | U14: 6.2772 | V14: 6.24363 | W14: 6.20016 | X14: 6.14704 | Y14: 6.09246 | Z14: 6.02859 | AA14: 5.96347 | AB14: 5.8971 | AC14: 5.82201 | AD14: 5.74594 | AE14: 5.66892 | AF14: 5.58388 | AG14: 5.49826 | AH14: 5.41903 | AI14: 5.33228 | AJ14: 5.24517 | AK14: 5.15771 | AL14: 5.06987 | AM14: 4.98172 | AN14: 4.89329 | AO14: 4.80456 | AP14: 4.80129 | AQ14: 4.79763 | AR14: 4.79356 | AS14: 4.78906 | AT14: 4.78417 | AU14: 4.77893 | AV14: 4.77342 | AW14: 4.76767 | AX14: 4.76175 | AY14: 4.75575 | AZ14: 4.74976 | BA14: 4.74378 | BB14: 4.7379 | BC14: 4.73216 | BD14: 4.72661 | BE14: 4.72128 | BF14: 4.71618 | BG14: 4.71131 | BH14: 4.70668 | BI14: 4.70217 | BJ14: #N/A | BK14: TRUE
A15: Courbe de charge elec | B15: donnée non utilisée mais vérif de cohérence sur cet onglet | C15: demand_elec | D15: Tertiaire | E15: Pro | F15: Final electricity consumption for lighting in the tertiary sector | G15: TWh/an | H15: elccfterlgt | I15: bâtiment_démographie_v2.6 | J15: 14.55733 | K15: 14.05568 | L15: 13.06644 | M15: 12.24169 | N15: 11.44946 | O15: 10.74544 | P15: 10.11489 | Q15: 9.54668 | R15: 9.03183 | S15: 8.56302 | T15: 8.13427 | U15: 7.74052 | V15: 7.33843 | W15: 6.97062 | X15: 6.63278 | Y15: 6.32129 | Z15: 6.03309 | AA15: 5.7656 | AB15: 5.51661 | AC15: 5.2842 | AD15: 5.06674 | AE15: 4.8628 | AF15: 4.82147 | AG15: 4.77966 | AH15: 4.73741 | AI15: 4.69887 | AJ15: 4.6815 | AK15: 4.66343 | AL15: 4.64463 | AM15: 4.62513 | AN15: 4.60494 | AO15: 4.5684 | AP15: 4.55434 | AQ15: 4.53066 | AR15: 4.50631 | AS15: 4.48129 | AT15: 4.45562 | AU15: 4.42932 | AV15: 4.40244 | AW15: 4.37499 | AX15: 4.34702 | AY15: 4.31857 | AZ15: 4.3064 | BA15: 4.29371 | BB15: 4.28051 | BC15: 4.26684 | BD15: 4.25272 | BE15: 4.23814 | BF15: 4.22312 | BG15: 4.20767 | BH15: 4.19177 | BI15: 4.17526 | BJ15: #N/A | BK15: TRUE
A16: Courbe de charge elec | B16: donnée non utilisée mais vérif de cohérence sur cet onglet | C16: demand_elec | D16: Tertiaire | E16: Pro | F16: Final electricity consumption for IT equipment (desktop, laptop, screen) in the tertiary sector | G16: TWh/an | H16: elccfterite | I16: bâtiment_démographie_v2.6 | J16: 8.58105 | K16: 8.33488 | L16: 8.0804 | M16: 7.8811 | N16: 7.65539 | O16: 7.43265 | P16: 7.21237 | Q16: 7.03654 | R16: 6.86511 | S16: 6.69805 | T16: 6.53532 | U16: 6.37684 | V16: 6.22252 | W16: 6.07231 | X16: 5.9261 | Y16: 5.78378 | Z16: 5.64527 | AA16: 5.5614 | AB16: 5.47778 | AC16: 5.3943 | AD16: 5.31092 | AE16: 5.16443 | AF16: 5.06145 | AG16: 4.96024 | AH16: 4.86076 | AI16: 4.78047 | AJ16: 4.70576 | AK16: 4.6312 | AL16: 4.5568 | AM16: 4.48259 | AN16: 4.46583 | AO16: 4.44043 | AP16: 4.42565 | AQ16: 4.40614 | AR16: 4.38605 | AS16: 4.36538 | AT16: 4.34416 | AU16: 4.32754 | AV16: 4.31443 | AW16: 4.3007 | AX16: 4.28639 | AY16: 4.27154 | AZ16: 4.2595 | BA16: 4.24694 | BB16: 4.2339 | BC16: 4.22038 | BD16: 4.2064 | BE16: 4.19199 | BF16: 4.17713 | BG16: 4.16184 | BH16: 4.14612 | BI16: 4.12979 | BJ16: #N/A | BK16: TRUE
A17: Courbe de charge elec | B17: donnée non utilisée mais vérif de cohérence sur cet onglet | C17: demand_elec | D17: Tertiaire | E17: Pro | F17: Final electricity consumption for other office equipment (refrigeration, washing, excl. servers) | G17: TWh/an | H17: elccfterooe | I17: bâtiment_démographie_v2.6 | J17: 3.91339 | K17: 4.00354 | L17: 4.04435 | M17: 4.10336 | N17: 4.16093 | O17: 4.21641 | P17: 4.26951 | Q17: 4.27275 | R17: 4.27143 | S17: 4.26555 | T17: 4.25512 | U17: 4.22469 | V17: 4.19036 | W17: 4.13743 | X17: 4.06693 | Y17: 3.97996 | Z17: 3.87762 | AA17: 3.77433 | AB17: 3.77809 | AC17: 3.78119 | AD17: 3.78362 | AE17: 3.7854 | AF17: 3.78654 | AG17: 3.78704 | AH17: 3.78692 | AI17: 3.78619 | AJ17: 3.78488 | AK17: 3.78297 | AL17: 3.78047 | AM17: 3.77738 | AN17: 3.77371 | AO17: 3.76945 | AP17: 3.76459 | AQ17: 3.75913 | AR17: 3.75307 | AS17: 3.7464 | AT17: 3.73913 | AU17: 3.73129 | AV17: 3.72288 | AW17: 3.71394 | AX17: 3.70448 | AY17: 3.69453 | AZ17: 3.68412 | BA17: 3.67326 | BB17: 3.66197 | BC17: 3.65028 | BD17: 3.63819 | BE17: 3.62572 | BF17: 3.61288 | BG17: 3.59965 | BH17: 3.58605 | BI17: 3.57193 | BJ17: #N/A | BK17: TRUE
A18: Courbe de charge elec | B18: donnée non utilisée mais vérif de cohérence sur cet onglet | C18: demand_elec | D18: Tertiaire | E18: ? | F18: Final electricity consumption for public lighting | G18: TWh/an | H18: elccfterplg | I18: bâtiment_démographie_v2.6 | J18: 4.43896 | K18: 4.2194 | L18: 4.02255 | M18: 3.84507 | N18: 3.63012 | O18: 3.43458 | P18: 3.25595 | Q18: 3.09214 | R18: 2.94141 | S18: 2.80225 | T18: 2.6734 | U18: 2.55377 | V18: 2.44242 | W18: 2.33852 | X18: 2.24137 | Y18: 2.15033 | Z18: 2.06486 | AA18: 2.01181 | AB18: 1.96051 | AC18: 1.91088 | AD18: 1.86283 | AE18: 1.81631 | AF18: 1.77124 | AG18: 1.72756 | AH18: 1.68521 | AI18: 1.64414 | AJ18: 1.60429 | AK18: 1.56562 | AL18: 1.52807 | AM18: 1.4916 | AN18: 1.45617 | AO18: 1.4129 | AP18: 1.38248 | AQ18: 1.34881 | AR18: 1.31608 | AS18: 1.28423 | AT18: 1.25325 | AU18: 1.2231 | AV18: 1.19376 | AW18: 1.16518 | AX18: 1.13736 | AY18: 1.11025 | AZ18: 1.11025 | BA18: 1.11025 | BB18: 1.11025 | BC18: 1.11025 | BD18: 1.11025 | BE18: 1.11025 | BF18: 1.11025 | BG18: 1.11025 | BH18: 1.11025 | BI18: 1.11025 | BJ18: #N/A | BK18: TRUE
A19: Courbe de charge elec | B19: donnée non utilisée mais vérif de cohérence sur cet onglet | C19: demand_elec | D19: Tertiaire | E19: Base | F19: Final electricity consumption for server equipment (enterprise servers and data centers) | G19: TWh/an | H19: elccftersve | I19: bâtiment_démographie_v2.6 | J19: 7.4 | K19: 7.5 | L19: 7.6 | M19: 7.8 | N19: 8 | O19: 8.2 | P19: 9.5 | Q19: 10.8 | R19: 12.1 | S19: 13.4 | T19: 14.7 | U19: 16 | V19: 17.3 | W19: 18.6 | X19: 19.9 | Y19: 21.2 | Z19: 22.5 | AA19: 23.175 | AB19: 23.6385 | AC19: 23.87488 | AD19: 23.87488 | AE19: 23.87488 | AF19: 23.87488 | AG19: 23.87488 | AH19: 23.87488 | AI19: 23.87488 | AJ19: 23.87488 | AK19: 23.87488 | AL19: 23.87488 | AM19: 23.87488 | AN19: 23.87488 | AO19: 23.87488 | AP19: 23.87488 | AQ19: 23.87488 | AR19: 23.87488 | AS19: 23.87488 | AT19: 23.87488 | AU19: 23.87488 | AV19: 23.87488 | AW19: 23.87488 | AX19: 23.87488 | AY19: 23.87488 | AZ19: 23.87488 | BA19: 23.87488 | BB19: 23.87488 | BC19: 23.87488 | BD19: 23.87488 | BE19: 23.87488 | BF19: 23.87488 | BG19: 23.87488 | BH19: 23.87488 | BI19: 23.87488 | BJ19: #N/A | BK19: TRUE
A20: Courbe de charge elec | B20: donnée non utilisée mais vérif de cohérence sur cet onglet | C20: demand_elec | D20: Tertiaire | E20: Base | F20: Final electricity consumption of the telecom network infrastructure (excl. server equipment) | G20: TWh/an | H20: elccftertni | I20: bâtiment_démographie_v2.6 | J20: 3.56222 | K20: 3.57778 | L20: 3.59333 | M20: 3.60889 | N20: 3.62444 | O20: 3.64 | P20: 3.6764 | Q20: 3.71316 | R20: 3.7503 | S20: 3.7878 | T20: 3.82568 | U20: 3.86393 | V20: 3.90257 | W20: 3.9416 | X20: 3.98101 | Y20: 4.02082 | Z20: 4.06103 | AA20: 4.10164 | AB20: 4.14266 | AC20: 4.18409 | AD20: 4.22593 | AE20: 4.26819 | AF20: 4.31087 | AG20: 4.35398 | AH20: 4.39752 | AI20: 4.44149 | AJ20: 4.48591 | AK20: 4.53077 | AL20: 4.57607 | AM20: 4.62183 | AN20: 4.66805 | AO20: 4.71473 | AP20: 4.76188 | AQ20: 4.8095 | AR20: 4.85759 | AS20: 4.90617 | AT20: 4.95523 | AU20: 5.00478 | AV20: 5.05483 | AW20: 5.10538 | AX20: 5.15643 | AY20: 5.208 | AZ20: 5.208 | BA20: 5.208 | BB20: 5.208 | BC20: 5.208 | BD20: 5.208 | BE20: 5.208 | BF20: 5.208 | BG20: 5.208 | BH20: 5.208 | BI20: 5.208 | BJ20: #N/A | BK20: TRUE
A21: Courbe de charge elec | B21: donnée non utilisée mais vérif de cohérence sur cet onglet | C21: demand_elec | D21: Tertiaire | E21: Base | F21: Final electricity consumption for cold production in the tertiary sector | G21: TWh/an | H21: elccftercol | I21: bâtiment_démographie_v2.6 | J21: 7.75556 | K21: 7.63333 | L21: 7.51111 | M21: 7.38889 | N21: 7.26667 | O21: 7.14444 | P21: 7.02222 | Q21: 7.02222 | R21: 7.02222 | S21: 7.02222 | T21: 7.02222 | U21: 7.02222 | V21: 7.02222 | W21: 7.02222 | X21: 7.02222 | Y21: 7.02222 | Z21: 7.02222 | AA21: 7.02222 | AB21: 7.02222 | AC21: 7.02222 | AD21: 7.02222 | AE21: 7.02222 | AF21: 7.02222 | AG21: 7.02222 | AH21: 7.02222 | AI21: 7.02222 | AJ21: 7.02222 | AK21: 7.02222 | AL21: 7.02222 | AM21: 7.02222 | AN21: 7.02222 | AO21: 7.02222 | AP21: 7.02222 | AQ21: 7.02222 | AR21: 7.02222 | AS21: 7.02222 | AT21: 7.02222 | AU21: 7.02222 | AV21: 7.02222 | AW21: 7.02222 | AX21: 7.02222 | AY21: 7.02222 | AZ21: 7.02222 | BA21: 7.02222 | BB21: 7.02222 | BC21: 7.02222 | BD21: 7.02222 | BE21: 7.02222 | BF21: 7.02222 | BG21: 7.02222 | BH21: 7.02222 | BI21: 7.02222 | BJ21: #N/A | BK21: TRUE
A22: Courbe de charge elec | B22: donnée non utilisée mais vérif de cohérence sur cet onglet | C22: demand_elec | D22: Tertiaire | E22: Base | F22: Final electricity consumption for other activities in the tertiary sector | G22: TWh/an | H22: elccfteroth | I22: bâtiment_démographie_v2.6 | J22: 28.93333 | K22: 28.66667 | L22: 28.4 | M22: 28.13333 | N22: 27.86667 | O22: 27.6 | P22: 27.33333 | Q22: 27.06667 | R22: 26.8 | S22: 26.53333 | T22: 26.26667 | U22: 26 | V22: 25.73333 | W22: 25.46667 | X22: 25.2 | Y22: 24.93333 | Z22: 24.66667 | AA22: 24.4 | AB22: 24.13333 | AC22: 23.86667 | AD22: 23.6 | AE22: 23.33333 | AF22: 23.06667 | AG22: 22.8 | AH22: 22.53333 | AI22: 22.26667 | AJ22: 22 | AK22: 21.73333 | AL22: 21.46667 | AM22: 21.2 | AN22: 21 | AO22: 21 | AP22: 21 | AQ22: 21 | AR22: 21 | AS22: 21 | AT22: 21 | AU22: 21 | AV22: 21 | AW22: 21 | AX22: 21 | AY22: 21 | AZ22: 21 | BA22: 21 | BB22: 21 | BC22: 21 | BD22: 21 | BE22: 21 | BF22: 21 | BG22: 21 | BH22: 21 | BI22: 21 | BJ22: #N/A | BK22: TRUE
A23: Courbe de charge elec | B23: donnée non utilisée mais vérif de cohérence sur cet onglet | C23: demand_elec | D23: Tertiaire | E23: Base | F23: Autre élec spécifique tertiaire (ventilation, portes auto, ascenseurs etc.) | G23: TWh/an | H23: elccfterbmg | I23: bâtiment_démographie_v2.6 | J23: 1.27209 | K23: 1.25814 | L23: 1.24419 | M23: 1.23023 | N23: 1.21628 | O23: 1.20233 | P23: 1.18837 | Q23: 1.17442 | R23: 1.16047 | S23: 1.14651 | T23: 1.13256 | U23: 1.1186 | V23: 1.10465 | W23: 1.0907 | X23: 1.07674 | Y23: 1.06279 | Z23: 1.04884 | AA23: 1.03488 | AB23: 1.02093 | AC23: 1.00698 | AD23: 0.99302 | AE23: 0.97907 | AF23: 0.96512 | AG23: 0.95116 | AH23: 0.93721 | AI23: 0.92326 | AJ23: 0.9093 | AK23: 0.89535 | AL23: 0.8814 | AM23: 0.86744 | AN23: 0.85349 | AO23: 0.83953 | AP23: 0.82558 | AQ23: 0.81163 | AR23: 0.79767 | AS23: 0.78372 | AT23: 0.76977 | AU23: 0.75581 | AV23: 0.74186 | AW23: 0.72791 | AX23: 0.71395 | AY23: 0.7 | AZ23: 0.7 | BA23: 0.7 | BB23: 0.7 | BC23: 0.7 | BD23: 0.7 | BE23: 0.7 | BF23: 0.7 | BG23: 0.7 | BH23: 0.7 | BI23: 0.7 | BJ23: #N/A | BK23: TRUE
A24: Courbe de charge elec | B24: donnée nécessitant un traitement dans traitement_nW_EOLES | C24: demand_elec_ter | D24: Tertiaire | F24: TOTAL | G24: TWh/an | H24: elccfter | I24: bâtiment_démographie_v2.6 | J24: 132.26229 | K24: 130.44511 | L24: 130.96653 | M24: 128.37319 | N24: 125.9242 | O24: 124.73346 | P24: 124.71928 | Q24: 124.89231 | R24: 125.10709 | S24: 125.35972 | T24: 125.6437 | U24: 125.90615 | V24: 126.04473 | W24: 126.12381 | X24: 126.11973 | Y24: 126.03112 | Z24: 125.85622 | AA24: 125.08547 | AB24: 124.16555 | AC24: 122.93387 | AD24: 121.45976 | AE24: 119.92399 | AF24: 118.5809 | AG24: 117.23578 | AH24: 115.89638 | AI24: 114.57101 | AJ24: 113.27213 | AK24: 111.97674 | AL24: 110.69165 | AM24: 109.42565 | AN24: 108.31191 | AO24: 107.40139 | AP24: 106.85822 | AQ24: 106.34409 | AR24: 105.87724 | AS24: 105.45646 | AT24: 105.07907 | AU24: 104.74643 | AV24: 104.45298 | AW24: 104.18982 | AX24: 103.95221 | AY24: 103.73578 | AZ24: 103.54489 | BA24: 103.36613 | BB24: 103.19657 | BC24: 103.03379 | BD24: 102.8749 | BE24: 102.71595 | BF24: 102.55892 | BG24: 102.40881 | BH24: 102.28406 | BI24: 102.152
A25: Courbe de charge elec | B25: donnée non utilisée mais vérif de cohérence sur cet onglet | C25: demand_elec | D25: Tertiaire | F25: DELTA TOTAL vs. somme | G25: TWh/an | J25: =J24-SUM(J11:J23) -> 0 | K25: =K24-SUM(K11:K23) -> 0 | L25: =L24-SUM(L11:L23) -> -1e-05 | M25: =M24-SUM(M11:M23) -> -1e-05 | N25: =N24-SUM(N11:N23) -> 0 | O25: =O24-SUM(O11:O23) -> 0 | P25: =P24-SUM(P11:P23) -> 1e-05 | Q25: =Q24-SUM(Q11:Q23) -> 2e-05 | ... BI25: =BI24-SUM(BI11:BI23) -> 1e-05
A27: Courbe de charge elec | B27: donnée non utilisée mais vérif de cohérence sur cet onglet | C27: demand_elec | D27: Mobilité domestique | F27: Mobilité - VP | G27: TWh/an | H27: elccfmobvp | I27: transports_v6.13 | J27: 0.33091 | K27: 0.42852 | L27: 0.80105 | M27: 1.42728 | N27: 1.99158 | O27: 2.84853 | P27: 4.09331 | Q27: 5.1722 | R27: 6.5855 | S27: 8.06723 | T27: 9.78761 | U27: 11.91067 | V27: 14.2006 | W27: 16.37184 | X27: 18.63486 | Y27: 20.8421 | Z27: 23.0201 | AA27: 25.15144 | AB27: 27.44936 | AC27: 29.71927 | AD27: 31.9794 | AE27: 34.24092 | AF27: 36.63668 | AG27: 39.00934 | AH27: 41.27006 | AI27: 43.32919 | AJ27: 45.10003 | AK27: 46.63773 | AL27: 47.86858 | AM27: 48.80693 | AN27: 49.47819 | AO27: 49.67895 | AP27: 49.6764 | AQ27: 49.65556 | AR27: 49.63102 | AS27: 49.60264 | AT27: 49.57077 | AU27: 49.53587 | AV27: 49.49845 | AW27: 49.459 | AX27: 49.41809 | AY27: 49.37652 | AZ27: 49.33507 | BA27: 49.29393 | BB27: 49.25373 | BC27: 49.21503 | BD27: 49.17813 | BE27: 49.14339 | BF27: 49.11086 | BG27: 49.08059 | BH27: 49.05262 | BI27: 49.02316 | BJ27: #N/A | BK27: TRUE
A28: Courbe de charge elec | B28: donnée non utilisée mais vérif de cohérence sur cet onglet | C28: demand_elec | D28: Mobilité domestique | F28: Mobilité - autres (bus, 2RM, vélos, train/metro/tram) | G28: TWh/an | H28: elccfmobautre | I28: transports_v6.13 | J28: 8.70587 | K28: 5.0253 | L28: 6.59833 | M28: 8.93174 | N28: 9.4797 | O28: 10.11228 | P28: 10.43964 | Q28: 10.53455 | R28: 10.63075 | S28: 10.67003 | T28: 10.71177 | U28: 10.76048 | V28: 10.86162 | W28: 11.02246 | X28: 11.32383 | Y28: 11.64611 | Z28: 11.98696 | AA28: 12.34842 | AB28: 12.72236 | AC28: 13.10345 | AD28: 13.48687 | AE28: 13.87792 | AF28: 14.21473 | AG28: 14.53928 | AH28: 14.84961 | AI28: 15.14502 | AJ28: 15.43686 | AK28: 15.71599 | AL28: 15.98431 | AM28: 16.24431 | AN28: 16.49859 | AO28: 16.80042 | AP28: 16.80497 | AQ28: 16.78092 | AR28: 16.75208 | AS28: 16.71814 | AT28: 16.75368 | AU28: 16.6327 | AV28: 16.70825 | AW28: 16.78553 | AX28: 16.86488 | AY28: 16.94679 | AZ28: 16.99115 | BA28: 17.00702 | BB28: 17.02363 | BC28: 17.04103 | BD28: 17.05935 | BE28: 17.07871 | BF28: 17.09917 | BG28: 17.12073 | BH28: 17.14344 | BI28: 17.16583 | BJ28: #N/A | BK28: TRUE
A29: Courbe de charge elec | B29: donnée nécessitant un traitement dans traitement_nW_EOLES | C29: demand_elec_mob | D29: Mobilité domestique | F29: TOTAL | G29: TWh/an | H29: elccfmob | I29: transports_v6.13 | J29: 9.03678 | K29: 5.45382 | L29: 7.39938 | M29: 10.35901 | N29: 11.47128 | O29: 12.96082 | P29: 14.53295 | Q29: 15.70675 | R29: 17.21625 | S29: 18.73726 | T29: 20.49937 | U29: 22.67115 | V29: 25.06221 | W29: 27.3943 | X29: 29.9587 | Y29: 32.4882 | Z29: 35.00706 | AA29: 37.49986 | AB29: 40.17172 | AC29: 42.82273 | AD29: 45.46627 | AE29: 48.11884 | AF29: 50.85142 | AG29: 53.54862 | AH29: 56.11967 | AI29: 58.47421 | AJ29: 60.53689 | AK29: 62.35372 | AL29: 63.85289 | AM29: 65.05123 | AN29: 65.97678 | AO29: 66.47937 | AP29: 66.48137 | AQ29: 66.43648 | AR29: 66.3831 | AS29: 66.32078 | AT29: 66.32445 | AU29: 66.16857 | AV29: 66.2067 | AW29: 66.24452 | AX29: 66.28297 | AY29: 66.32331 | AZ29: 66.32622 | BA29: 66.30095 | BB29: 66.27736 | BC29: 66.25606 | BD29: 66.23748 | BE29: 66.22211 | BF29: 66.21002 | BG29: 66.20132 | BH29: 66.19606 | BI29: 66.18899 | BJ29: Consommation finale d'électricité liée à la mobilité des passagers
A30: Courbe de charge elec | B30: donnée non utilisée mais vérif de cohérence sur cet onglet | C30: demand_elec | D30: Mobilité domestique | F30: DELTA TOTAL vs. somme | G30: TWh/an | J30: =J29-SUM(J27:J28) -> 0 | K30: =K29-SUM(K27:K28) -> 0 | L30: =L29-SUM(L27:L28) -> 0 | M30: =M29-SUM(M27:M28) -> -1e-05 | N30: =N29-SUM(N27:N28) -> 0 | O30: =O29-SUM(O27:O28) -> 1e-05 | P30: =P29-SUM(P27:P28) -> 0 | Q30: =Q29-SUM(Q27:Q28) -> 0 | ... BI30: =BI29-SUM(BI27:BI28) -> 0
A32: Courbe de charge elec | B32: donnée non utilisée mais vérif de cohérence sur cet onglet | C32: demand_elec | D32: Fret domestique | F32: Fret - VUL | G32: TWh/an | H32: elccffrevul | I32: transports_v6.13 | J32: 0.15168 | K32: 0.15521 | L32: 0.20528 | M32: 0.24436 | N32: 0.30068 | O32: 0.4019 | P32: 0.74608 | Q32: 0.96025 | R32: 1.27948 | S32: 1.79065 | T32: 2.53908 | U32: 3.5019 | V32: 4.66792 | W32: 6.00502 | X32: 7.51452 | Y32: 9.15558 | Z32: 10.90089 | AA32: 12.69927 | AB32: 14.49647 | AC32: 16.23754 | AD32: 17.90587 | AE32: 19.48413 | AF32: 20.95375 | AG32: 22.29544 | AH32: 23.49163 | AI32: 24.52919 | AJ32: 25.40202 | AK32: 26.11208 | AL32: 26.66886 | AM32: 27.08807 | AN32: 27.38971 | AO32: 27.59603 | AP32: 27.72931 | AQ32: 27.81017 | AR32: 27.85593 | AS32: 27.87995 | AT32: 27.89158 | AU32: 27.89676 | AV32: 27.89885 | AW32: 27.89964 | AX32: 27.89989 | AY32: 27.89997 | AZ32: 27.9 | BA32: 27.9 | BB32: 27.9 | BC32: 27.9 | BD32: 27.9 | BE32: 27.9 | BF32: 27.9 | BG32: 27.9 | BH32: 27.9 | BI32: 27.9 | BJ32: #N/A | BK32: TRUE
A33: Courbe de charge elec | B33: donnée non utilisée mais vérif de cohérence sur cet onglet | C33: demand_elec | D33: Fret domestique | F33: Fret - PL (FR et étrangers) | G33: TWh/an | H33: elccffrepl | I33: transports_v6.13 | J33: 0.01518 | K33: 0.0131 | L33: 0.0158 | M33: 0.01674 | N33: 0.01659 | O33: 0.0627 | P33: 0.34061 | Q33: 0.42522 | R33: 0.53585 | S33: 0.68543 | T33: 0.88475 | U33: 1.15024 | V33: 1.47251 | W33: 1.83732 | X33: 2.40103 | Y33: 3.08007 | Z33: 3.92107 | AA33: 4.91903 | AB33: 5.995 | AC33: 7.12954 | AD33: 8.32036 | AE33: 9.56645 | AF33: 10.90376 | AG33: 12.30166 | AH33: 13.71185 | AI33: 15.04574 | AJ33: 16.19688 | AK33: 17.13563 | AL33: 17.7782 | AM33: 18.15199 | AN33: 18.31392 | AO33: 18.32482 | AP33: 18.26522 | AQ33: 18.20407 | AR33: 18.14139 | AS33: 18.07719 | AT33: 18.01148 | AU33: 17.90103 | AV33: 17.78938 | AW33: 17.67655 | AX33: 17.5626 | AY33: 17.44754 | AZ33: 17.46454 | BA33: 17.48076 | BB33: 17.4962 | BC33: 17.51089 | BD33: 17.52485 | BE33: 17.48694 | BF33: 17.44914 | BG33: 17.41143 | BH33: 17.37383 | BI33: 17.33632 | BJ33: #N/A | BK33: TRUE
A34: Courbe de charge elec | B34: donnée non utilisée mais vérif de cohérence sur cet onglet | C34: demand_elec | D34: Fret domestique | F34: Fret - ferroviaire | G34: TWh/an | H34: elccffrefer | I34: transports_v6.13 | J34: 1.09838 | K34: 1.01328 | L34: 1.15731 | M34: 1.14042 | N34: 0.98004 | O34: 1.05085 | P34: 1.05833 | Q34: 1.05622 | R34: 1.05256 | S34: 1.11198 | T34: 1.14794 | U34: 1.18187 | V34: 1.21552 | W34: 1.2474 | X34: 1.27769 | Y34: 1.30661 | Z34: 1.33442 | AA34: 1.36141 | AB34: 1.38786 | AC34: 1.41402 | AD34: 1.44008 | AE34: 1.4662 | AF34: 1.496 | AG34: 1.52612 | AH34: 1.55652 | AI34: 1.58713 | AJ34: 1.61786 | AK34: 1.6486 | AL34: 1.67925 | AM34: 1.70971 | AN34: 1.73992 | AO34: 1.7693 | AP34: 1.80679 | AQ34: 1.84413 | AR34: 1.88133 | AS34: 1.91838 | AT34: 1.95418 | AU34: 1.98356 | AV34: 2.01243 | AW34: 2.04062 | AX34: 2.06793 | AY34: 2.0941 | AZ34: 2.08583 | BA34: 2.07612 | BB34: 2.06475 | BC34: 2.0515 | BD34: 2.03625 | BE34: 2.01894 | BF34: 1.99967 | BG34: 1.97862 | BH34: 1.95612 | BI34: 1.93262 | BJ34: #N/A | BK34: TRUE
A35: Courbe de charge elec | B35: donnée nécessitant un traitement dans traitement_nW_EOLES | C35: demand_elec_fret | D35: Fret domestique | F35: TOTAL | G35: TWh/an | H35: elccffre | I35: transports_v6.13 | J35: 1.26524 | K35: 1.18159 | L35: 1.37839 | M35: 1.40152 | N35: 1.29731 | O35: 1.51545 | P35: 2.14502 | Q35: 2.4417 | R35: 2.86789 | S35: 3.58807 | T35: 4.57177 | U35: 5.83401 | V35: 7.35594 | W35: 9.08974 | X35: 11.19324 | Y35: 13.54226 | Z35: 16.15638 | AA35: 18.97972 | AB35: 21.87932 | AC35: 24.7811 | AD35: 27.66631 | AE35: 30.51678 | AF35: 33.35351 | AG35: 36.12322 | AH35: 38.75999 | AI35: 41.16207 | AJ35: 43.21676 | AK35: 44.89631 | AL35: 46.12631 | AM35: 46.94977 | AN35: 47.44354 | AO35: 47.69015 | AP35: 47.80131 | AQ35: 47.85837 | AR35: 47.87864 | AS35: 47.87552 | AT35: 47.85724 | AU35: 47.78134 | AV35: 47.70066 | AW35: 47.61681 | AX35: 47.53042 | AY35: 47.44162 | AZ35: 47.45037 | BA35: 47.45688 | BB35: 47.46095 | BC35: 47.46239 | BD35: 47.46109 | BE35: 47.40588 | BF35: 47.3488 | BG35: 47.29005 | BH35: 47.22995 | BI35: 47.16894 | BJ35: Consommation finale d'électricité dans le transport de marchandises
A36: Courbe de charge elec | B36: donnée non utilisée mais vérif de cohérence sur cet onglet | C36: demand_elec | D36: Fret domestique | F36: DELTA TOTAL vs. somme | G36: TWh/an | J36: =J35-SUM(J32:J34) -> 0 | K36: =K35-SUM(K32:K34) -> 0 | L36: =L35-SUM(L32:L34) -> 0 | M36: =M35-SUM(M32:M34) -> 0 | N36: =N35-SUM(N32:N34) -> 0 | O36: =O35-SUM(O32:O34) -> 0 | P36: =P35-SUM(P32:P34) -> 0 | Q36: =Q35-SUM(Q32:Q34) -> 1e-05 | ... BI36: =BI35-SUM(BI32:BI34) -> 0
A38: Courbe de charge elec | B38: donnée nécessitant un traitement dans traitement_nW_EOLES | C38: demand_elec_agr | D38: Agriculture | F38: Conso d'élec de l'agriculture | G38: TWh/an | H38: elccfagr | I38: agriculture_v5 | J38: 8.47942 | K38: 8.07949 | L38: 7.64995 | M38: 7.88962 | N38: 7.14746 | O38: 7.14746 | P38: 7.89465 | Q38: 8.01921 | R38: 8.16312 | S38: 8.32483 | T38: 8.50255 | U38: 8.69435 | V38: 8.89811 | W38: 9.11161 | X38: 9.3325 | Y38: 9.55838 | Z38: 9.78675 | AA38: 10.01512 | AB38: 10.241 | AC38: 10.46189 | AD38: 10.67539 | AE38: 10.87915 | AF38: 11.07094 | AG38: 11.24867 | AH38: 11.41037 | AI38: 11.55429 | AJ38: 11.67884 | AK38: 11.78267 | AL38: 11.86462 | AM38: 11.92381 | AN38: 11.95958 | AO38: 11.97155 | AP38: 11.97454 | AQ38: 11.98343 | AR38: 11.99801 | AS38: 12.01791 | AT38: 12.04265 | AU38: 12.07162 | AV38: 12.1041 | AW38: 12.13929 | AX38: 12.17633 | AY38: 12.21431 | AZ38: 12.25228 | BA38: 12.28932 | BB38: 12.32452 | BC38: 12.357 | BD38: 12.38596 | BE38: 12.4107 | BF38: 12.43061 | BG38: 12.44518 | BH38: 12.45408 | BI38: 12.45706 | BJ38: #N/A | BK38: TRUE
A39: Courbe de charge elec | B39: donnée nécessitant un traitement dans traitement_nW_EOLES | C39: demand_elec_ind | D39: Industrie manufacturière | E39: Pro | F39: Conso d'élec de l'industrie | G39: TWh/an | H39: elccfind | I39: industrie | J39: 111.6186 | K39: 101.63997 | L39: 107.66192 | M39: 104.69555 | N39: 102.81144 | O39: 101.68124 | P39: 102.20269 | Q39: 103.11652 | R39: 104.56324 | S39: 106.34312 | T39: 108.05253 | U39: 109.46302 | V39: 110.74475 | W39: 111.86779 | X39: 112.92387 | Y39: 113.99316 | Z39: 114.07532 | AA39: 114.69562 | AB39: 115.34976 | AC39: 115.68589 | AD39: 115.82046 | AE39: 112.69467 | AF39: 113.26553 | AG39: 113.36708 | AH39: 114.39086 | AI39: 114.52518 | AJ39: 115.20246 | AK39: 115.6797 | AL39: 116.23297 | AM39: 116.65812 | AN39: 116.71588 | AO39: 116.83425 | AP39: 116.24859 | AQ39: 115.87599 | AR39: 114.84787 | AS39: 114.6957 | AT39: 114.60027 | AU39: 114.09647 | AV39: 113.83748 | AW39: 114.01311 | AX39: 114.10024 | AY39: 113.93828 | AZ39: 114.53557 | BA39: 114.11485 | BB39: 114.22638 | BC39: 113.15087 | BD39: 113.63445 | BE39: 112.95177 | BF39: 112.96351 | BG39: 112.27905 | BH39: 112.59247 | BI39: 112.07422 | BJ39: Électricité | BK39: TRUE
A40: Courbe de charge elec | B40: donnée non utilisée mais vérif de cohérence avec sorties | C40: demand_elec | D40: Electrolyse | F40: Conso d'élec pour production H2 | G40: TWh/an | H40: sec_uses.elc_se.hyd_se | I40: SEPIA | J40: 0 | K40: 0 | L40: 0 | M40: 0 | N40: 0 | O40: 0 | P40: 0 | Q40: 1.5384 | R40: 3.1536 | S40: 4.7304 | T40: 6.3072 | U40: 7.884 | V40: 10.3368 | W40: 12.7021 | X40: 14.9796 | Y40: 17.1697 | Z40: 19.2719 | AA40: 24.5979 | AB40: 29.7138 | AC40: 34.6197 | AD40: 39.3151 | AE40: 43.8002 | AF40: 49.792 | AG40: 55.5035 | AH40: 60.9341 | AI40: 66.085 | AJ40: 70.9559 | AK40: 77.8594 | AL40: 84.3766 | AM40: 90.5087 | AN40: 96.2544 | AO40: 101.6156 | AP40: 102.6677 | AQ40: 103.7185 | AR40: 104.7692 | AS40: 105.8214 | AT40: 106.872 | AU40: 107.9236 | AV40: 108.9749 | AW40: 110.0259 | AX40: 111.0763 | AY40: 112.1276 | AZ40: 112.8291 | BA40: 113.5293 | BB40: 114.2305 | BC40: 114.9313 | BD40: 115.6321 | BE40: 116.3323 | BF40: 117.033 | BG40: 117.7347 | BH40: 118.4344 | BI40: 119.1367 | BJ40: #N/A | BK40: TRUE
A41: Courbe de charge elec | B41: donnée nécessitant un traitement dans traitement_nW_EOLES | C41: demand_elec_neth | D41: Branche énergie de l'industrie | F41: Conso d'élec pour réseaux de chaleur (PAC, P2H...) | G41: TWh/an | H41: sec_uses.elc_se.vap_se | I41: SEPIA | J41: 0.2532 | K41: 0.2532 | L41: 0.3391 | M41: 0.5017 | N41: 0.5696 | O41: 0.6442 | P41: 0.7189 | Q41: 0.7223 | R41: 0.7252 | S41: 0.7276 | T41: 0.7296 | U41: 0.75 | V41: 0.9284 | W41: 1.1446 | X41: 1.3998 | Y41: 1.7188 | Z41: 2.0313 | AA41: 2.2759 | AB41: 2.4944 | AC41: 2.7109 | AD41: 2.8543 | AE41: 2.9212 | AF41: 2.9879 | AG41: 3.0545 | AH41: 3.1212 | AI41: 3.1879 | AJ41: 3.2545 | AK41: 3.2545 | AL41: 3.2545 | AM41: 3.2545 | AN41: 3.2545 | AO41: 3.2545 | AP41: 3.2545 | AQ41: 3.2545 | AR41: 3.2545 | AS41: 3.2545 | AT41: 3.2545 | AU41: 3.2545 | AV41: 3.2545 | AW41: 3.2545 | AX41: 3.2545 | AY41: 3.2545 | AZ41: 3.2545 | BA41: 3.2545 | BB41: 3.2545 | BC41: 3.2545 | BD41: 3.2545 | BE41: 3.2545 | BF41: 3.2545 | BG41: 3.2545 | BH41: 3.2545 | BI41: 3.2545 | BJ41: #N/A | BK41: TRUE
A42: Courbe de charge elec | B42: donnée nécessitant un traitement dans traitement_nW_EOLES | C42: demand_elec_other | D42: Branche énergie de l'industrie | F42: Autre conso d'élec de la branche énergie (raffineries…) | G42: TWh/an | H42: sec_uses.elc_se.ens | I42: SEPIA | J42: 9.4734 | K42: 8.2468 | L42: 8.5828 | M42: 9.1784 | N42: 9.1257 | O42: 9.0529 | P42: 9.3541 | Q42: 9.7113 | R42: 10.1042 | S42: 10.4642 | T42: 10.8655 | U42: 11.4625 | V42: 12.0109 | W42: 12.5895 | X42: 13.2082 | Y42: 13.8502 | Z42: 14.4703 | AA42: 15.0957 | AB42: 15.7211 | AC42: 16.3252 | AD42: 16.8922 | AE42: 17.3968 | AF42: 17.9083 | AG42: 18.3949 | AH42: 18.8579 | AI42: 19.3463 | AJ42: 19.759 | AK42: 20.174 | AL42: 20.6698 | AM42: 21.1644 | AN42: 21.6228 | AO42: 22.0575 | AP42: 21.8699 | AQ42: 21.6802 | AR42: 21.4882 | AS42: 21.3759 | AT42: 21.1796 | AU42: 21.1412 | AV42: 21.1098 | AW42: 21.0755 | AX42: 20.9899 | AY42: 20.9709 | AZ42: 20.969 | BA42: 20.9655 | BB42: 20.9626 | BC42: 20.9633 | BD42: 20.9613 | BE42: 20.9589 | BF42: 20.9573 | BG42: 20.9544 | BH42: 20.9502 | BI42: 20.9477 | BJ42: #N/A | BK42: TRUE
A43: Courbe de charge elec | B43: donnée non utilisée mais vérif de cohérence avec sorties | C43: demand_elec | D43: Pertes | F43: Pertes liées au stockage (batteries, STEP) | G43: TWh/an | H43: sec_uses.elc_se.sto_se | I43: SEPIA | J43: 1.795 | K43: 1.7554 | L43: 1.6373 | M43: 1.9913 | N43: 1.6212 | O43: 2.065 | P43: 2.065 | Q43: 2.065 | R43: 2.065 | S43: 2.065 | T43: 2.065 | U43: 2.065 | V43: 2.065 | W43: 2.065 | X43: 2.065 | Y43: 2.065 | Z43: 2.065 | AA43: 2.065 | AB43: 2.065 | AC43: 2.065 | AD43: 2.065 | AE43: 2.065 | AF43: 2.065 | AG43: 2.065 | AH43: 2.065 | AI43: 2.065 | AJ43: 2.065 | AK43: 2.065 | AL43: 2.065 | AM43: 2.065 | AN43: 2.065 | AO43: 2.065 | AP43: 2.065 | AQ43: 2.065 | AR43: 2.065 | AS43: 2.065 | AT43: 2.065 | AU43: 2.065 | AV43: 2.065 | AW43: 2.065 | AX43: 2.065 | AY43: 2.065 | AZ43: 2.065 | BA43: 2.065 | BB43: 2.065 | BC43: 2.065 | BD43: 2.065 | BE43: 2.065 | BF43: 2.065 | BG43: 2.065 | BH43: 2.065 | BI43: 2.065 | BJ43: #N/A | BK43: TRUE
A44: Courbe de charge elec | B44: donnée non utilisée mais vérif de cohérence avec sorties | C44: demand_elec | D44: Excédents | F44: Excédents | G44: TWh/an | H44: sec_uses.elc_se.exp | I44: SEPIA | J44: 63.682 | K44: 51.3818 | L44: 63.5099 | M44: 0 | N44: 54.2261 | O44: 99.2347 | P44: 108.7035 | Q44: 114.2355 | R44: 107.1213 | S44: 105.6057 | T44: 119.3642 | U44: 98.1384 | V44: 81.8314 | W44: 95.5186 | X44: 86.2619 | Y44: 78.164 | Z44: 75.2403 | AA44: 74.8837 | AB44: 71.5464 | AC44: 71.245 | AD44: 92.6629 | AE44: 88.577 | AF44: 80.0542 | AG44: 70.3994 | AH44: 43.415 | AI44: 51.3645 | AJ44: 59.4076 | AK44: 51.9256 | AL44: 59.2221 | AM44: 44.0117 | AN44: 52.9166 | AO44: 40.4532 | AP44: 52.5081 | AQ44: 61.6219 | AR44: 45.6705 | AS44: 56.6618 | AT44: 64.0294 | AU44: 67.6545 | AV44: 64.5227 | AW44: 56.6648 | AX44: 61.1764 | AY44: 58.3952 | AZ44: 69.0732 | BA44: 79.285 | BB44: 72.378 | BC44: 74.9072 | BD44: 84.8105 | BE44: 88.4367 | BF44: 91.2742 | BG44: 93.9498 | BH44: 95.391 | BI44: 97.0218 | BJ44: #N/A | BK44: TRUE
A45: Courbe de charge elec | B45: donnée nécessitant un traitement dans traitement_nW_EOLES | C45: demand_elec_losses | D45: Pertes | F45: Pertes réseau (transport & distribution) | G45: TWh/an | H45: sec_uses.elc_se.per_ntw | I45: SEPIA | J45: 37.8639 | K45: 35.0984 | L45: 38.1994 | M45: 34.419 | N45: 36.517 | O45: 36.9621 | P45: 37.0951 | Q45: 37.1525 | R45: 37.3262 | S45: 37.558 | T45: 37.8453 | U45: 38.1799 | V45: 38.551 | W45: 38.9156 | X45: 39.3129 | Y45: 39.7234 | Z45: 40.0506 | AA45: 40.382 | AB45: 40.7126 | AC45: 40.9699 | AD45: 41.1675 | AE45: 41.0471 | AF45: 41.2742 | AG45: 41.4448 | AH45: 41.6706 | AI45: 41.7839 | AJ45: 41.8505 | AK45: 41.8434 | AL45: 41.7772 | AM45: 41.6471 | AN45: 41.4511 | AO45: 41.2226 | AP45: 41.0231 | AQ45: 40.8455 | AR45: 40.6205 | AS45: 40.4861 | AT45: 40.3815 | AU45: 40.2502 | AV45: 40.1599 | AW45: 40.1108 | AX45: 40.0527 | AY45: 39.9809 | AZ45: 40.0153 | BA45: 39.9601 | BB45: 39.9523 | BC45: 39.8425 | BD45: 39.8694 | BE45: 39.7772 | BF45: 39.7467 | BG45: 39.6576 | BH45: 39.659 | BI45: 39.588 | BJ45: #N/A | BK45: TRUE
A47: Courbe de charge elec | B47: donnée non utilisée mais vérif de cohérence avec sorties | C47: demand_elec | F47: TOTAL | G47: TWh/an | H47: sec_uses.elc_se.total | I47: SEPIA | J47: 535.606 | K47: 499.314 | L47: 522.4551 | M47: 448.7313 | N47: 495.7138 | O47: 538.3669 | P47: 550.5346 | Q47: 559.3532 | R47: 556.9529 | S47: 560.7208 | T47: 580.4255 | U47: 565.7272 | V47: 557.4092 | W47: 578.9829 | X47: 577.9975 | Y47: 578.3309 | Z47: 582.7614 | AA47: 593.0029 | AB47: 600.0682 | AC47: 609.1046 | AD47: 638.8786 | AE47: 638.9977 | AF47: 640.5315 | AG47: 639.9324 | AH47: 622.4334 | AI47: 638.2398 | AJ47: 653.3165 | AK47: 653.9497 | AL47: 668.2671 | AM47: 658.917 | AN47: 672.4864 | AO47: 663.9046 | AP47: 674.5028 | AQ47: 682.4343 | AR47: 664.709 | AS47: 675.0673 | AT47: 682.17 | AU47: 685.1957 | AV47: 681.9774 | AW47: 674.5506 | AX47: 679.3781 | AY47: 676.7462 | AZ47: 688.5541 | BA47: 698.7716 | BB47: 692.4662 | BC47: 694.3245 | BD47: 705.2622 | BE47: 708.4343 | BF47: 711.5899 | BG47: 713.8501 | BH47: 716.0037 | BI47: 717.4475 | BJ47: #N/A
A48: Courbe de charge elec | B48: donnée non utilisée mais vérif de cohérence sur cet onglet | C48: demand_elec | F48: DELTA TOTAL vs. somme | G48: TWh/an | J48: =J47-SUMIF($BK$2:$BK$45,TRUE,J$2:J$45) -> -1e-05 | K48: =K47-SUMIF($BK$2:$BK$45,TRUE,K$2:K$45) -> -1e-05 | L48: =L47-SUMIF($BK$2:$BK$45,TRUE,L$2:L$45) -> -0.00011 | M48: =M47-SUMIF($BK$2:$BK$45,TRUE,M$2:M$45) -> -3e-05 | N48: =N47-SUMIF($BK$2:$BK$45,TRUE,N$2:N$45) -> 4e-05 | O48: =O47-SUMIF($BK$2:$BK$45,TRUE,O$2:O$45) -> 8e-05 | P48: =P47-SUMIF($BK$2:$BK$45,TRUE,P$2:P$45) -> 4e-05 | Q48: =Q47-SUMIF($BK$2:$BK$45,TRUE,Q$2:Q$45) -> 0.00016 | ... BI48: =BI47-SUMIF($BK$2:$BK$45,TRUE,BI$2:BI$45) -> 0.00015
A50: Capacites | B50: donnée non utilisée | C50: max_cap_nuclear | D50: Nucléaire | F50: ="Capacité installée " & LOWER(D50) -> Capacité installée nucléaire | G50: GW | H50: cainuc | I50: nucléaire_v4.1 | J50: 63.13 | K50: 61.4 | L50: 61.4 | M50: 61.4 | N50: 61.4 | O50: 63 | P50: 62.64 | Q50: 62.64 | R50: 62.64 | S50: 62.64 | T50: 62.64 | U50: 61.725 | V50: 58.99 | W50: 55.39 | X50: 54.48 | Y50: 52.66 | Z50: 51.745 | AA50: 49.035 | AB50: 49.035 | AC50: 48.125 | AD50: 45.43 | AE50: 40.935 | AF50: 38.285 | AG50: 35.175 | AH50: 31.63 | AI50: 30.33 | AJ50: 27.685 | AK50: 26.375 | AL50: 22.805 | AM50: 20.145 | AN50: 18.835 | AO50: 17.525 | AP50: 15.32 | AQ50: 12.66 | AR50: 10.05 | AS50: 8.72 | AT50: 7.41 | AU50: 7.41 | AV50: 7.41 | AW50: 7.41 | AX50: 7.41 | AY50: 5.955 | AZ50: 4.5 | BA50: 3.05 | BB50: 1.6 | BC50: 1.6 | BD50: 1.6 | BE50: 1.6 | BF50: 1.6 | BG50: 1.6 | BH50: 1.6 | BI50: 1.6 | BJ50: #N/A
A51: Capacites | B51: donnée utilisée directement dans les feuilles suivantes | C51: max_cap_pv_ground | D51: Solaire | F51: Capacité installée solaire utility-scale | G51: GW | H51: caispv_ground | I51: PV_v4.2 | J51: 4.91204 | K51: 5.22603 | L51: 6.75042 | M51: 7.80221 | N51: 8.74691 | O51: 10.6351 | P51: 12.65555 | Q51: 14.55555 | R51: 16.45555 | S51: 18.35555 | T51: 20.25555 | U51: 22.15555 | V51: 24.05663 | W51: 25.96073 | X51: 27.86944 | Y51: 29.78401 | Z51: 31.70536 | AA51: 33.63405 | AB51: 35.57032 | AC51: 37.51404 | AD51: 39.46476 | AE51: 41.42169 | AF51: 43.38368 | AG51: 45.34926 | AH51: 47.31661 | AI51: 49.28355 | AJ51: 51.2476 | AK51: 53.20589 | AL51: 55.15525 | AM51: 57.09214 | AN51: 59.01269 | AO51: 60.91269 | AP51: 62.74104 | AQ51: 64.4143 | AR51: 65.87042 | AS51: 67.06883 | AT51: 67.99037 | AU51: 68.63731 | AV51: 69.03336 | AW51: 69.22368 | AX51: 69.27483 | AY51: 69.27483 | AZ51: 69.27483 | BA51: 69.27483 | BB51: 69.27483 | BC51: 69.27483 | BD51: 69.27483 | BE51: 69.27483 | BF51: 69.27483 | BG51: 69.27483 | BH51: 69.27483 | BI51: 69.27483
A52: Capacites | B52: donnée utilisée directement dans les feuilles suivantes | C52: max_cap_pv_roof_com | D52: Solaire | F52: Capacité installée solaire grandes toitures | G52: GW | H52: caispv_roof_com | I52: PV_v4.2 | J52: 3.01785 | K52: 3.46815 | L52: 4.428 | M52: 5.31 | N52: 6.6612 | O52: 9.49925 | P52: 13.05325 | Q52: 16.39325 | R52: 19.45082 | S52: 22.22392 | T52: 24.76726 | U52: 27.19226 | V52: 29.57571 | W52: 31.92167 | X52: 34.23378 | Y52: 36.51528 | Z52: 38.76899 | AA52: 40.99735 | AB52: 43.20236 | AC52: 45.38565 | AD52: 47.5484 | AE52: 49.69142 | AF52: 51.81511 | AG52: 53.91943 | AH52: 56.00397 | AI52: 58.06789 | AJ52: 60.10996 | AK52: 62.12853 | AL52: 64.12156 | AM52: 66.08657 | AN52: 68.02072 | AO52: 69.92072 | AP52: 71.78191 | AQ52: 73.59867 | AR52: 75.36562 | AS52: 77.07764 | AT52: 78.72983 | AU52: 80.31755 | AV52: 81.8364 | AW52: 83.28225 | AX52: 84.65116 | AY52: 85.9395 | AZ52: 87.14383 | BA52: 88.26099 | BB52: 89.28805 | BC52: 90.22234 | BD52: 91.0614 | BE52: 91.80305 | BF52: 92.44535 | BG52: 92.98659 | BH52: 93.42532 | BI52: 93.76032
A53: Capacites | B53: donnée utilisée directement dans les feuilles suivantes | C53: max_cap_pv_roof_indiv | D53: Solaire | F53: Capacité installée solaire petites toitures | G53: GW | H53: caispv_roof_indiv | I53: PV_v4.2 | J53: 1.7974 | K53: 1.95225 | L53: 2.20115 | M53: 2.5935 | N53: 3.44375 | O53: 4.69965 | P53: 5.6582 | Q53: 6.3582 | R53: 7.21929 | S53: 8.24304 | T53: 9.39257 | U53: 10.59257 | V53: 11.79184 | W53: 12.98894 | X53: 14.18252 | Y53: 15.37132 | Z53: 16.55414 | AA53: 17.72984 | AB53: 18.89738 | AC53: 20.05577 | AD53: 21.20414 | AE53: 22.34164 | AF53: 23.46753 | AG53: 24.58113 | AH53: 25.68184 | AI53: 26.76914 | AJ53: 27.84258 | AK53: 28.90178 | AL53: 29.94644 | AM53: 30.97634 | AN53: 31.99132 | AO53: 32.99132 | AP53: 33.97534 | AQ53: 34.94144 | AR53: 35.88777 | AS53: 36.81257 | AT53: 37.71414 | AU53: 38.59084 | AV53: 39.44112 | AW53: 40.26352 | AX53: 41.05664 | AY53: 41.81914 | AZ53: 42.54977 | BA53: 43.24737 | BB53: 43.91084 | BC53: 44.53914 | BD53: 45.13132 | BE53: 45.68652 | BF53: 46.20394 | BG53: 46.68284 | BH53: 47.12257 | BI53: 47.52257
A54: Capacites | B54: donnée utilisée directement dans les feuilles suivantes | C54: max_cap_onshore | D54: Eolien onshore | F54: ="Capacité installée " & LOWER(D54) -> Capacité installée eolien onshore | G54: GW | H54: caieon | I54: éolien_v3.3 | J54: 16.511 | K54: 17.616 | L54: 18.75781 | M54: 20.86048 | N54: 22.25248 | O54: 23.58715 | P54: 25.10715 | Q54: 26.56999 | R54: 28.03488 | S54: 29.68713 | T54: 31.53771 | U54: 33.40939 | V54: 35.43225 | W54: 37.56846 | X54: 39.71378 | Y54: 41.90931 | Z54: 44.14755 | AA54: 46.418 | AB54: 48.71836 | AC54: 51.04572 | AD54: 53.39535 | AE54: 55.57934 | AF54: 57.63303 | AG54: 59.65909 | AH54: 61.63829 | AI54: 63.55358 | AJ54: 65.34341 | AK54: 67.06786 | AL54: 68.69216 | AM54: 70.30087 | AN54: 71.6765 | AO54: 72.96889 | AP54: 74.11528 | AQ54: 75.19178 | AR54: 76.07342 | AS54: 76.90289 | AT54: 77.69866 | AU54: 78.39624 | AV54: 79.04572 | AW54: 79.63718 | AX54: 80.17674 | AY54: 80.65538 | AZ54: 81.08987 | BA54: 81.44893 | BB54: 81.72371 | BC54: 81.92578 | BD54: 82.05753 | BE54: 82.12378 | BF54: 82.11402 | BG54: 82.06832 | BH54: 81.98063 | BI54: 81.84756 | BJ54: Capacité éolienne terrestre installée
A55: Capacites | B55: donnée utilisée directement dans les feuilles suivantes | C55: max_cap_offshore_float | D55: Eolien offshore | F55: Capacité installée éolien flottant | G55: GW | H55: caieof_float | I55: éolien_v3.3 | J55: 0 | K55: 0 | L55: 0.002 | M55: 0.0083 | N55: 0.02342 | O55: 0.0272 | P55: 0.0632 | Q55: 0.0872 | R55: 0.0872 | S55: 0.0872 | T55: 0.0872 | U55: 0.0872 | V55: 0.2372 | W55: 0.9372 | X55: 1.6372 | Y55: 2.7972 | Z55: 4.9372 | AA55: 6.6572 | AB55: 9.2372 | AC55: 10.6372 | AD55: 12.7372 | AE55: 14.1372 | AF55: 15.6372 | AG55: 16.6372 | AH55: 18.1372 | AI55: 19.1372 | AJ55: 20.6372 | AK55: 21.6372 | AL55: 22.84038 | AM55: 23.64931 | AN55: 24.8685 | AO55: 25.67147 | AP55: 26.89547 | AQ55: 27.73147 | AR55: 27.73147 | AS55: 27.73147 | AT55: 27.73147 | AU55: 27.73147 | AV55: 27.84617 | AW55: 28.31284 | AX55: 28.7181 | AY55: 29.2981 | AZ55: 30.21525 | BA55: 30.88414 | BB55: 31.79062 | BC55: 32.23273 | BD55: 32.82503 | BE55: 33.17503 | BF55: 33.5043 | BG55: 33.69478 | BH55: 33.93897 | BI55: 34.07533
A56: Capacites | B56: donnée utilisée directement dans les feuilles suivantes | C56: max_cap_offshore_ground | D56: Eolien offshore | F56: Capacité installée éolien posé | G56: GW | H56: caieof_ground | I56: éolien_v3.3 | J56: 0 | K56: 0 | L56: 0 | M56: 0.5794 | N56: 0.8279 | O56: 1.3242 | P56: 1.884 | Q56: 2.2746 | R56: 2.7562 | S56: 2.905 | T56: 3.325 | U56: 3.505 | V56: 4.205 | W56: 4.505 | X56: 5.255 | Y56: 6.705 | Z56: 7.705 | AA56: 8.705 | AB56: 9.705 | AC56: 11.205 | AD56: 12.005 | AE56: 13.205 | AF56: 14.005 | AG56: 14.505 | AH56: 15.33332 | AI56: 16.06362 | AJ56: 16.95052 | AK56: 17.17764 | AL56: 17.53993 | AM56: 17.84519 | AN56: 17.92406 | AO56: 18.10886 | AP56: 18.17186 | AQ56: 18.36127 | AR56: 18.42127 | AS56: 18.5239 | AT56: 18.6399 | AU56: 18.66847 | AV56: 18.67226 | AW56: 18.63854 | AX56: 18.55808 | AY56: 18.49108 | AZ56: 18.38048 | BA56: 18.276 | BB56: 18.18202 | BC56: 18.07618 | BD56: 17.95916 | BE56: 17.83157 | BF56: 17.83157 | BG56: 17.83157 | BH56: 17.79141 | BI56: 17.76621
A57: Capacites | B57: donnée utilisée directement dans les feuilles suivantes | C57: max_cap_lake | D57: Hydro (lac) | F57: ="Capacité installée " & LOWER(D57) -> Capacité installée hydro (lac) | G57: GW | H57: caihdr_lake | I57: autres_EnR_élec_v1.4 | J57: 12.97013 | K57: 13.00247 | L57: 12.74301 | M57: 13.02673 | N57: 13.02665 | O57: 13.03119 | P57: 13.03119 | Q57: 13.03119 | R57: 13.03119 | S57: 13.03119 | T57: 13.03119 | U57: 13.03119 | V57: 13.03119 | W57: 13.03119 | X57: 13.03119 | Y57: 13.03119 | Z57: 13.03119 | AA57: 13.03119 | AB57: 13.03119 | AC57: 13.03119 | AD57: 13.03119 | AE57: 13.03119 | AF57: 13.03119 | AG57: 13.03119 | AH57: 13.03119 | AI57: 13.03119 | AJ57: 13.03119 | AK57: 13.03119 | AL57: 13.03119 | AM57: 13.03119 | AN57: 13.03119 | AO57: 13.03119 | AP57: 13.03119 | AQ57: 13.03119 | AR57: 13.03119 | AS57: 13.03119 | AT57: 13.03119 | AU57: 13.03119 | AV57: 13.03119 | AW57: 13.03119 | AX57: 13.03119 | AY57: 13.03119 | AZ57: 13.03119 | BA57: 13.03119 | BB57: 13.03119 | BC57: 13.03119 | BD57: 13.03119 | BE57: 13.03119 | BF57: 13.03119 | BG57: 13.03119 | BH57: 13.03119 | BI57: 13.03119
A58: Capacites | B58: donnée utilisée directement dans les feuilles suivantes | C58: max_cap_river | D58: Hydro (fil de l'eau) | F58: ="Capacité installée " & LOWER(D58) -> Capacité installée hydro (fil de l'eau) | G58: GW | H58: caihdr_river | I58: autres_EnR_élec_v1.4 | J58: 7.6 | K58: 7.6 | L58: 7.6 | M58: 7.6 | N58: 7.6 | O58: 7.6 | P58: 7.6 | Q58: 7.6 | R58: 7.6 | S58: 7.6 | T58: 7.6 | U58: 7.6 | V58: 7.6 | W58: 7.6 | X58: 7.6 | Y58: 7.6 | Z58: 7.6 | AA58: 7.6 | AB58: 7.6 | AC58: 7.6 | AD58: 7.6 | AE58: 7.6 | AF58: 7.6 | AG58: 7.6 | AH58: 7.6 | AI58: 7.6 | AJ58: 7.6 | AK58: 7.6 | AL58: 7.6 | AM58: 7.6 | AN58: 7.6 | AO58: 7.6 | AP58: 7.6 | AQ58: 7.6 | AR58: 7.6 | AS58: 7.6 | AT58: 7.6 | AU58: 7.6 | AV58: 7.6 | AW58: 7.6 | AX58: 7.6 | AY58: 7.6 | AZ58: 7.6 | BA58: 7.6 | BB58: 7.6 | BC58: 7.6 | BD58: 7.6 | BE58: 7.6 | BF58: 7.6 | BG58: 7.6 | BH58: 7.6 | BI58: 7.6
A59: Capacites | B59: donnée utilisée directement dans les feuilles suivantes | C59: max_cap_marine | D59: Energies marines (marémoteur, vagues, houle...) | F59: ="Capacité installée " & LOWER(D59) -> Capacité installée energies marines (marémoteur, vagues, houle...) | G59: GW | H59: caienm | I59: autres_EnR_élec_v1.4 | J59: 0.25 | K59: 0.25 | L59: 0.25 | M59: 0.25 | N59: 0.25 | O59: 0.25 | P59: 0.25 | Q59: 0.25 | R59: 0.25 | S59: 0.25 | T59: 0.25 | U59: 0.25 | V59: 0.25 | W59: 0.5 | X59: 0.5 | Y59: 0.5 | Z59: 0.5 | AA59: 0.50848 | AB59: 0.53247 | AC59: 0.56974 | AD59: 0.61809 | AE59: 0.67532 | AF59: 0.73921 | AG59: 0.80757 | AH59: 0.87817 | AI59: 0.94882 | AJ59: 1.0173 | AK59: 1.08142 | AL59: 1.13895 | AM59: 1.1877 | AN59: 1.22545 | AO59: 1.25 | AP59: 1.26698 | AQ59: 1.28349 | AR59: 1.29946 | AS59: 1.31487 | AT59: 1.32966 | AU59: 1.34381 | AV59: 1.35726 | AW59: 1.36997 | AX59: 1.38191 | AY59: 1.39303 | AZ59: 1.40329 | BA59: 1.41265 | BB59: 1.42106 | BC59: 1.42849 | BD59: 1.43489 | BE59: 1.44022 | BF59: 1.44443 | BG59: 1.4475 | BH59: 1.44937 | BI59: 1.45 | BJ59: Capacité installée des sources d'énergie marine
A60: Capacites | B60: donnée utilisée directement dans les feuilles suivantes | C60: max_cap_geothermal_coge | D60: Géothermie haute température | F60: ="Capacité installée " & LOWER(D60) -> Capacité installée géothermie haute température | G60: GW | H60: caight | I60: autres_EnR_élec_v1.4 | J60: 0.0009 | K60: 0.00059 | L60: 0.00091 | M60: 0.00084 | N60: 0.00072 | O60: 0.00072 | P60: 0.00125 | Q60: 0.00165 | R60: 0.00228 | S60: 0.00307 | T60: 0.004 | U60: 0.005 | V60: 0.00687 | W60: 0.01031 | X60: 0.01513 | Y60: 0.02116 | Z60: 0.02821 | AA60: 0.03611 | AB60: 0.04468 | AC60: 0.05373 | AD60: 0.06309 | AE60: 0.07258 | AF60: 0.08201 | AG60: 0.09122 | AH60: 0.10001 | AI60: 0.10822 | AJ60: 0.11565 | AK60: 0.12214 | AL60: 0.1275 | AM60: 0.13155 | AN60: 0.13411 | AO60: 0.135 | AP60: 0.135 | AQ60: 0.135 | AR60: 0.135 | AS60: 0.135 | AT60: 0.135 | AU60: 0.135 | AV60: 0.135 | AW60: 0.135 | AX60: 0.135 | AY60: 0.135 | AZ60: 0.135 | BA60: 0.135 | BB60: 0.135 | BC60: 0.135 | BD60: 0.135 | BE60: 0.135 | BF60: 0.135 | BG60: 0.135 | BH60: 0.135 | BI60: 0.135 | BJ60: Capacité installée en énergie géothermique à haute température et en CSP
A62: Facteurs de charge | B62: donnée non utilisée mais vérif de cohérence avec sorties | C62: capacity_factor_nuclear | D62: Nucléaire | F62: ="Facteur de charge " & LOWER(D62) -> Facteur de charge nucléaire | G62: ratio (0-1) | H62: fchnuc | I62: nucléaire_v4.1 | J62: 0.68617 | K62: 0.6236 | L62: 0.67062 | M62: 0.51923 | N62: 0.59571 | O62: 0.65543 | P62: 0.68005 | Q62: 0.67064 | R62: 0.64476 | S62: 0.63176 | T62: 0.64683 | U62: 0.61029 | V62: 0.59824 | W62: 0.65227 | X62: 0.62924 | Y62: 0.61085 | Z62: 0.58398 | AA62: 0.59132 | AB62: 0.55231 | AC62: 0.5341 | AD62: 0.58774 | AE62: 0.59723 | AF62: 0.58375 | AG62: 0.57815 | AH62: 0.5103 | AI62: 0.52652 | AJ62: 0.55811 | AK62: 0.52579 | AL62: 0.60764 | AM62: 0.55782 | AN62: 0.59774 | AO62: 0.50837 | AP62: 0.56113 | AQ62: 0.64185 | AR62: 0.51875 | AS62: 0.63534 | AT62: 0.74767 | AU62: 0.7009 | AV62: 0.56188 | AW62: 0.34724 | AX62: 0.33236 | AY62: 0.24635 | AZ62: 0.44422 | BA62: 0.8143 | BB62: 0.63538 | BC62: 0.45969 | BD62: 0.91687 | BE62: 0.91687 | BF62: 0.91687 | BG62: 0.91687 | BH62: 0.91687 | BI62: 0.91687 | BJ62: #N/A
A63: Facteurs de charge | B63: donnée non utilisée mais vérif de cohérence avec sorties | C63: capacity_factor_pv | D63: PV | F63: ="Facteur de charge " & LOWER(D63) -> Facteur de charge pv | G63: ratio (0-1) | H63: fchspv | I63: PV_v4.2 | J63: 0.13669 | K63: 0.13635 | L63: 0.12696 | M63: 0.13915 | N63: 0.12891 | O63: 0.10614 | P63: 0.1196 | Q63: 0.12729 | R63: 0.12711 | S63: 0.12704 | T63: 0.12703 | U63: 0.12703 | V63: 0.12705 | W63: 0.12706 | X63: 0.12708 | Y63: 0.12709 | Z63: 0.12711 | AA63: 0.12713 | AB63: 0.12715 | AC63: 0.12717 | AD63: 0.12719 | AE63: 0.1272 | AF63: 0.12722 | AG63: 0.12724 | AH63: 0.12726 | AI63: 0.12727 | AJ63: 0.12729 | AK63: 0.12731 | AL63: 0.12732 | AM63: 0.12734 | AN63: 0.12735 | AO63: 0.12737 | AP63: 0.12738 | AQ63: 0.12738 | AR63: 0.12738 | AS63: 0.12737 | AT63: 0.12735 | AU63: 0.12732 | AV63: 0.12729 | AW63: 0.12725 | AX63: 0.12721 | AY63: 0.12717 | AZ63: 0.12714 | BA63: 0.12711 | BB63: 0.12708 | BC63: 0.12705 | BD63: 0.12703 | BE63: 0.12701 | BF63: 0.127 | BG63: 0.12699 | BH63: 0.12698 | BI63: 0.12697 | BJ63: Facteur de charge moyen pour les systèmes photovoltaïques solaires
A64: Facteurs de charge | B64: donnée non utilisée mais vérif de cohérence avec sorties | C64: capacity_factor_onshore | D64: Eolien onshore | F64: ="Facteur de charge " & LOWER(D64) -> Facteur de charge eolien onshore | G64: ratio (0-1) | H64: fcheon | I64: éolien_v3.3 | J64: 0.23369 | K64: 0.25662 | L64: 0.22483 | M64: 0.20878 | N64: 0.25668 | O64: 0.2155 | P64: 0.21113 | Q64: 0.213 | R64: 0.21794 | S64: 0.22255 | T64: 0.227 | U64: 0.23078 | V64: 0.23375 | W64: 0.2367 | X64: 0.24057 | Y64: 0.24365 | Z64: 0.24805 | AA64: 0.25247 | AB64: 0.25603 | AC64: 0.25843 | AD64: 0.25996 | AE64: 0.26197 | AF64: 0.26422 | AG64: 0.26589 | AH64: 0.26738 | AI64: 0.26877 | AJ64: 0.27022 | AK64: 0.27171 | AL64: 0.27313 | AM64: 0.2746 | AN64: 0.27579 | AO64: 0.27698 | AP64: 0.27813 | AQ64: 0.27925 | AR64: 0.28028 | AS64: 0.28132 | AT64: 0.28237 | AU64: 0.28332 | AV64: 0.28427 | AW64: 0.28519 | AX64: 0.28619 | AY64: 0.28715 | AZ64: 0.28817 | BA64: 0.28921 | BB64: 0.29018 | BC64: 0.29107 | BD64: 0.29189 | BE64: 0.29262 | BF64: 0.29339 | BG64: 0.29403 | BH64: 0.29461 | BI64: 0.29516 | BJ64: Facteur de charge moyen pour l'éolien terrestre
A65: Facteurs de charge | B65: donnée non utilisée mais vérif de cohérence avec sorties | C65: capacity_factor_offshore | D65: Eolien offshore | F65: ="Facteur de charge " & LOWER(D65) -> Facteur de charge eolien offshore | G65: ratio (0-1) | H65: fcheof | I65: éolien_v3.3 | J65: 0 | K65: 0 | L65: 0.37747 | M65: 0.44131 | N65: 0.45826 | O65: 0.35722 | P65: 0.39186 | Q65: 0.42472 | R65: 0.41294 | S65: 0.41012 | T65: 0.40367 | U65: 0.40143 | V65: 0.39305 | W65: 0.38844 | X65: 0.38311 | Y65: 0.37775 | Z65: 0.37667 | AA65: 0.37628 | AB65: 0.37677 | AC65: 0.37623 | AD65: 0.37658 | AE65: 0.3764 | AF65: 0.37648 | AG65: 0.37666 | AH65: 0.37538 | AI65: 0.37469 | AJ65: 0.37763 | AK65: 0.37614 | AL65: 0.37458 | AM65: 0.37526 | AN65: 0.37599 | AO65: 0.3766 | AP65: 0.3773 | AQ65: 0.37796 | AR65: 0.37807 | AS65: 0.37834 | AT65: 0.3787 | AU65: 0.37897 | AV65: 0.37915 | AW65: 0.37973 | AX65: 0.38026 | AY65: 0.38085 | AZ65: 0.38205 | BA65: 0.38307 | BB65: 0.38437 | BC65: 0.38509 | BD65: 0.38605 | BE65: 0.38671 | BF65: 0.38723 | BG65: 0.38756 | BH65: 0.38823 | BI65: 0.38868 | BJ65: Facteur de charge moyen pour l'éolien offshore
A66: Facteurs de charge | B66: donnée non utilisée mais vérif de cohérence avec sorties | C66: capacity_factor_river | D66: Hydro | F66: ="Facteur de charge " & LOWER(D66) -> Facteur de charge hydro | G66: ratio (0-1) | H66: fchhdr | I66: autres_EnR_élec_v1.4 | J66: 0.30712 | K66: 0.3377 | L66: 0.3251 | M66: 0.24201 | N66: 0.3046 | O66: 0.39234 | P66: 0.31922 | Q66: 0.31922 | R66: 0.31922 | S66: 0.31922 | T66: 0.31922 | U66: 0.31922 | V66: 0.31922 | W66: 0.31922 | X66: 0.31922 | Y66: 0.31922 | Z66: 0.31922 | AA66: 0.31922 | AB66: 0.31922 | AC66: 0.31922 | AD66: 0.31922 | AE66: 0.31922 | AF66: 0.31922 | AG66: 0.31922 | AH66: 0.31922 | AI66: 0.31922 | AJ66: 0.31922 | AK66: 0.31922 | AL66: 0.31922 | AM66: 0.31922 | AN66: 0.31922 | AO66: 0.31922 | AP66: 0.31922 | AQ66: 0.31922 | AR66: 0.31922 | AS66: 0.31922 | AT66: 0.31922 | AU66: 0.31922 | AV66: 0.31922 | AW66: 0.31922 | AX66: 0.31922 | AY66: 0.31922 | AZ66: 0.31922 | BA66: 0.31922 | BB66: 0.31922 | BC66: 0.31922 | BD66: 0.31922 | BE66: 0.31922 | BF66: 0.31922 | BG66: 0.31922 | BH66: 0.31922 | BI66: 0.31922 | BJ66: #N/A
A67: Facteurs de charge | B67: donnée non utilisée mais vérif de cohérence avec sorties | C67: capacity_factor_marine | D67: Energies marines | F67: ="Facteur de charge " & LOWER(D67) -> Facteur de charge energies marines | G67: ratio (0-1) | H67: fchenm | I67: autres_EnR_élec_v1.4 | J67: 0.21603 | K67: 0.21729 | L67: 0.2182 | M67: 0.22122 | N67: 0.20264 | O67: 0.20945 | P67: 0.21808 | Q67: 0.21808 | R67: 0.21808 | S67: 0.21808 | T67: 0.21808 | U67: 0.21808 | V67: 0.21808 | W67: 0.29904 | X67: 0.29904 | Y67: 0.29904 | Z67: 0.29904 | AA67: 0.30039 | AB67: 0.30398 | AC67: 0.30895 | AD67: 0.31451 | AE67: 0.32006 | AF67: 0.32524 | AG67: 0.32987 | AH67: 0.3339 | AI67: 0.33734 | AJ67: 0.34021 | AK67: 0.34257 | AL67: 0.34446 | AM67: 0.34592 | AN67: 0.34697 | AO67: 0.34762 | AP67: 0.34805 | AQ67: 0.34846 | AR67: 0.34885 | AS67: 0.34921 | AT67: 0.34956 | AU67: 0.34988 | AV67: 0.35018 | AW67: 0.35045 | AX67: 0.35071 | AY67: 0.35094 | AZ67: 0.35115 | BA67: 0.35134 | BB67: 0.35151 | BC67: 0.35166 | BD67: 0.35179 | BE67: 0.35189 | BF67: 0.35198 | BG67: 0.35203 | BH67: 0.35207 | BI67: 0.35208 | BJ67: Facteur de charge moyen pour les sources d'énergie marines
A68: Facteurs de charge | B68: donnée non utilisée mais vérif de cohérence avec sorties | C68: capacity_factor_geothermal_coge | D68: Géothermie haute température | F68: ="Facteur de charge " & LOWER(D68) -> Facteur de charge géothermie haute température | G68: ratio (0-1) | H68: fchght | I68: autres_EnR_élec_v1.4 | J68: 0.79909 | K68: 0.79909 | L68: 0.79909 | M68: 0.79909 | N68: 0.79909 | O68: 0.79909 | P68: 0.79909 | Q68: 0.79909 | R68: 0.79909 | S68: 0.79909 | T68: 0.79909 | U68: 0.79909 | V68: 0.79909 | W68: 0.79909 | X68: 0.79909 | Y68: 0.79909 | Z68: 0.79909 | AA68: 0.79909 | AB68: 0.79909 | AC68: 0.79909 | AD68: 0.79909 | AE68: 0.79909 | AF68: 0.79909 | AG68: 0.79909 | AH68: 0.79909 | AI68: 0.79909 | AJ68: 0.79909 | AK68: 0.79909 | AL68: 0.79909 | AM68: 0.79909 | AN68: 0.79909 | AO68: 0.79909 | AP68: 0.79909 | AQ68: 0.79909 | AR68: 0.79909 | AS68: 0.79909 | AT68: 0.79909 | AU68: 0.79909 | AV68: 0.79909 | AW68: 0.79909 | AX68: 0.79909 | AY68: 0.79909 | AZ68: 0.79909 | BA68: 0.79909 | BB68: 0.79909 | BC68: 0.79909 | BD68: 0.79909 | BE68: 0.79909 | BF68: 0.79909 | BG68: 0.79909 | BH68: 0.79909 | BI68: 0.79909 | BJ68: Facteur de charge moyen pour l'énergie géothermique à haute température et le CSP
A70: Caracteristiques techno | B70: donnée utilisée directement dans les feuilles suivantes | C70: conversion_efficiency_electrolysis | D70: Electrolyse | F70: Rendement électricité => hydrogène | G70: ratio (0-1) | H70: rdmels | I70: prod-hydrogène_v3.7 | J70: 0.57488 | K70: 0.57488 | L70: 0.58222 | M70: 0.5849 | N70: 0.58825 | O70: 0.59232 | P70: 0.59712 | Q70: 0.60263 | R70: 0.60454 | S70: 0.60775 | T70: 0.61184 | U70: 0.6165 | V70: 0.62148 | W70: 0.62657 | X70: 0.63161 | Y70: 0.63644 | Z70: 0.64097 | AA70: 0.6451 | AB70: 0.64879 | AC70: 0.65202 | AD70: 0.6548 | AE70: 0.65715 | AF70: 0.66002 | AG70: 0.66191 | AH70: 0.66356 | AI70: 0.66501 | AJ70: 0.66631 | AK70: 0.6675 | AL70: 0.66862 | AM70: 0.66968 | AN70: 0.6707 | AO70: 0.67191 | AP70: 0.67271 | AQ70: 0.6735 | AR70: 0.67425 | AS70: 0.67493 | AT70: 0.67555 | AU70: 0.67634 | AV70: 0.67689 | AW70: 0.67739 | AX70: 0.67785 | AY70: 0.67827 | AZ70: 0.67866 | BA70: 0.67904 | BB70: 0.6794 | BC70: 0.67975 | BD70: 0.68018 | BE70: 0.68047 | BF70: 0.68075 | BG70: 0.68101 | BH70: 0.68126 | BI70: 0.68147 | BJ70: #N/A
A71: Caracteristiques techno | B71: donnée utilisée directement dans les feuilles suivantes | C71: conversion_efficiency_methanation | D71: Méthanation | F71: Rendement hydrogène => méthane | G71: ratio (0-1) | H71: rdmmet | I71: bioenergies-PtX_v1.27 | J71: 0 | K71: 0 | L71: 0 | M71: 0 | N71: 0 | O71: 0 | P71: 0 | Q71: 0 | R71: 0 | S71: 0 | T71: 0 | U71: 0 | V71: 0.82833 | W71: 0.82833 | X71: 0.82833 | Y71: 0.82833 | Z71: 0.82833 | AA71: 0.82833 | AB71: 0.82833 | AC71: 0.82833 | AD71: 0.82833 | AE71: 0.82833 | AF71: 0.82833 | AG71: 0.82833 | AH71: 0.82833 | AI71: 0.82833 | AJ71: 0.82833 | AK71: 0.82833 | AL71: 0.82833 | AM71: 0.82833 | AN71: 0.82833 | AO71: 0.82833 | AP71: 0.82833 | AQ71: 0.82833 | AR71: 0.82833 | AS71: 0.82833 | AT71: 0.82833 | AU71: 0.82833 | AV71: 0.82833 | AW71: 0.82833 | AX71: 0.82833 | AY71: 0.82833 | AZ71: 0.82833 | BA71: 0.82833 | BB71: 0.82833 | BC71: 0.82833 | BD71: 0.82833 | BE71: 0.82833 | BF71: 0.82833 | BG71: 0.82833 | BH71: 0.82833 | BI71: 0.82833 | BJ71: #N/A
A73: Demande H2 | B73: donnée nécessitant un traitement dans traitement_nW_EOLES | C73: demand_H2_ind | D73: Industrie | F73: ="Conso pour " & LOWER(D73) -> Conso pour industrie | G73: TWh PCI/an | H73: sec_uses.hyd_se.ind | I73: SEPIA | J73: 0.19 | K73: 0.093 | L73: 0.0987 | M73: 0.1446 | N73: 0.1422 | O73: 0.1374 | P73: 0.1393 | Q73: 0.1616 | R73: 0.1799 | S73: 0.1956 | T73: 0.21 | U73: 0.1893 | V73: 0.162 | W73: 0.1802 | X73: 0.1531 | Y73: 0.171 | Z73: 0.6457 | AA73: 0.5743 | AB73: 0.5568 | AC73: 0.559 | AD73: 0.5539 | AE73: 3.0024 | AF73: 3.0352 | AG73: 3.0261 | AH73: 3.0908 | AI73: 3.0757 | AJ73: 3.1125 | AK73: 3.1198 | AL73: 3.1434 | AM73: 3.161 | AN73: 3.1573 | AO73: 3.1685 | AP73: 3.147 | AQ73: 3.1293 | AR73: 3.0607 | AS73: 3.0597 | AT73: 3.0644 | AU73: 3.032 | AV73: 3.0242 | AW73: 3.0466 | AX73: 3.0511 | AY73: 3.0393 | AZ73: 3.0941 | BA73: 3.0662 | BB73: 3.0803 | BC73: 3.007 | BD73: 3.0384 | BE73: 3.0016 | BF73: 3.0027 | BG73: 2.9645 | BH73: 2.9946 | BI73: 2.9595 | BJ73: #N/A
A74: Demande H2 | B74: donnée nécessitant un traitement dans traitement_nW_EOLES | C74: demand_H2_mob | D74: Mobilité | F74: ="Conso pour " & LOWER(D74) -> Conso pour mobilité | G74: TWh PCI/an | H74: sec_uses.hyd_se.mob | I74: SEPIA | J74: 0 | K74: 0 | L74: 0 | M74: 0 | N74: 0 | O74: 0 | P74: 0 | Q74: 0.0106 | R74: 0.0109 | S74: 0.011 | T74: 0.0111 | U74: 0.0225 | V74: 0.0658 | W74: 0.1102 | X74: 0.1614 | Y74: 0.2182 | Z74: 0.2812 | AA74: 0.3508 | AB74: 0.4273 | AC74: 0.5106 | AD74: 0.6001 | AE74: 0.6952 | AF74: 0.726 | AG74: 0.755 | AH74: 0.7816 | AI74: 0.8057 | AJ74: 0.8272 | AK74: 0.8462 | AL74: 0.8628 | AM74: 0.8773 | AN74: 0.8901 | AO74: 0.9098 | AP74: 0.9092 | AQ74: 0.9085 | AR74: 0.9078 | AS74: 0.9069 | AT74: 0.906 | AU74: 0.905 | AV74: 0.904 | AW74: 0.9029 | AX74: 0.9017 | AY74: 0.9006 | AZ74: 0.8995 | BA74: 0.8983 | BB74: 0.8972 | BC74: 0.8961 | BD74: 0.8951 | BE74: 0.8941 | BF74: 0.8931 | BG74: 0.8922 | BH74: 0.8913 | BI74: 0.8904 | BJ74: #N/A
A75: Demande H2 | B75: donnée nécessitant un traitement dans traitement_nW_EOLES | C75: demand_H2_fret | D75: Fret | F75: ="Conso pour " & LOWER(D75) -> Conso pour fret | G75: TWh PCI/an | H75: sec_uses.hyd_se.fre | I75: SEPIA | J75: 0 | K75: 0 | L75: 0.2301 | M75: 0 | N75: 0 | O75: 0 | P75: 0 | Q75: 0 | R75: 0 | S75: 0 | T75: 0 | U75: 0 | V75: 0 | W75: 0 | X75: 0 | Y75: 0 | Z75: 0 | AA75: 0 | AB75: 0 | AC75: 0 | AD75: 0 | AE75: 0 | AF75: 0 | AG75: 0 | AH75: 0 | AI75: 0 | AJ75: 0 | AK75: 0 | AL75: 0 | AM75: 0 | AN75: 0 | AO75: 0 | AP75: 0 | AQ75: 0 | AR75: 0 | AS75: 0 | AT75: 0 | AU75: 0 | AV75: 0 | AW75: 0 | AX75: 0 | AY75: 0 | AZ75: 0 | BA75: 0 | BB75: 0 | BC75: 0 | BD75: 0 | BE75: 0 | BF75: 0 | BG75: 0 | BH75: 0 | BI75: 0 | BJ75: #N/A
A76: Demande H2 | B76: donnée nécessitant un traitement dans traitement_nW_EOLES | C76: demand_H2_other | D76: Non-énergétique | F76: ="Conso pour " & LOWER(D76) -> Conso pour non-énergétique | G76: TWh PCI/an | H76: sec_uses.hyd_se.neind | I76: SEPIA | J76: 0 | K76: 0 | L76: 0 | M76: 0 | N76: 0 | O76: 0 | P76: 0 | Q76: 0 | R76: 0 | S76: 0 | T76: 0 | U76: 0.0318 | V76: 0.0599 | W76: 0.0855 | X76: 0.1094 | Y76: 0.1322 | Z76: 1.2912 | AA76: 4.0387 | AB76: 5.7984 | AC76: 7.1498 | AD76: 8.9597 | AE76: 10.8735 | AF76: 12.2955 | AG76: 13.7093 | AH76: 15.1013 | AI76: 16.4376 | AJ76: 17.7176 | AK76: 18.9028 | AL76: 19.9178 | AM76: 20.7516 | AN76: 21.3672 | AO76: 21.7492 | AP76: 22.1418 | AQ76: 22.5302 | AR76: 22.8983 | AS76: 23.2672 | AT76: 23.6164 | AU76: 23.9276 | AV76: 24.2101 | AW76: 24.4708 | AX76: 24.7131 | AY76: 24.9409 | AZ76: 25.1577 | BA76: 25.3293 | BB76: 25.4949 | BC76: 25.6114 | BD76: 25.7717 | BE76: 25.8956 | BF76: 26.0052 | BG76: 26.0639 | BH76: 26.142 | BI76: 26.1675 | BJ76: #N/A
A77: Demande H2 | B77: donnée nécessitant un traitement dans traitement_nW_EOLES | C77: demand_H2_en | D77: Branche énergie | F77: ="Conso pour " & LOWER(D77) -> Conso pour branche énergie | G77: TWh PCI/an | H77: sec_uses.hyd_se.ens | I77: SEPIA | J77: 0 | K77: 0 | L77: 0 | M77: 0 | N77: 0 | O77: 0 | P77: 0 | Q77: 0 | R77: 0 | S77: 0 | T77: 0 | U77: 0 | V77: 0.1205 | W77: 0.2418 | X77: 0.3636 | Y77: 0.4853 | Z77: 0.6058 | AA77: 0.7242 | AB77: 0.8391 | AC77: 0.9495 | AD77: 1.0544 | AE77: 1.1531 | AF77: 1.2473 | AG77: 1.3395 | AH77: 1.4304 | AI77: 1.5209 | AJ77: 1.6117 | AK77: 1.7039 | AL77: 1.7982 | AM77: 1.8955 | AN77: 1.9968 | AO77: 2.1028 | AP77: 2.0995 | AQ77: 2.0952 | AR77: 2.09 | AS77: 2.0841 | AT77: 2.0773 | AU77: 2.07 | AV77: 2.0622 | AW77: 2.054 | AX77: 2.0457 | AY77: 2.0373 | AZ77: 2.0373 | BA77: 2.0373 | BB77: 2.0373 | BC77: 2.0373 | BD77: 2.0373 | BE77: 2.0373 | BF77: 2.0373 | BG77: 2.0373 | BH77: 2.0373 | BI77: 2.0373 | BJ77: #N/A
A78: Demande H2 | B78: donnée non utilisée mais vérif de cohérence avec sorties | C78: demand_H2 | D78: Méthanation (P2G) | F78: ="Conso pour " & LOWER(D78) -> Conso pour méthanation (p2g) | G78: TWh PCI/an | H78: sec_uses.hyd_se.gaz_se | I78: SEPIA | J78: 0 | K78: 0 | L78: 0 | M78: 0 | N78: 0 | O78: 0 | P78: 0 | Q78: 0 | R78: 0 | S78: 0 | T78: 0 | U78: 0 | V78: 0.2486 | W78: 0.5827 | X78: 1.0063 | Y78: 1.5258 | Z78: 2.1347 | AA78: 2.8338 | AB78: 3.6172 | AC78: 4.4789 | AD78: 5.4104 | AE78: 6.4018 | AF78: 7.451 | AG78: 8.5545 | AH78: 9.7044 | AI78: 10.9492 | AJ78: 12.1766 | AK78: 13.477 | AL78: 14.9884 | AM78: 16.5789 | AN78: 18.2015 | AO78: 19.8672 | AP78: 19.9089 | AQ78: 19.9463 | AR78: 19.98 | AS78: 20.1277 | AT78: 20.151 | AU78: 20.153 | AV78: 20.165 | AW78: 20.171 | AX78: 20.1018 | AY78: 20.1306 | AZ78: 20.1558 | BA78: 20.1615 | BB78: 20.1666 | BC78: 20.2901 | BD78: 20.2926 | BE78: 20.2933 | BF78: 20.2923 | BG78: 20.2901 | BH78: 20.2165 | BI78: 20.2104
A79: Demande H2 | B79: donnée nécessitant un traitement dans traitement_nW_EOLES | C79: demand_H2_efuel | D79: E-fuel | F79: ="Conso pour " & LOWER(D79) -> Conso pour e-fuel | G79: TWh PCI/an | H79: sec_uses.hyd_se.lqf_se | I79: SEPIA | J79: 0 | K79: 0 | L79: 0 | M79: 0 | N79: 0 | O79: 0 | P79: 0 | Q79: 0 | R79: 0 | S79: 0 | T79: 0 | U79: 0 | V79: 0.0465 | W79: 0.1763 | X79: 0.389 | Y79: 0.7113 | Z79: 1.1035 | AA79: 1.5855 | AB79: 2.1481 | AC79: 2.7944 | AD79: 3.5231 | AE79: 4.3333 | AF79: 5.2342 | AG79: 6.2177 | AH79: 7.2855 | AI79: 8.7794 | AJ79: 10.0811 | AK79: 11.4964 | AL79: 13.0219 | AM79: 14.7782 | AN79: 16.5231 | AO79: 18.3663 | AP79: 18.4062 | AQ79: 18.4415 | AR79: 18.4752 | AS79: 19.214 | AT79: 19.2312 | AU79: 19.1436 | AV79: 19.1391 | AW79: 19.1227 | AX79: 18.6793 | AY79: 18.8464 | AZ79: 19.0031 | BA79: 19.0431 | BB79: 19.0794 | BC79: 19.8241 | BD79: 19.8441 | BE79: 19.8522 | BF79: 19.8506 | BG79: 19.8402 | BH79: 19.4021 | BI79: 19.3678
A80: Demande H2 | B80: donnée non utilisée mais vérif de cohérence avec sorties | C80: demand_H2 | D80: Excédent | F80: =D80 -> Excédent | G80: TWh PCI/an | H80: sec_uses.hyd_se.exp | I80: SEPIA | J80: 0 | K80: 0 | L80: 0 | M80: 0 | N80: 0 | O80: 0 | P80: 0 | Q80: 0.7549 | R80: 1.7156 | S80: 2.6683 | T80: 3.6378 | U80: 4.6168 | V80: 5.7208 | W80: 6.582 | X80: 7.2785 | Y80: 7.6838 | Z80: 6.2906 | AA80: 5.7608 | AB80: 5.891 | AC80: 6.1306 | AD80: 5.6419 | AE80: 2.324 | AF80: 2.8745 | AG80: 3.1362 | AH80: 3.0395 | AI80: 2.3787 | AJ80: 1.7518 | AK80: 2.4252 | AL80: 2.6835 | AM80: 2.5695 | AN80: 2.4218 | AO80: 2.1127 | AP80: 2.4531 | AQ80: 2.8034 | AR80: 3.2287 | AS80: 2.7626 | AT80: 3.151 | AU80: 3.7617 | AV80: 4.2594 | AW80: 4.7624 | AX80: 5.8003 | AY80: 6.1576 | AZ80: 6.2251 | BA80: 6.5552 | BB80: 6.8525 | BC80: 6.4585 | BD80: 6.7714 | BE80: 7.1865 | BF80: 7.5889 | BG80: 8.0902 | BH80: 9.0009 | BI80: 9.5551
A81: Demande H2 | B81: donnée non utilisée mais vérif de cohérence avec sorties | C81: demand_H2 | F81: TOTAL | G81: TWh PCI/an | H81: sec_uses.hyd_se.total | I81: SEPIA | J81: 0.19 | K81: 0.093 | L81: 0.3288 | M81: 0.1446 | N81: 0.1422 | O81: 0.1374 | P81: 0.1393 | Q81: 0.9271 | R81: 1.9065 | S81: 2.8749 | T81: 3.859 | U81: 4.8605 | V81: 6.4241 | W81: 7.9587 | X81: 9.4613 | Y81: 10.9275 | Z81: 12.3527 | AA81: 15.8681 | AB81: 19.278 | AC81: 22.5727 | AD81: 25.7435 | AE81: 28.7833 | AF81: 32.8637 | AG81: 36.7383 | AH81: 40.4335 | AI81: 43.9472 | AJ81: 47.2786 | AK81: 51.9711 | AL81: 56.4159 | AM81: 60.6119 | AN81: 64.5578 | AO81: 68.2766 | AP81: 69.0656 | AQ81: 69.8544 | AR81: 70.6406 | AS81: 71.4221 | AT81: 72.1974 | AU81: 72.993 | AV81: 73.764 | AW81: 74.5304 | AX81: 75.293 | AY81: 76.0528 | AZ81: 76.5726 | BA81: 77.091 | BB81: 77.6082 | BC81: 78.1246 | BD81: 78.6507 | BE81: 79.1606 | BF81: 79.6702 | BG81: 80.1785 | BH81: 80.6846 | BI81: 81.1881 | BJ81: #N/A
A82: Demande H2 | B82: donnée non utilisée mais vérif de cohérence sur cet onglet | C82: demand_H2 | F82: DELTA TOTAL vs. somme | G82: TWh/an | J82: =J81-SUM(J73:J80) -> 0 | K82: =K81-SUM(K73:K80) -> 0 | L82: =L81-SUM(L73:L80) -> 0 | M82: =M81-SUM(M73:M80) -> 0 | N82: =N81-SUM(N73:N80) -> 0 | O82: =O81-SUM(O73:O80) -> 0 | P82: =P81-SUM(P73:P80) -> 0 | Q82: =Q81-SUM(Q73:Q80) -> 0 | ... BI82: =BI81-SUM(BI73:BI80) -> 0.0001
A84: Demande CH4 | B84: donnée nécessitant un traitement dans traitement_nW_EOLES | C84: demand_CH4_res_heat | D84: Résidentiel | E84: Thermosensible chaud | F84: Conso d'élec pour chauffage résidentiel (effet joule + électricité des PAC) | G84: TWh/an | H84: gazcfreschf | I84: bâtiment_démographie_v2.6 | J84: 109.74464 | K84: 108.9416 | L84: 108.76653 | M84: 102.19669 | N84: 95.81418 | O84: 94.96194 | P84: 93.72489 | Q84: 92.55918 | R84: 91.37992 | S84: 90.14249 | T84: 88.7803 | U84: 87.19986 | V84: 85.23399 | W84: 82.8241 | X84: 79.89421 | Y84: 76.41984 | Z84: 72.4156 | AA84: 67.92757 | AB84: 63.04104 | AC84: 57.88324 | AD84: 52.61249 | AE84: 47.40143 | AF84: 42.41826 | AG84: 37.81156 | AH84: 33.69329 | AI84: 30.13122 | AJ84: 26.78623 | AK84: 23.94898 | AL84: 21.7258 | AM84: 19.94982 | AN84: 18.53383 | AO84: 17.39375 | AP84: 16.6965 | AQ84: 16.16119 | AR84: 15.75119 | AS84: 15.43446 | AT84: 15.3068 | AU84: 15.20956 | AV84: 15.11972 | AW84: 15.0545 | AX84: 14.99261 | AY84: 14.93263 | AZ84: 14.87393 | BA84: 14.81636 | BB84: 14.75999 | BC84: 14.70504 | BD84: 14.65176 | BE84: 14.60048 | BF84: 14.55151 | BG84: 14.50521 | BH84: 14.46199 | BI84: 14.4211 | BJ84: Consommation finale d'énergie provenant du réseau de gaz / gaz consommé localement pour le chauffage des locaux | BK84: TRUE
A85: Demande CH4 | B85: donnée non utilisée mais vérif de cohérence sur cet onglet | C85: demand_CH4 | D85: Résidentiel | F85: Eau chaude sanitaire résidentiel | G85: TWh/an | H85: gazcfresecs | I85: bâtiment_démographie_v2.6 | J85: 14.94765 | K85: 14.83982 | L85: 14.70623 | M85: 14.59951 | N85: 14.50375 | O85: 14.41095 | P85: 14.29267 | Q85: 14.17587 | R85: 14.04481 | S85: 13.89212 | T85: 13.70779 | U85: 13.47871 | V85: 13.18983 | W85: 12.82555 | X85: 12.37202 | Y85: 11.8202 | Z85: 11.16813 | AA85: 10.42304 | AB85: 9.60235 | AC85: 8.73276 | AD85: 7.84701 | AE85: 6.97912 | AF85: 6.16 | AG85: 5.41438 | AH85: 4.75872 | AI85: 4.20097 | AJ85: 3.74139 | AK85: 3.37401 | AL85: 3.08849 | AM85: 2.87224 | AN85: 2.71189 | AO85: 2.59465 | AP85: 2.50922 | AQ85: 2.44626 | AR85: 2.39845 | AS85: 2.36043 | AT85: 2.32848 | AU85: 2.30014 | AV85: 2.27387 | AW85: 2.24878 | AX85: 2.22436 | AY85: 2.20037 | AZ85: 2.17669 | BA85: 2.15327 | BB85: 2.13009 | BC85: 2.10717 | BD85: 2.08452 | BE85: 2.06214 | BF85: 2.04004 | BG85: 2.01821 | BH85: 1.99664 | BI85: 1.97528 | BJ85: Consommation finale d'énergie provenant du réseau de gaz / gaz consommé localement pour l'eau chaude sanitaire | BK85: TRUE
A86: Demande CH4 | B86: donnée non utilisée mais vérif de cohérence sur cet onglet | C86: demand_CH4 | D86: Résidentiel | F86: Cuisson résidentiel | G86: TWh/an | H86: gazcfrescui | I86: bâtiment_démographie_v2.6 | J86: 1.55018 | K86: 1.47635 | L86: 1.49259 | M86: 1.42081 | N86: 1.34834 | O86: 1.28048 | P86: 1.21656 | Q86: 1.15549 | R86: 1.03939 | S86: 0.93465 | T86: 0.84018 | U86: 0.755 | V86: 0.67973 | W86: 0.61176 | X86: 0.48926 | Y86: 0.39116 | Z86: 0.31263 | AA86: 0 | AB86: 0 | AC86: 0 | AD86: 0 | AE86: 0 | AF86: 0 | AG86: 0 | AH86: 0 | AI86: 0 | AJ86: 0 | AK86: 0 | AL86: 0 | AM86: 0 | AN86: 0 | AO86: 0 | AP86: 0 | AQ86: 0 | AR86: 0 | AS86: 0 | AT86: 0 | AU86: 0 | AV86: 0 | AW86: 0 | AX86: 0 | AY86: 0 | AZ86: 0 | BA86: 0 | BB86: 0 | BC86: 0 | BD86: 0 | BE86: 0 | BF86: 0 | BG86: 0 | BH86: 0 | BI86: 0 | BJ86: Consommation finale d'énergie provenant du réseau de gaz / gaz consommé localement pour la cuisson domestique | BK86: TRUE
A87: Demande CH4 | B87: donnée nécessitant un traitement dans traitement_nW_EOLES | C87: demand_CH4_res | D87: Résidentiel | F87: TOTAL | G87: TWh/an | H87: gazcfres | I87: bâtiment_démographie_v2.6 | J87: 126.24247 | K87: 125.25777 | L87: 124.96535 | M87: 118.21701 | N87: 111.66627 | O87: 110.65337 | P87: 109.23411 | Q87: 107.89053 | R87: 106.46411 | S87: 104.96925 | T87: 103.32827 | U87: 101.43357 | V87: 99.10354 | W87: 96.26141 | X87: 92.75549 | Y87: 88.6312 | Z87: 83.89637 | AA87: 78.35061 | AB87: 72.64339 | AC87: 66.61601 | AD87: 60.45951 | AE87: 54.38055 | AF87: 48.57826 | AG87: 43.22595 | AH87: 38.45201 | AI87: 34.33219 | AJ87: 30.52763 | AK87: 27.323 | AL87: 24.8143 | AM87: 22.82206 | AN87: 21.24572 | AO87: 19.9884 | AP87: 19.20572 | AQ87: 18.60744 | AR87: 18.14964 | AS87: 17.7949 | AT87: 17.63528 | AU87: 17.5097 | AV87: 17.39359 | AW87: 17.30328 | AX87: 17.21697 | AY87: 17.133 | AZ87: 17.05063 | BA87: 16.96963 | BB87: 16.89008 | BC87: 16.81221 | BD87: 16.73628 | BE87: 16.66262 | BF87: 16.59155 | BG87: 16.52341 | BH87: 16.45864 | BI87: 16.39638
A88: Demande CH4 | B88: donnée non utilisée mais vérif de cohérence sur cet onglet | C88: demand_CH4 | D88: Résidentiel | F88: DELTA TOTAL vs. somme | G88: TWh/an | J88: =J87-SUM(J84:J86) -> 0 | K88: =K87-SUM(K84:K86) -> 0 | L88: =L87-SUM(L84:L86) -> 0 | M88: =M87-SUM(M84:M86) -> 0 | N88: =N87-SUM(N84:N86) -> 0 | O88: =O87-SUM(O84:O86) -> 0 | P88: =P87-SUM(P84:P86) -> -1e-05 | Q88: =Q87-SUM(Q84:Q86) -> -1e-05 | ... BI88: =BI87-SUM(BI84:BI86) -> 0
A90: Demande CH4 | B90: donnée nécessitant un traitement dans traitement_nW_EOLES | C90: demand_CH4_ter_heat | D90: Tertiaire | E90: Thermosensible chaud | F90: Conso d'élec pour chauffage tertiaire (effet joule + électricité des PAC) | G90: TWh/an | H90: gazcfterchf | I90: bâtiment_démographie_v2.6 | J90: 62.25524 | K90: 61.17207 | L90: 60.86537 | M90: 56.16028 | N90: 52.8173 | O90: 52.35941 | P90: 51.82227 | Q90: 51.19903 | R90: 50.48304 | S90: 49.66707 | T90: 48.74086 | U90: 47.6872 | V90: 46.46596 | W90: 45.06943 | X90: 43.4871 | Y90: 41.73485 | Z90: 39.85133 | AA90: 37.88196 | AB90: 35.85212 | AC90: 33.70935 | AD90: 31.5804 | AE90: 29.4772 | AF90: 27.41031 | AG90: 25.3902 | AH90: 23.42813 | AI90: 21.53661 | AJ90: 19.72869 | AK90: 18.01922 | AL90: 16.42251 | AM90: 14.95051 | AN90: 13.61176 | AO90: 12.41038 | AP90: 11.34579 | AQ90: 10.41307 | AR90: 9.60376 | AS90: 8.90692 | AT90: 8.31025 | AU90: 7.80099 | AV90: 7.36664 | AW90: 6.99548 | AX90: 6.67688 | AY90: 6.40148 | AZ90: 6.16121 | BA90: 5.94926 | BB90: 5.75999 | BC90: 5.58878 | BD90: 5.43121 | BE90: 5.28234 | BF90: 5.14247 | BG90: 5.01454 | BH90: 4.91237 | BI90: 4.79602 | BJ90: #N/A | BK90: TRUE
A91: Demande CH4 | B91: donnée non utilisée mais vérif de cohérence sur cet onglet | C91: demand_CH4 | D91: Tertiaire | F91: Eau chaude sanitaire tertiaire | G91: TWh/an | H91: gazcfterecs | I91: bâtiment_démographie_v2.6 | J91: 13.87728 | K91: 13.85302 | L91: 13.78937 | M91: 13.78932 | N91: 13.70189 | O91: 13.60923 | P91: 13.50701 | Q91: 13.38994 | R91: 13.24982 | S91: 13.07492 | T91: 12.84963 | U91: 12.55469 | V91: 12.16919 | W91: 11.67385 | X91: 11.05559 | Y91: 10.31265 | Z91: 9.45798 | AA91: 8.51945 | AB91: 7.53605 | AC91: 6.55131 | AD91: 5.60625 | AE91: 4.7338 | AF91: 3.9562 | AG91: 3.2848 | AH91: 2.72173 | AI91: 2.26218 | AJ91: 1.8968 | AK91: 1.6136 | AL91: 1.3995 | AM91: 1.24155 | AN91: 1.12761 | AO91: 1.04696 | AP91: 0.99055 | AQ91: 0.95111 | AR91: 0.92308 | AS91: 0.90241 | AT91: 0.88628 | AU91: 0.87285 | AV91: 0.86096 | AW91: 0.84992 | AX91: 0.83932 | AY91: 0.82897 | AZ91: 0.81877 | BA91: 0.80865 | BB91: 0.7986 | BC91: 0.78861 | BD91: 0.77868 | BE91: 0.76882 | BF91: 0.75903 | BG91: 0.74929 | BH91: 0.73962 | BI91: 0.72998 | BJ91: #N/A | BK91: TRUE
A92: Demande CH4 | B92: donnée non utilisée mais vérif de cohérence sur cet onglet | C92: demand_CH4 | D92: Tertiaire | F92: Cuisson tertiaire | G92: TWh/an | H92: gazcftercui | I92: bâtiment_démographie_v2.6 | J92: 4.66328 | K92: 4.66585 | L92: 4.64943 | M92: 4.63162 | N92: 4.5967 | O92: 4.5757 | P92: 4.53806 | Q92: 4.46233 | R92: 4.38487 | S92: 4.32284 | T92: 4.25944 | U92: 4.16808 | V92: 4.05248 | W92: 3.93794 | X92: 3.84102 | Y92: 3.74479 | Z92: 3.6654 | AA92: 3.58632 | AB92: 3.50759 | AC92: 3.44474 | AD92: 3.38186 | AE92: 3.31898 | AF92: 3.27103 | AG92: 3.22274 | AH92: 3.20794 | AI92: 3.2075 | AJ92: 3.20682 | AK92: 3.2059 | AL92: 3.20472 | AM92: 3.20329 | AN92: 3.20163 | AO92: 3.19971 | AP92: 3.19753 | AQ92: 3.19509 | AR92: 3.19238 | AS92: 3.18938 | AT92: 3.18613 | AU92: 3.18264 | AV92: 3.17897 | AW92: 3.17514 | AX92: 3.1712 | AY92: 3.1672 | AZ92: 3.16321 | BA92: 3.15923 | BB92: 3.15531 | BC92: 3.15149 | BD92: 3.1478 | BE92: 3.14425 | BF92: 3.14085 | BG92: 3.13761 | BH92: 3.13452 | BI92: 3.13152 | BJ92: #N/A | BK92: TRUE
A93: Demande CH4 | B93: donnée nécessitant un traitement dans traitement_nW_EOLES | C93: demand_CH4_ter | D93: Tertiaire | F93: TOTAL | G93: TWh/an | H93: gazcfter | I93: bâtiment_démographie_v2.6 | J93: 80.7958 | K93: 79.69094 | L93: 79.30417 | M93: 74.58123 | N93: 71.11589 | O93: 70.54435 | P93: 69.86734 | Q93: 69.05129 | R93: 68.11772 | S93: 67.06483 | T93: 65.84993 | U93: 64.40998 | V93: 62.68763 | W93: 60.68123 | X93: 58.38372 | Y93: 55.7923 | Z93: 52.97471 | AA93: 49.98774 | AB93: 46.89576 | AC93: 43.7054 | AD93: 40.56851 | AE93: 37.52998 | AF93: 34.63753 | AG93: 31.89774 | AH93: 29.35779 | AI93: 27.00628 | AJ93: 24.83231 | AK93: 22.83872 | AL93: 21.02673 | AM93: 19.39535 | AN93: 17.941 | AO93: 16.65704 | AP93: 15.53386 | AQ93: 14.55927 | AR93: 13.71922 | AS93: 12.9987 | AT93: 12.38265 | AU93: 11.85648 | AV93: 11.40657 | AW93: 11.02054 | AX93: 10.6874 | AY93: 10.39766 | AZ93: 10.14319 | BA93: 9.91714 | BB93: 9.7139 | BC93: 9.52888 | BD93: 9.35769 | BE93: 9.19542 | BF93: 9.04235 | BG93: 8.90144 | BH93: 8.78651 | BI93: 8.65751
A94: Demande CH4 | B94: donnée non utilisée mais vérif de cohérence sur cet onglet | C94: demand_CH4 | D94: Tertiaire | F94: DELTA TOTAL vs. somme | G94: TWh/an | J94: =J93-SUM(J90:J92) -> 0 | K94: =K93-SUM(K90:K92) -> 0 | L94: =L93-SUM(L90:L92) -> 0 | M94: =M93-SUM(M90:M92) -> 1e-05 | N94: =N93-SUM(N90:N92) -> 0 | O94: =O93-SUM(O90:O92) -> 1e-05 | P94: =P93-SUM(P90:P92) -> 0 | Q94: =Q93-SUM(Q90:Q92) -> -1e-05 | ... BI94: =BI93-SUM(BI90:BI92) -> -1e-05
A96: Demande CH4 | B96: donnée nécessitant un traitement dans traitement_nW_EOLES | C96: demand_CH4_mob | D96: Mobilité domestique | F96: ="Conso pour " & LOWER(D96) -> Conso pour mobilité domestique | G96: TWh PCI/an | H96: gazcfmob | I96: transports_v6.13 | J96: 0.39622 | K96: 0.32996 | L96: 0.46996 | M96: 0.6581 | N96: 0.86945 | O96: 1.03458 | P96: 1.16528 | Q96: 1.33622 | R96: 1.50692 | S96: 1.67738 | T96: 1.84755 | U96: 2.01742 | V96: 2.18696 | W96: 2.35615 | X96: 2.52496 | Y96: 2.69337 | Z96: 2.86135 | AA96: 3.07135 | AB96: 3.29139 | AC96: 3.51661 | AD96: 3.74701 | AE96: 3.9826 | AF96: 4.22343 | AG96: 4.46952 | AH96: 4.72089 | AI96: 4.97759 | AJ96: 5.2397 | AK96: 5.50723 | AL96: 5.78015 | AM96: 6.0585 | AN96: 6.34231 | AO96: 6.63153 | AP96: 6.57968 | AQ96: 6.52736 | AR96: 6.47456 | AS96: 6.42127 | AT96: 6.36755 | AU96: 6.31347 | AV96: 6.25912 | AW96: 6.20458 | AX96: 6.14993 | AY96: 6.0953 | AZ96: 6.04078 | BA96: 5.98641 | BB96: 5.93228 | BC96: 5.87844 | BD96: 5.82495 | BE96: 5.77183 | BF96: 5.7191 | BG96: 5.66675 | BH96: 5.61477 | BI96: 5.56268 | BJ96: Consommation finale d'énergie provenant des carburants gazeux pour moteurs - méthane dans la mobilité des passagers | BK96: TRUE
A97: Demande CH4 | B97: donnée nécessitant un traitement dans traitement_nW_EOLES | C97: demand_CH4_fret | D97: Fret domestique | F97: ="Conso pour " & LOWER(D97) -> Conso pour fret domestique | G97: TWh PCI/an | H97: gazcffre | I97: transports_v6.13 | J97: 1.02821 | K97: 1.35284 | L97: 1.87954 | M97: 2.13258 | N97: 2.34531 | O97: 2.4534 | P97: 3.06713 | Q97: 3.31363 | R97: 3.66835 | S97: 4.15074 | T97: 4.78712 | U97: 5.55726 | V97: 6.56746 | W97: 7.77571 | X97: 9.02446 | Y97: 10.36445 | Z97: 11.81923 | AA97: 13.48354 | AB97: 15.19385 | AC97: 16.96033 | AD97: 18.8134 | AE97: 20.75296 | AF97: 22.83529 | AG97: 24.97046 | AH97: 27.04326 | AI97: 28.87592 | AJ97: 30.28125 | AK97: 31.15131 | AL97: 31.49249 | AM97: 31.41233 | AN97: 31.05217 | AO97: 30.53875 | AP97: 29.82238 | AQ97: 29.11807 | AR97: 28.42566 | AS97: 27.745 | AT97: 27.07594 | AU97: 26.16759 | AV97: 25.28273 | AW97: 24.42081 | AX97: 23.58128 | AY97: 22.76362 | AZ97: 22.13345 | BA97: 21.51485 | BB97: 20.9076 | BC97: 20.31145 | BD97: 19.72621 | BE97: 19.27364 | BF97: 18.82897 | BG97: 18.39205 | BH97: 17.96274 | BI97: 17.54088 | BJ97: Consommation finale de gaz méthane dans le transport de marchandises | BK97: TRUE
A98: Demande CH4 | B98: donnée nécessitant un traitement dans traitement_nW_EOLES | C98: demand_CH4_mar | D98: Maritime international | F98: ="Conso pour " & LOWER(D98) -> Conso pour maritime international | G98: TWh PCI/an | H98: ngvcffrewati | I98: transports_v6.13 | J98: 0 | K98: 0 | L98: 0 | M98: 0 | N98: 0 | O98: 0 | P98: 0 | Q98: 0 | R98: 0 | S98: 0 | T98: 0.07522 | U98: 0.14623 | V98: 0.3126 | W98: 0.46923 | X98: 0.61631 | Y98: 0.75406 | Z98: 0.88267 | AA98: 1.05125 | AB98: 1.20806 | AC98: 1.35337 | AD98: 1.48746 | AE98: 1.61059 | AF98: 1.76456 | AG98: 1.9053 | AH98: 2.03315 | AI98: 2.14846 | AJ98: 2.25156 | AK98: 2.34278 | AL98: 2.42248 | AM98: 2.49099 | AN98: 2.54864 | AO98: 2.59578 | AP98: 2.63481 | AQ98: 2.6679 | AR98: 2.69506 | AS98: 2.71628 | AT98: 2.73157 | AU98: 2.74092 | AV98: 2.74433 | AW98: 2.83481 | AX98: 2.92528 | AY98: 3.01575 | AZ98: 3.13638 | BA98: 3.25701 | BB98: 3.37764 | BC98: 3.49827 | BD98: 3.6189 | BE98: 3.73953 | BF98: 3.86016 | BG98: 3.98079 | BH98: 4.10142 | BI98: 4.22205 | BJ98: Consommation finale de GNV/biométhane pour le transport international de marchandises par voie maritime | BK98: TRUE
A99: Demande CH4 | B99: donnée nécessitant un traitement dans traitement_nW_EOLES | C99: demand_CH4_ind | D99: Industrie | F99: ="Conso pour " & LOWER(D99) -> Conso pour industrie | G99: TWh PCI/an | H99: gazcfind | I99: industrie | J99: 121.06672 | K99: 109.59278 | L99: 114.74634 | M99: 111.80485 | N99: 108.49605 | O99: 109.26139 | P99: 110.22505 | Q99: 109.25309 | R99: 105.41797 | S99: 100.38195 | T99: 95.30085 | U99: 90.69725 | V99: 87.20832 | W99: 83.82663 | X99: 80.61153 | Y99: 77.56537 | Z99: 73.01152 | AA99: 69.20932 | AB99: 66.30334 | AC99: 63.81134 | AD99: 61.31147 | AE99: 55.49106 | AF99: 53.55534 | AG99: 51.43763 | AH99: 49.63395 | AI99: 47.8173 | AJ99: 46.32663 | AK99: 45.08231 | AL99: 44.09402 | AM99: 43.33155 | AN99: 42.70702 | AO99: 42.32369 | AP99: 42.3444 | AQ99: 42.29716 | AR99: 42.13702 | AS99: 42.13005 | AT99: 42.13808 | AU99: 42.06042 | AV99: 42.04328 | AW99: 42.11855 | AX99: 42.27257 | AY99: 42.38283 | AZ99: 42.64349 | BA99: 42.73287 | BB99: 42.9049 | BC99: 42.86451 | BD99: 43.13583 | BE99: 43.21278 | BF99: 43.41948 | BG99: 43.42696 | BH99: 43.62221 | BI99: 43.69609 | BJ99: Réseau de gaz / gaz consommé localement | BK99: TRUE
A100: Demande CH4 | B100: donnée nécessitant un traitement dans traitement_nW_EOLES | C100: demand_CH4_agr | D100: Agriculture | F100: ="Conso pour " & LOWER(D100) -> Conso pour agriculture | G100: TWh PCI/an | H100: gazcfagr | I100: agriculture_v5 | J100: 2.76407 | K100: 2.72293 | L100: 2.94648 | M100: 2.64058 | N100: 2.75832 | O100: 2.6603 | P100: 2.59029 | Q100: 2.8206 | R100: 3.08673 | S100: 3.38575 | T100: 3.71438 | U100: 4.06903 | V100: 4.44582 | W100: 4.84061 | X100: 5.24907 | Y100: 5.66674 | Z100: 6.08903 | AA100: 6.51133 | AB100: 6.929 | AC100: 7.33746 | AD100: 7.73225 | AE100: 8.10904 | AF100: 8.46369 | AG100: 8.79232 | AH100: 9.09134 | AI100: 9.35747 | AJ100: 9.58778 | AK100: 9.77976 | AL100: 9.93131 | AM100: 10.04075 | AN100: 10.10691 | AO100: 10.12904 | AP100: 10.13456 | AQ100: 10.15101 | AR100: 10.17796 | AS100: 10.21477 | AT100: 10.26051 | AU100: 10.31408 | AV100: 10.37413 | AW100: 10.43921 | AX100: 10.5077 | AY100: 10.57793 | AZ100: 10.64815 | BA100: 10.71664 | BB100: 10.78172 | BC100: 10.84178 | BD100: 10.89534 | BE100: 10.94108 | BF100: 10.97789 | BG100: 11.00484 | BH100: 11.02129 | BI100: 11.02682 | BJ100: #N/A | BK100: TRUE
A101: Demande CH4 | B101: donnée nécessitant un traitement dans traitement_nW_EOLES | C101: demand_CH4_other | D101: Non-énergétique | F101: ="Conso pour " & LOWER(D101) -> Conso pour non-énergétique | G101: TWh PCI/an | H101: gazcfneind | I101: industrie | J101: 12.97889 | K101: 11.76221 | L101: 10.08336 | M101: 11.10729 | N101: 10.14342 | O101: 10.0596 | P101: 10.64405 | Q101: 10.98236 | R101: 11.30462 | S101: 11.60815 | T101: 11.89343 | U101: 11.50702 | V101: 11.46979 | W101: 11.41044 | X101: 11.3272 | Y101: 11.23092 | Z101: 10.13698 | AA101: 7.73092 | AB101: 6.65584 | AC101: 6.24061 | AD101: 5.51433 | AE101: 4.79556 | AF101: 4.78906 | AG101: 4.86247 | AH101: 5.00266 | AI101: 5.18887 | AJ101: 5.39775 | AK101: 5.63088 | AL101: 5.85459 | AM101: 6.06468 | AN101: 6.23825 | AO101: 6.36191 | AP101: 6.52168 | AQ101: 6.67854 | AR101: 6.83058 | AS101: 6.98775 | AT101: 7.13937 | AU101: 7.28627 | AV101: 7.42838 | AW101: 7.57297 | AX101: 7.71487 | AY101: 7.85429 | AZ101: 7.99534 | BA101: 8.12359 | BB101: 8.25618 | BC101: 8.36854 | BD101: 8.50817 | BE101: 8.62774 | BF101: 8.75104 | BG101: 8.85644 | BH101: 8.98501 | BI101: 9.09052 | BJ101: Consommation non énergétique de gaz pour la production de matières premières | BK101: TRUE
A102: Demande CH4 | B102: donnée nécessitant un traitement dans traitement_nW_EOLES | C102: demand_CH4_raf | D102: Raffineries | F102: ="Conso pour " & LOWER(D102) & " (pertes réseau incluses)" -> Conso pour raffineries (pertes réseau incluses) | G102: TWh PCI/an | H102: sec_uses.gaz_se.ens | I102: SEPIA | J102: 8.1595 | K102: 8.4912 | L102: 8.8977 | M102: 5.6825 | N102: 5.1249 | O102: 5.1533 | P102: 6.3168 | Q102: 6.9448 | R102: 7.5378 | S102: 7.9152 | T102: 8.2056 | U102: 8.3855 | V102: 8.4301 | W102: 8.3822 | X102: 8.3219 | Y102: 8.1791 | Z102: 7.9773 | AA102: 7.7512 | AB102: 7.4913 | AC102: 7.1811 | AD102: 6.8206 | AE102: 6.417 | AF102: 5.988 | AG102: 5.5307 | AH102: 5.0656 | AI102: 4.6146 | AJ102: 4.2039 | AK102: 3.8397 | AL102: 3.5405 | AM102: 3.3053 | AN102: 3.1266 | AO102: 3.0138 | AP102: 3.0119 | AQ102: 3.0087 | AR102: 3.0042 | AS102: 3.0331 | AT102: 3.026 | AU102: 3.013 | AV102: 3.0035 | AW102: 2.9929 | AX102: 2.9614 | AY102: 2.9595 | AZ102: 2.9648 | BA102: 2.9645 | BB102: 2.9641 | BC102: 2.9984 | BD102: 2.9976 | BE102: 2.9965 | BF102: 2.9952 | BG102: 2.9938 | BH102: 2.9719 | BI102: 2.9699 | BJ102: #N/A | BK102: TRUE
A103: Demande CH4 | B103: donnée non utilisée mais vérif de cohérence avec sorties | C103: demand_CH4 | D103: Prod élec | F103: ="Conso pour " & LOWER(D103) & " (pertes réseau incluses)" -> Conso pour prod élec (pertes réseau incluses) | G103: TWh PCI/an | H103: sec_uses.gaz_se.elc_se | I103: SEPIA | J103: 67.045 | K103: 59.0807 | L103: 55.2119 | M103: 70.4268 | N103: 49.9463 | O103: 29.5585 | P103: 29.5585 | Q103: 29.5585 | R103: 29.5585 | S103: 29.1557 | T103: 28.7705 | U103: 28.4013 | V103: 26.9207 | W103: 25.4547 | X103: 24.0019 | Y103: 22.562 | Z103: 21.1339 | AA103: 20.5705 | AB103: 20.0072 | AC103: 19.4439 | AD103: 18.8806 | AE103: 18.3173 | AF103: 18.8292 | AG103: 19.3412 | AH103: 19.8531 | AI103: 20.3651 | AJ103: 20.877 | AK103: 21.389 | AL103: 21.901 | AM103: 22.4129 | AN103: 22.9249 | AO103: 23.4368 | AP103: 23.4368 | AQ103: 23.4368 | AR103: 23.4368 | AS103: 23.4368 | AT103: 23.4368 | AU103: 23.4368 | AV103: 23.4368 | AW103: 23.4368 | AX103: 23.4368 | AY103: 23.4368 | AZ103: 23.4368 | BA103: 23.4368 | BB103: 23.4368 | BC103: 23.4368 | BD103: 23.4368 | BE103: 23.4368 | BF103: 23.4368 | BG103: 23.4368 | BH103: 23.4368 | BI103: 23.4368 | BJ103: #N/A | BK103: TRUE
A104: Demande CH4 | B104: donnée nécessitant un traitement dans traitement_nW_EOLES | C104: demand_CH4_neth | D104: Prod chaleur | F104: ="Conso pour " & LOWER(D104) & " (pertes réseau incluses)" -> Conso pour prod chaleur (pertes réseau incluses) | G104: TWh PCI/an | H104: sec_uses.gaz_se.vap_se | I104: SEPIA | J104: 21.1336 | K104: 21.2239 | L104: 22.4933 | M104: 20.8703 | N104: 20.2233 | O104: 18.8877 | P104: 18.5851 | Q104: 18.5851 | R104: 18.5851 | S104: 18.5851 | T104: 18.5851 | U104: 18.5851 | V104: 17.534 | W104: 16.4835 | X104: 15.4335 | Y104: 14.3839 | Z104: 13.3348 | AA104: 12.6434 | AB104: 11.952 | AC104: 11.2607 | AD104: 10.5693 | AE104: 9.8779 | AF104: 9.3937 | AG104: 8.9095 | AH104: 8.4253 | AI104: 7.9411 | AJ104: 7.4569 | AK104: 6.9727 | AL104: 6.4885 | AM104: 6.0042 | AN104: 5.52 | AO104: 5.0358 | AP104: 5.0358 | AQ104: 5.0358 | AR104: 5.0358 | AS104: 5.0358 | AT104: 5.0358 | AU104: 5.0358 | AV104: 5.0358 | AW104: 5.0358 | AX104: 5.0358 | AY104: 5.0358 | AZ104: 5.0358 | BA104: 5.0358 | BB104: 5.0358 | BC104: 5.0358 | BD104: 5.0358 | BE104: 5.0358 | BF104: 5.0358 | BG104: 5.0358 | BH104: 5.0358 | BI104: 5.0358 | BJ104: #N/A | BK104: TRUE
A105: Demande CH4 | B105: donnée non utilisée mais vérif de cohérence avec sorties | C105: demand_CH4 | D105: Excédent | F105: =D105 -> Excédent | G105: TWh PCI/an | H105: sec_uses.gaz_se.exp | I105: SEPIA | J105: 0 | K105: 0 | L105: 0 | M105: 0 | N105: 0 | O105: 0 | P105: 0 | Q105: 0 | R105: 0 | S105: 0 | T105: 0 | U105: 0 | V105: 0 | W105: 0 | X105: 0 | Y105: 0 | Z105: 0 | AA105: 0 | AB105: 0 | AC105: 0 | AD105: 0 | AE105: 0 | AF105: 0 | AG105: 0 | AH105: 0 | AI105: 0 | AJ105: 0 | AK105: 0 | AL105: 0 | AM105: 0 | AN105: 6.9484 | AO105: 17.0306 | AP105: 19.8929 | AQ105: 22.4368 | AR105: 24.7687 | AS105: 27.0364 | AT105: 28.557 | AU105: 30.1891 | AV105: 31.6581 | AW105: 32.778 | AX105: 33.4711 | AY105: 34.4234 | AZ105: 34.9316 | BA105: 35.5239 | BB105: 35.9938 | BC105: 37.0476 | BD105: 37.3552 | BE105: 37.7364 | BF105: 37.9666 | BG105: 38.3989 | BH105: 38.3651 | BI105: 38.7072 | BJ105: #N/A | BK105: TRUE
A106: Demande CH4 | B106: donnée nécessitant un traitement dans traitement_nW_EOLES | C106: demand_CH4_losses | D106: Pertes | F106: Pertes réseau (transport & distribution) | G106: TWh/an | H106: sec_uses.gaz_se.per_ntw | I106: SEPIA | J106: 5.0404 | K106: 3.9966 | L106: 3.4812 | M106: 4.2883 | N106: 4.08 | O106: 2.9767 | P106: 2.984 | Q106: 2.9662 | R106: 2.9229 | S106: 2.8672 | T106: 2.8072 | U106: 2.7449 | V106: 2.6932 | W106: 2.6337 | X106: 2.5691 | Y106: 2.4978 | Z106: 2.3918 | AA106: 2.2756 | AB106: 2.1787 | AC106: 2.0862 | AD106: 1.9922 | AE106: 1.8673 | AF106: 1.7915 | AG106: 1.7225 | AH106: 1.6621 | AI106: 1.6093 | AJ106: 1.5599 | AK106: 1.5136 | AL106: 1.4741 | AM106: 1.439 | AN106: 1.4061 | AO106: 1.3794 | AP106: 1.3546 | AQ106: 1.3326 | AR106: 1.3124 | AS106: 1.2962 | AT106: 1.2832 | AU106: 1.2682 | AV106: 1.2548 | AW106: 1.2445 | AX106: 1.2357 | AY106: 1.2272 | AZ106: 1.2229 | BA106: 1.2171 | BB106: 1.2125 | BC106: 1.2058 | BD106: 1.2028 | BE106: 1.199 | BF106: 1.1966 | BG106: 1.1922 | BH106: 1.1901 | BI106: 1.1865 | BJ106: #N/A | BK106: TRUE
A107: Demande CH4 | B107: donnée non utilisée mais vérif de cohérence avec sorties | C107: demand_CH4 | F107: TOTAL | G107: TWh PCI/an | H107: sec_uses.gaz_se.total | I107: SEPIA | J107: 446.6509 | K107: 423.5019 | L107: 424.4793 | M107: 422.4095 | N107: 386.7692 | O107: 363.2432 | P107: 364.2377 | Q107: 362.7023 | R107: 358.1708 | S107: 351.7613 | T107: 345.1652 | U107: 337.9545 | V107: 329.5601 | W107: 320.5755 | X107: 310.8191 | Y107: 300.3213 | Z107: 286.5096 | AA107: 272.6369 | AB107: 260.75 | AC107: 249.513 | AD107: 237.8967 | AE107: 223.1318 | AF107: 214.8496 | AG107: 207.0652 | AH107: 200.3412 | AI107: 194.2341 | AJ107: 188.5424 | AK107: 183.371 | AL107: 178.8201 | AM107: 174.7777 | AN107: 178.108 | AO107: 185.1226 | AP107: 185.5092 | AQ107: 185.8574 | AR107: 186.1677 | AS107: 186.8471 | AT107: 187.0698 | AU107: 187.1919 | AV107: 187.3212 | AW107: 187.4028 | AX107: 187.1969 | AY107: 187.3032 | AZ107: 187.3833 | BA107: 187.3962 | BB107: 187.4073 | BC107: 187.8285 | BD107: 187.8316 | BE107: 187.8292 | BF107: 187.8216 | BG107: 187.8101 | BH107: 187.5524 | BI107: 187.5292 | BJ107: #N/A
A108: Demande CH4 | B108: donnée non utilisée mais vérif de cohérence sur cet onglet | C108: demand_CH4 | F108: DELTA TOTAL vs. somme | G108: TWh/an | J108: =J107-SUMIF($BK$84:$BK$106,TRUE,J$84:J$106) -> 2e-05 | K108: =K107-SUMIF($BK$84:$BK$106,TRUE,K$84:K$106) -> 7e-05 | L108: =L107-SUMIF($BK$84:$BK$106,TRUE,L$84:L$106) -> 0 | M108: =M107-SUMIF($BK$84:$BK$106,TRUE,M$84:M$106) -> -3e-05 | N108: =N107-SUMIF($BK$84:$BK$106,TRUE,N$84:N$106) -> -1e-05 | O108: =O107-SUMIF($BK$84:$BK$106,TRUE,O$84:O$106) -> 2e-05 | P108: =P107-SUMIF($BK$84:$BK$106,TRUE,P$84:P$106) -> 4e-05 | Q108: =Q107-SUMIF($BK$84:$BK$106,TRUE,Q$84:Q$106) -> -4e-05 | ... BI108: =BI107-SUMIF($BK$84:$BK$106,TRUE,BI$84:BI$106) -> 6e-05
A110: Potentiel biomasse | B110: donnée utilisée directement dans les feuilles suivantes | C110: biomass_potential_pyrogazification | D110: Pyrogazéification | F110: Production de méthane à partir de biomasse solide | G110: TWh PCI/an | H110: promet | I110: bioenergies-PtX_v1.27 | J110: 0 | K110: 0 | L110: 0 | M110: 0 | N110: 0 | O110: 0 | P110: 0 | Q110: 0 | R110: 0 | S110: 0 | T110: 0 | U110: 0 | V110: 0.36043 | W110: 0.71941 | X110: 1.07688 | Y110: 1.49279 | Z110: 1.86227 | AA110: 2.23756 | AB110: 2.60499 | AC110: 2.97079 | AD110: 3.33466 | AE110: 3.69647 | AF110: 4.06429 | AG110: 4.43064 | AH110: 4.79709 | AI110: 5.3786 | AJ110: 5.76968 | AK110: 6.17363 | AL110: 6.5848 | AM110: 7.06265 | AN110: 7.4845 | AO110: 7.90705 | AP110: 7.9242 | AQ110: 7.93941 | AR110: 7.95396 | AS110: 8.27866 | AT110: 8.28603 | AU110: 8.24737 | AV110: 8.24528 | AW110: 8.23796 | AX110: 8.04293 | AY110: 8.11635 | AZ110: 8.18536 | BA110: 8.20296 | BB110: 8.21892 | BC110: 8.54634 | BD110: 8.55513 | BE110: 8.55869 | BF110: 8.558 | BG110: 8.5534 | BH110: 8.36076 | BI110: 8.34571 | BJ110: Production de méthane par pyrogazéification/méthanisation
A111: Potentiel biomasse | B111: donnée utilisée directement dans les feuilles suivantes | C111: biomass_potential_methanization | D111: Méthanisation | F111: Production de méthane par méthanisation | G111: TWh PCI/an | H111: prodombgr | I111: bioenergies-PtX_v1.27 | J111: 1.11062 | K111: 1.98736 | L111: 3.90445 | M111: 6.27772 | N111: 8.22226 | O111: 10.1286 | P111: 13.43683 | Q111: 17.31664 | R111: 21.76311 | S111: 26.75905 | T111: 32.27342 | U111: 39.59494 | V111: 46.09482 | W111: 52.94167 | X111: 60.0491 | Y111: 67.32051 | Z111: 74.65376 | AA111: 81.94407 | AB111: 89.08621 | AC111: 95.98131 | AD111: 102.53651 | AE111: 108.66813 | AF111: 114.42525 | AG111: 119.86897 | AH111: 124.95191 | AI111: 129.63238 | AJ111: 133.87642 | AK111: 138.23605 | AL111: 144.25139 | AM111: 150.02937 | AN111: 155.54171 | AO111: 160.75888 | AP111: 161.09386 | AQ111: 161.39588 | AR111: 161.66372 | AS111: 161.89608 | AT111: 162.09208 | AU111: 162.25119 | AV111: 162.37263 | AW111: 162.45661 | AX111: 162.50304 | AY111: 162.51201 | AZ111: 162.50227 | BA111: 162.49284 | BB111: 162.4838 | BC111: 162.4753 | BD111: 162.46753 | BE111: 162.46096 | BF111: 162.45485 | BG111: 162.44987 | BH111: 162.44569 | BI111: 162.44256 | BJ111: Production primaire totale de biogaz
A113: Contrainte carbone | B113: donnée non utilisée mais vérif de cohérence avec sorties | C113: carbon_budget | D113: Prod élec & chaleur | F113: Emissions tous GES uniquement prod élec & chaleur | G113: MtCO2eq/an | H113: ghg_sector.elc_vap_ghg | I113: SEPIA | J113: 29.45777 | K113: 27.05641 | L113: 28.73913 | M113: 30.75031 | N113: 23.68085 | O113: 19.06812 | P113: 18.66615 | Q113: 18.49616 | R113: 18.30926 | S113: 17.91045 | T113: 16.80181 | U113: 15.37719 | V113: 14.56087 | W113: 13.7262 | X113: 12.84872 | Y113: 11.97396 | Z113: 11.12535 | AA113: 10.6236 | AB113: 10.14137 | AC113: 9.6639 | AD113: 9.18762 | AE113: 8.67889 | AF113: 8.3897 | AG113: 8.10982 | AH113: 7.90285 | AI113: 7.74482 | AJ113: 7.05664 | AK113: 6.72687 | AL113: 6.33731 | AM113: 5.94728 | AN113: 5.84686 | AO113: 5.82715 | AP113: 5.80123 | AQ113: 5.80242 | AR113: 5.80314 | AS113: 5.80422 | AT113: 5.80469 | AU113: 5.80529 | AV113: 5.80565 | AW113: 5.80613 | AX113: 5.80661 | AY113: 5.80661 | AZ113: 5.8072 | BA113: 5.80768 | BB113: 5.80756 | BC113: 5.80768 | BD113: 5.80708 | BE113: 5.80672 | BF113: 5.80649 | BG113: 5.80625 | BH113: 5.80613 | BI113: 5.80601 | BJ113: #N/A
A114: Contrainte carbone | B114: donnée non utilisée mais vérif de cohérence avec sorties | C114: carbon_budget | D114: Charbon | F114: ="Emissions tous GES tous secteur, issues de la combustion de "&D114 -> Emissions tous GES tous secteur, issues de la combustion de Charbon | G114: MtCO2eq/an | H114: ghg_source.cms_pe | I114: SEPIA | J114: 9.9062 | K114: 7.9888 | L114: 10.8814 | M114: 9.5504 | N114: 7.346 | O114: 6.5194 | P114: 6.4615 | Q114: 6.3807 | R114: 6.1072 | S114: 5.7463 | T114: 5.1212 | U114: 4.6263 | V114: 4.4319 | W114: 4.2278 | X114: 4.0248 | Y114: 3.8241 | Z114: 3.2143 | AA114: 3.0046 | AB114: 2.8024 | AC114: 2.5872 | AD114: 2.369 | AE114: 1.3055 | AF114: 1.1571 | AG114: 0.9758 | AH114: 0.7946 | AI114: 0.6132 | AJ114: 0.4495 | AK114: 0.3041 | AL114: 0.187 | AM114: 0.0981 | AN114: 0.0418 | AO114: 0.0197 | AP114: 0.0162 | AQ114: 0.0135 | AR114: 0.0112 | AS114: 0.0098 | AT114: 0.0087 | AU114: 0.0077 | AV114: 0.007 | AW114: 0.0066 | AX114: 0.0063 | AY114: 0.0059 | AZ114: 0.006 | BA114: 0.0056 | BB114: 0.0056 | BC114: 0.0052 | BD114: 0.0052 | BE114: 0.005 | BF114: 0.0049 | BG114: 0.0047 | BH114: 0.0049 | BI114: 0.0047 | BJ114: #N/A
...

Sheet traitement_nW_EOLES
A1: code EOLES | B1: Descriptif | C1: Valeur | D1: Usage
B4: correction climat chauffage | C4: -0.07
B5: correction climat clim | C5: 0.6
B7: Demande élec
A9: demand_elec_res_heat | B9: Chauffage résidentiel | C9: {=INDEX(Data_EOLES!$J$1:$EK$191,MATCH(A9,Data_EOLES!$C:$C,0),MATCH(year_simulated,VALUE(Data_EOLES!$J$1:$EK$1),0))} -> 27.61632 | D9: dans cette feuille
A10: demand_elec_ter_heat | B10: Chauffage tertiaire | C10: {=INDEX(Data_EOLES!$J$1:$EK$191,MATCH(A10,Data_EOLES!$C:$C,0),MATCH(year_simulated,VALUE(Data_EOLES!$J$1:$EK$1),0))} -> 7.67608 | D10: dans cette feuille
A11: demand_elec_res_cool | B11: Clim résidentiel | C11: {=INDEX(Data_EOLES!$J$1:$EK$191,MATCH(A11,Data_EOLES!$C:$C,0),MATCH(year_simulated,VALUE(Data_EOLES!$J$1:$EK$1),0))} -> 3.34028 | D11: Pas utilisé ?
A12: demand_elec_ter_cool | B12: Clim tertiaire | C12: {=INDEX(Data_EOLES!$J$1:$EK$191,MATCH(A12,Data_EOLES!$C:$C,0),MATCH(year_simulated,VALUE(Data_EOLES!$J$1:$EK$1),0))} -> 16.65179 | D12: Pas utilisé ?
A14: demand_elec_res | B14: Total résidentiel | C14: {=INDEX(Data_EOLES!$J$1:$EK$191,MATCH(A14,Data_EOLES!$C:$C,0),MATCH(year_simulated,VALUE(Data_EOLES!$J$1:$EK$1),0))} -> 96.29877 | D14: dans cette feuille
A15: demand_elec_ter | B15: Total tertaire | C15: {=INDEX(Data_EOLES!$J$1:$EK$191,MATCH(A15,Data_EOLES!$C:$C,0),MATCH(year_simulated,VALUE(Data_EOLES!$J$1:$EK$1),0))} -> 103.73578 | D15: dans cette feuille
A16: demand_elec_mob | B16: Total mobilité | C16: {=INDEX(Data_EOLES!$J$1:$EK$191,MATCH(A16,Data_EOLES!$C:$C,0),MATCH(year_simulated,VALUE(Data_EOLES!$J$1:$EK$1),0))} -> 66.32331 | D16: dans cette feuille
A17: demand_elec_fret | B17: Total frêt | C17: {=INDEX(Data_EOLES!$J$1:$EK$191,MATCH(A17,Data_EOLES!$C:$C,0),MATCH(year_simulated,VALUE(Data_EOLES!$J$1:$EK$1),0))} -> 47.44162 | D17: dans cette feuille
A18: demand_elec_ind | B18: Total industrie | C18: {=INDEX(Data_EOLES!$J$1:$EK$191,MATCH(A18,Data_EOLES!$C:$C,0),MATCH(year_simulated,VALUE(Data_EOLES!$J$1:$EK$1),0))} -> 113.93828 | D18: dans cette feuille
A19: demand_elec_agr | B19: Total agriculture | C19: {=INDEX(Data_EOLES!$J$1:$EK$191,MATCH(A19,Data_EOLES!$C:$C,0),MATCH(year_simulated,VALUE(Data_EOLES!$J$1:$EK$1),0))} -> 12.21431 | D19: dans cette feuille
A20: demand_elec_other | B20: Total autre énergie | C20: {=INDEX(Data_EOLES!$J$1:$EK$191,MATCH(A20,Data_EOLES!$C:$C,0),MATCH(year_simulated,VALUE(Data_EOLES!$J$1:$EK$1),0))} -> 20.9709 | D20: dans cette feuille
A21: demand_elec_neth | B21: Total chaleur | C21: {=INDEX(Data_EOLES!$J$1:$EK$191,MATCH(A21,Data_EOLES!$C:$C,0),MATCH(year_simulated,VALUE(Data_EOLES!$J$1:$EK$1),0))} -> 3.2545 | D21: dans cette feuille
A22: demand_elec_losses | B22: Pertes réseau (transport & distribution) | C22: {=INDEX(Data_EOLES!$J$1:$EK$191,MATCH(A22,Data_EOLES!$C:$C,0),MATCH(year_simulated,VALUE(Data_EOLES!$J$1:$EK$1),0))} -> 39.9809 | D22: dans cette feuille
A24: demand_elec_tot | B24: Total elec | C24: =SUM(C14:C22) -> 504.15837 | D24: create_demand_param
B25: ="Total chauffage elec " &year_simulated -> Total chauffage elec 2060 | C25: =SUM(C9:C10) -> 35.2924 | D25: dans cette feuille
B26: Total chauffage elec 2019 corrigé climat 2050 | C26: =C27*(1+C4) -> 67.162163
B27: Total chauffage elec 2019 | C27: {=INDEX(Data_EOLES!$J$1:$EK$191,MATCH($A9,Data_EOLES!$C:$C,0),MATCH(2019,VALUE(Data_EOLES!$J$1:$EK$1),0)) + INDEX(Data_EOLES!$J$1:$EK$191,MATCH($A10,Data_EOLES!$C:$C,0),MATCH(2019,VALUE(Data_EOLES!$J$1:$EK$1),0))} -> 72.21738 | D27: dans cette feuille
B28: Total clim elec 2050 | C28: =SUM(C11:C12) -> 19.99207
B29: Total clim elec 2019 corrigé climat 2050 | C29: =C30*(1+C5) -> 25.846464
B30: Total clim elec 2019 | C30: {=INDEX(Data_EOLES!$J$1:$EK$191,MATCH($A11,Data_EOLES!$C:$C,0),MATCH(2019,VALUE(Data_EOLES!$J$1:$EK$1),0)) + INDEX(Data_EOLES!$J$1:$EK$191,MATCH($A12,Data_EOLES!$C:$C,0),MATCH(2019,VALUE(Data_EOLES!$J$1:$EK$1),0))} -> 16.15404
A31: coef_elec | B31: ="coef elec 2019 "&year_simulated -> coef elec 2019 2060 | C31: =C25/C26 -> 0.52548039 | D31: create_demand_param
A32: coef_clim_elec | B32: coef clim 2019 2050 | C32: =C28/C29 -> 0.77349343 | D32: create_demand_param
B34: Demande gaz (TWh PCI)
A36: demand_CH4_res_heat | B36: Chauffage résidentiel | C36: {=INDEX(Data_EOLES!$J$1:$EK$191,MATCH(A36,Data_EOLES!$C:$C,0),MATCH(year_simulated,VALUE(Data_EOLES!$J$1:$EK$1),0))} -> 14.93263 | D36: dans cette feuille
A37: demand_CH4_ter_heat | B37: Chauffage tertiaire | C37: {=INDEX(Data_EOLES!$J$1:$EK$191,MATCH(A37,Data_EOLES!$C:$C,0),MATCH(year_simulated,VALUE(Data_EOLES!$J$1:$EK$1),0))} -> 6.40148 | D37: dans cette feuille
A41: demand_CH4_res | B41: Total résidentiel | C41: {=INDEX(Data_EOLES!$J$1:$EK$191,MATCH(A41,Data_EOLES!$C:$C,0),MATCH(year_simulated,VALUE(Data_EOLES!$J$1:$EK$1),0))} -> 17.133 | D41: dans cette feuille
A42: demand_CH4_ter | B42: Total tertaire | C42: {=INDEX(Data_EOLES!$J$1:$EK$191,MATCH(A42,Data_EOLES!$C:$C,0),MATCH(year_simulated,VALUE(Data_EOLES!$J$1:$EK$1),0))} -> 10.39766 | D42: dans cette feuille
A43: demand_CH4_mob | B43: Total mobilité | C43: {=INDEX(Data_EOLES!$J$1:$EK$191,MATCH(A43,Data_EOLES!$C:$C,0),MATCH(year_simulated,VALUE(Data_EOLES!$J$1:$EK$1),0))} -> 6.0953 | D43: dans cette feuille
A44: demand_CH4_fret | B44: Total frêt | C44: {=INDEX(Data_EOLES!$J$1:$EK$191,MATCH(A44,Data_EOLES!$C:$C,0),MATCH(year_simulated,VALUE(Data_EOLES!$J$1:$EK$1),0))} -> 22.76362 | D44: dans cette feuille
A45: demand_CH4_ind | B45: Total industrie | C45: {=INDEX(Data_EOLES!$J$1:$EK$191,MATCH(A45,Data_EOLES!$C:$C,0),MATCH(year_simulated,VALUE(Data_EOLES!$J$1:$EK$1),0))} -> 42.38283 | D45: dans cette feuille
A46: demand_CH4_agr | B46: Total agriculture | C46: {=INDEX(Data_EOLES!$J$1:$EK$191,MATCH(A46,Data_EOLES!$C:$C,0),MATCH(year_simulated,VALUE(Data_EOLES!$J$1:$EK$1),0))} -> 10.57793 | D46: dans cette feuille
A47: demand_CH4_raf | B47: Total autre énergie | C47: {=INDEX(Data_EOLES!$J$1:$EK$191,MATCH(A47,Data_EOLES!$C:$C,0),MATCH(year_simulated,VALUE(Data_EOLES!$J$1:$EK$1),0))} -> 2.9595 | D47: dans cette feuille
B48: Total chaleur cogé gaz | C48: 2 | D48: lecture Sankey
A49: demand_CH4_neth | B49: Total chaleur | C49: {=INDEX(Data_EOLES!$J$1:$EK$191,MATCH(A49,Data_EOLES!$C:$C,0),MATCH(year_simulated,VALUE(Data_EOLES!$J$1:$EK$1),0))} -> 5.0358 | D49: dans cette feuille
A50: demand_CH4_other | B50: Total non-énergétique | C50: {=INDEX(Data_EOLES!$J$1:$EK$191,MATCH(A50,Data_EOLES!$C:$C,0),MATCH(year_simulated,VALUE(Data_EOLES!$J$1:$EK$1),0))} -> 7.85429 | D50: dans cette feuille
A51: demand_CH4_mar | B51: Total transport maritime international | C51: {=INDEX(Data_EOLES!$J$1:$EK$191,MATCH(A51,Data_EOLES!$C:$C,0),MATCH(year_simulated,VALUE(Data_EOLES!$J$1:$EK$1),0))} -> 3.01575 | D51: dans cette feuille
A52: demand_CH4_exc | B52: Excédents | C52: {=INDEX(Data_EOLES!$J$1:$EK$191,MATCH(A52,Data_EOLES!$C:$C,0),MATCH(year_simulated,VALUE(Data_EOLES!$J$1:$EK$1),0))} -> #N/A | D52: dans cette feuille
A53: demand_CH4_losses | B53: Pertes réseaux | C53: {=INDEX(Data_EOLES!$J$1:$EK$191,MATCH(A53,Data_EOLES!$C:$C,0),MATCH(year_simulated,VALUE(Data_EOLES!$J$1:$EK$1),0))} -> 1.2272 | D53: dans cette feuille
A55: demand_CH4_tot | B55: Total gaz | C55: =SUM(C41:C47)+SUM(C49:C51)+C53 - C48 -> 127.44288 | D55: create_demand_param
B56: ="Total chauffage gaz "&year_simulated -> Total chauffage gaz 2060 | C56: =SUM(C36:C37) -> 21.33411 | D56: dans cette feuille
B57: Total chauffage gaz 2019 | C57: {=INDEX(Data_EOLES!$J$1:$EK$191,MATCH($A36,Data_EOLES!$C:$C,0),MATCH(2019,VALUE(Data_EOLES!$J$1:$EK$1),0)) + INDEX(Data_EOLES!$J$1:$EK$191,MATCH($A37,Data_EOLES!$C:$C,0),MATCH(2019,VALUE(Data_EOLES!$J$1:$EK$1),0))} -> 171.99988 | D57: dans cette feuille
A58: coef_CH4 | B58: ="coef gaz 2019 "&year_simulated -> coef gaz 2019 2060 | C58: =C56/C57 -> 0.12403561 | D58: create_demand_param
B62: Demande H2 (TWh PCI)
A64: demand_H2_ind | B64: Industrie | C64: {=INDEX(Data_EOLES!$J$1:$EK$191,MATCH(A64,Data_EOLES!$C:$C,0),MATCH(year_simulated,VALUE(Data_EOLES!$J$1:$EK$1),0))} -> 3.0393 | D64: dans cette feuille
A65: demand_H2_mob | B65: Mobilité | C65: {=INDEX(Data_EOLES!$J$1:$EK$191,MATCH(A65,Data_EOLES!$C:$C,0),MATCH(year_simulated,VALUE(Data_EOLES!$J$1:$EK$1),0))} -> 0.9006 | D65: dans cette feuille
A66: demand_H2_fret | B66: Frêt | C66: {=INDEX(Data_EOLES!$J$1:$EK$191,MATCH(A66,Data_EOLES!$C:$C,0),MATCH(year_simulated,VALUE(Data_EOLES!$J$1:$EK$1),0))} -> 0 | D66: dans cette feuille
A67: demand_H2_other | B67: Non-énergétique | C67: {=INDEX(Data_EOLES!$J$1:$EK$191,MATCH(A67,Data_EOLES!$C:$C,0),MATCH(year_simulated,VALUE(Data_EOLES!$J$1:$EK$1),0))} -> 24.9409 | D67: dans cette feuille
A68: demand_H2_en | B68: Branche énergie | C68: {=INDEX(Data_EOLES!$J$1:$EK$191,MATCH(A68,Data_EOLES!$C:$C,0),MATCH(year_simulated,VALUE(Data_EOLES!$J$1:$EK$1),0))} -> 2.0373 | D68: dans cette feuille
A69: demand_H2_exc | B69: Excédents | C69: {=INDEX(Data_EOLES!$J$1:$EK$191,MATCH(A69,Data_EOLES!$C:$C,0),MATCH(year_simulated,VALUE(Data_EOLES!$J$1:$EK$1),0))} -> #N/A | D69: dans cette feuille
A70: demand_H2_efuel | B70: e-fuel | C70: {=INDEX(Data_EOLES!$J$1:$EK$191,MATCH(A70,Data_EOLES!$C:$C,0),MATCH(year_simulated,VALUE(Data_EOLES!$J$1:$EK$1),0))} -> 18.8464 | D70: dans cette feuille
A72: demand_H2_tot | B72: Total H2 | C72: =SUM(C64:C68)+C70 -> 49.7645 | D72: create_demand_param
B74: Production d'élec thermique cogé & non cogé (TWh)
A76: annual_production_gaz_coge_res | B76: Centrales cogé gaz réseau | C76: {=INDEX(Data_EOLES!$J$1:$EK$191,MATCH(A76,Data_EOLES!$C:$C,0),MATCH(year_simulated,VALUE(Data_EOLES!$J$1:$EK$1),0))} -> 2.24473 | D76: dans cette feuille
A77: annual_production_gaz_coge_biog | B77: Centrales cogé biogaz | C77: {=INDEX(Data_EOLES!$J$1:$EK$191,MATCH(A77,Data_EOLES!$C:$C,0),MATCH(year_simulated,VALUE(Data_EOLES!$J$1:$EK$1),0))} -> 0 | D77: dans cette feuille
A79: annual_production_ocgt_coge | B79: Total prod centrales gaz | C79: =SUM(C76:C77) -> 2.24473 | D79: max_cap
A81: annual_production_waste_noncoge | B81: Incinération déchets sans cogé | C81: {=INDEX(Data_EOLES!$J$1:$EK$191,MATCH(A81,Data_EOLES!$C:$C,0),MATCH(year_simulated,VALUE(Data_EOLES!$J$1:$EK$1),0))} -> 1.47053 | D81: dans cette feuille
A82: annual_production_waste_coge | B82: Incinération déchets avec cogé | C82: {=INDEX(Data_EOLES!$J$1:$EK$191,MATCH(A82,Data_EOLES!$C:$C,0),MATCH(year_simulated,VALUE(Data_EOLES!$J$1:$EK$1),0))} -> 2.83552 | D82: dans cette feuille
A84: annual_production_waste | B84: Total prod déchets | C84: =SUM(C80:C82) -> 4.30605 | D84: max_cap

Sheet create_demand_param
A1: demand_elec_tot | B1: =INDEX(traitement_nW_EOLES!$C:$C,MATCH($A1,traitement_nW_EOLES!$A:$A,0)) -> 504.15837
A2: coef_elec | B2: =INDEX(traitement_nW_EOLES!$C:$C,MATCH($A2,traitement_nW_EOLES!$A:$A,0)) -> 0.52548039
A3: coef_clim_elec | B3: =INDEX(traitement_nW_EOLES!$C:$C,MATCH($A3,traitement_nW_EOLES!$A:$A,0)) -> 0.77349343
A4: demand_CH4_tot | B4: =INDEX(traitement_nW_EOLES!$C:$C,MATCH($A4,traitement_nW_EOLES!$A:$A,0)) -> 127.44288
A5: coef_CH4 | B5: =INDEX(traitement_nW_EOLES!$C:$C,MATCH($A5,traitement_nW_EOLES!$A:$A,0)) -> 0.12403561
A6: demand_H2_tot | B6: =INDEX(traitement_nW_EOLES!$C:$C,MATCH($A6,traitement_nW_EOLES!$A:$A,0)) -> 49.7645

Sheet Constants
A1: Parameter | B1: value | C1: unit
A2: year_simulated | B2: 2060
A3: social_cost_of_carbon | B3: 400 | C3: €/tCO2
A4: carbon_budget | B4: 0 | C4: MtCO2/y
A5: CO2_industry_demand | B5: 37245 | C5: GWh of CH4
A6: CO2_industry_prod | B6: 52087 | C6: GWh of CH4
A7: CO2_usable_industry | B7: 0.838
A8: fcr_requirement | B8: 0.562 | C8: GW
A9: h2_saltcavern_discharge_to_storage_ratio | B9: 0.00658
A10: h2_saltcavern_charge_to_storage_ratio | B10: 0.00168
A11: load_shift_maximum_power | B11: 1.89e-05 | C11: /hour
A12: load_shift_period | B12: 6 | C12: hour
A13: load_uncertainty | B13: 0.01
A14: load_variation | B14: 0.1
A15: ch4_reservoir_charge_to_discharge_ratio | B15: 0.5
A16: phs_charge_to_discharge_ratio | B16: 0.92
A17: tr_loss | B17: 0.0001
A18: biomethane_import | B18: 170 | C18: €/MWh
A19: min_CF_hourly_nuclear | B19: 0.2
A20: max_CF_hourly_nuclear | B20: 0.9
A21: annual_production_nuclear | B21: {=INDEX(Data_EOLES!$J$1:$EK$191,MATCH(A21,Data_EOLES!$C:$C,0),MATCH(year_simulated,VALUE(Data_EOLES!$J$1:$EK$1),0))} -> 12.85092 | C21: TWh
A22: capacity_factor_nuclear_yearly | B22: 0.7
A23: limit_biogas_extra_import | B23: 240 | C23: TWh

Sheet Costs
A1: tech | B1: capex | C1: fOM | D1: storage_capex | E1: construction_time | F1: discount_rate | G1: lifetime | H1: vOM
A2: offshore_float | B2: 5017.5 | C2: 100.3 | E2: 3.5 | F2: 0.04 | G2: 30 | H2: 0
A3: offshore_ground | B3: 4807 | C3: 79.9 | E3: 3.5 | F3: 0.04 | G3: 30 | H3: 0
A4: onshore | B4: 836.5 | C4: 32 | E4: 1.5 | F4: 0.04 | G4: 25 | H4: 0
A5: pv_ground | B5: 686.8 | C5: 15.3 | E5: 0.5 | F5: 0.04 | G5: 25 | H5: 0
A6: pv_roof_com | B6: 799.85 | C6: 17.85 | E6: 0.25 | F6: 0.04 | G6: 25 | H6: 0
A7: pv_roof_indiv | B7: 1538.5 | C7: 47.2 | E7: 0 | F7: 0.04 | G7: 25 | H7: 0
A8: river | B8: 1400 | C8: 74 | E8: 7 | F8: 0.04 | G8: 70 | H8: 0.000625
A9: marine | B9: 2375 | C9: 343.75 | E9: 0 | F9: 0.04 | G9: 25 | H9: 0
A10: waste | B10: 0 | C10: 0 | E10: 0 | F10: 0.04 | G10: 25 | H10: 0
A11: biomass_coge | B11: 3900 | C11: 78 | E11: 0 | F11: 0.04 | G11: 25 | H11: 0.004125
A12: geothermal_coge | B12: 7537.5 | C12: 150.75 | E12: 0 | F12: 0.04 | G12: 30 | H12: 0
A13: ocgt_coge | B13: 1212.5 | C13: 47.2875 | E13: 0 | F13: 0.04 | G13: 30 | H13: 0.005
... A19: lake | B19: 2500 | C19: 74 | E19: 7 | F19: 0.04 | G19: 70 | H19: 0
A20: phs | B20: 2500 | C20: 74 | D20: 85 | E20: 7 | F20: 0.04 | G20: 70 | H20: 0
A21: battery_1h | B21: 0 | C21: 14 | D21: 297 | E21: 0.25 | F21: 0.04 | G21: 20 | H21: 0
A22: battery_2h | B22: 0 | C22: 16 | D22: 244 | E22: 0.25 | F22: 0.04 | G22: 20 | H22: 0
A23: battery_4h | B23: 0 | C23: 24 | D23: 224 | E23: 0.25 | F23: 0.04 | G23: 20 | H23: 0
A24: battery_8h | B24: 0 | C24: 40 | D24: 210 | E24: 0.25 | F24: 0.04 | G24: 20 | H24: 0
A25: methanization | B25: 2875 | C25: 117.875 | E25: 2 | F25: 0.04 | G25: 20 | H25: 0.003875
A26: pyrogazification | B26: 3468.75 | C26: 312.1875 | E26: 2 | F26: 0.04 | G26: 20 | H26: 0.0444
A27: biogas_import | B27: 0 | C27: 0 | E27: 0 | F27: 0.04 | G27: 1 | H27: 0.175
A28: H2_import | B28: 0 | C28: 0 | E28: 0 | F28: 0.04 | G28: 1 | H28: 0.2
A29: natural_gas | B29: 0 | C29: 0 | E29: 0 | F29: 0.04 | G29: 1 | H29: 0
A30: electrolysis | B30: =500/0.67*1.15 -> 858.20896 | C30: 15 | E30: 2 | F30: 0.04 | G30: 20 | H30: 0
A31: methanation | B31: 1609.5 | C31: 97.125 | E31: 2 | F31: 0.04 | G31: 20 | H31: 0
A32: h2_saltcavern | B32: 0 | C32: 2.5 | D32: 0.35 | E32: 3 | F32: 0.04 | G32: 40 | H32: 0.00625
A33: ch4_reservoir | B33: 0 | C33: 0 | D33: 0 | E33: 0 | F33: 0.04 | G33: 30 | H33: 0.0025
A34: str_dummy | B34: 10000 | C34: 1250 | D34: 1000 | E34: 10 | F34: 0.04 | G34: 10 | H34: 1.25
A35: rsv_dummy | B35: 10000 | C35: 1250 | E35: 10 | F35: 0.04 | G35: 10 | H35: 1.25
A36: lost_load | B36: 0 | C36: 0 | E36: 0 | F36: 0.04 | G36: 1 | H36: 10

Sheet fuel_prices
A1: fuel | B1: fuel_prices_2020 | C1: fuel_prices_rate
A2: coal | B2: 0.0066 | C2: 0.0158
A3: natural_gas | B3: 0.0203 | C3: 0.0233

Sheet tech_parameters
A1: tech | B1: frr_requirements | C1: carbon_content | D1: carbon_footprint | E1: co2_fraction | F1: co2_usable | G1: conversion_efficiency | H1: efficiency_storage_in | I1: efficiency_storage_out | J1: ramp_rate | K1: capacity_factor
A2: offshore_float | B2: 0.032 | D2: 0.007 | K2: 0.39
A3: offshore_ground | B3: 0.032 | D3: 0.007 | K3: 0.37
A4: onshore | B4: 0.032 | D4: 0.013 | K4: 0.29
A5: pv_ground | B5: 0.014 | D5: 0.014 | K5: 0.14
A6: pv_roof_com | B6: 0.014 | D6: 0.014 | K6: 0.12
A7: pv_roof_indiv | B7: 0.014 | D7: 0.014 | K7: 0.13
A8: river | B8: 0 | D8: 0.006 | K8: 0.3
A9: marine | B9: 0 | D9: 0 | K9: 0.45
A10: waste | B10: 0 | D10: 0 | K10: 0.173
A11: biomass_coge | B11: 0 | D11: 0 | K11: 0.4
A12: geothermal_coge | B12: 0 | D12: 0 | K12: 0.799
A13: ocgt_coge | B13: 0 | D13: 0.098 | G13: 0.4 | K13: 0.13
A14: nuclear | D14: 0.006 | J14: 0.5 | K14: 0.7
A15: coal | C15: 0.855 | D15: 1.1 | J15: 1.84
A16: ch4_ocgt | D16: 0.081 | G16: 0.4 | J16: 8.18
A17: ch4_ccgt | D17: 0.12 | G17: 0.6 | J17: 3.44
A18: h2_ccgt | D18: 0.035 | G18: 0.6 | J18: 3.44
A19: lake | D19: 0.006 | I19: 0.85
A20: phs | D20: 0.006 | H20: 0.9 | I20: 0.85
A21: battery_1h | D21: 0.058 | H21: 1 | I21: 0.9
A22: battery_2h | D22: 0.058 | H22: 1 | I22: 0.9
A23: battery_4h | D23: 0.058 | H23: 1 | I23: 0.9
A24: battery_8h | D24: 0.058 | H24: 1 | I24: 0.9
A25: methanization | E25: 0.42 | F25: 0.514
A26: pyrogazification | E26: 0.34 | F26: 0.676
A27: biogas_import
A28: H2_import
A29: natural_gas | C29: 0.2136 | D29: 0.2136
A30: electrolysis | D30: 0.005 | G30: {=INDEX(Data_EOLES!$J$1:$EK$191,MATCH(G$1&"_"&$A30,Data_EOLES!$C:$C,0),MATCH(year_simulated,VALUE(Data_EOLES!$J$1:$EK$1),0))} -> 0.67827
A31: methanation | G31: {=INDEX(Data_EOLES!$J$1:$EK$191,MATCH(G$1&"_"&$A31,Data_EOLES!$C:$C,0),MATCH(year_simulated,VALUE(Data_EOLES!$J$1:$EK$1),0))*G30} -> 0.56183139
A32: h2_saltcavern | D32: 0 | H32: 1 | I32: 1
A33: ch4_reservoir | D33: 0 | H33: 1 | I33: 1
A34: str_dummy | D34: 0 | H34: 1 | I34: 1
A35: rsv_dummy | D35: 0
A36: lost_load | D36: 0

Sheet reserve
A1: reserve | B1: reserve_activation_rate | C1: reserve_activation_time
A2: fcr | B2: 0.078 | C2: 0.00833
A3: frr | B3: 0.182 | C3: 0.0833

Sheet exist_cap
A1: tech | B1: FR | C1: ES | D1: IT | E1: CH | F1: DE | G1: BE | H1: UK | I1: NL | J1: IE | K1: PT
A2: offshore_float
A3: offshore_ground
A4: onshore
A5: pv_ground
A6: pv_roof_com
A7: pv_roof_indiv
A8: river | B8: {=INDEX(Data_EOLES!$J$1:$EK$191,MATCH("max_cap"&"_"&$A8,Data_EOLES!$C:$C,0),MATCH(year_simulated,VALUE(Data_EOLES!$J$1:$EK$1),0))} -> 7.6 | C8: =4.5 -> 4.5 | D8: =13 -> 13 | E8: =8.2 -> 8.2 | F8: =3.9 -> 3.9 | G8: =0.1 -> 0.1 | H8: =2.2 -> 2.2 | I8: =0.04 -> 0.04 | J8: =0.2 -> 0.2 | K8: =0.8 -> 0.8
A9: marine | B9: 0.25 | C9: =3.7 -> 3.7 | D9: =0 -> 0 | E9: =0 -> 0 | F9: =0 -> 0 | G9: =0 -> 0 | H9: =0 -> 0 | I9: =0 -> 0 | J9: =0 -> 0 | K9: =0 -> 0
A10: waste
A11: biomass_coge
A12: geothermal_coge
A13: ocgt_coge
A14: nuclear | B14: {=INDEX(Data_EOLES!$J$1:$EK$191,MATCH("annual_production"&"_"&$A14,Data_EOLES!$C:$C,0),MATCH(year_simulated,VALUE(Data_EOLES!$J$1:$EK$1),0))/INDEX(tech_parameters!$A$1:$CA$301, MATCH($A14,tech_parameters!$A$1:$A$301,0), MATCH("capacity_factor",tech_parameters!$A$1:$CA$1,0))/8.76} -> 2.0957143 | C14: 0 | D14: 0 | E14: 0 | F14: 0 | G14: 0 | H14: 0 | I14: 0 | J14: 0 | K14: 0
A15: coal
A16: ch4_ocgt
A17: ch4_ccgt
A18: h2_ccgt
A19: lake | B19: {=INDEX(Data_EOLES!$J$1:$EK$191,MATCH("max_cap"&"_"&$A19,Data_EOLES!$C:$C,0),MATCH(year_simulated,VALUE(Data_EOLES!$J$1:$EK$1),0))} -> 13.03119 | C19: =11.7 -> 11.7 | D19: =9 -> 9 | E19: =7.9 -> 7.9 | F19: =0.4 -> 0.4 | G19: =0 -> 0 | H19: =0 -> 0 | I19: =0 -> 0 | J19: =0 -> 0 | K19: =2.8 -> 2.8
A20: phs | B20: 5.06 | C20: 6.4 | D20: 7.22 | E20: 3.12 | F20: 6.5 | G20: 1.3 | H20: 2.8 | I20: 0 | J20: 0 | K20: 4.7
A21: battery_1h
A22: battery_2h
A23: battery_4h
A24: battery_8h
A25: methanization
A26: pyrogazification
A27: biogas_import
A28: H2_import
A29: natural_gas
A30: electrolysis
A31: methanation
A32: h2_saltcavern
... A36: lost_load

Sheet exist_en_cap
A1: tech | B1: FR | C1: ES | D1: IT | E1: CH | F1: DE | G1: BE | H1: UK | I1: NL | J1: IE | K1: PT
A2: offshore_float
A3: offshore_ground
A4: onshore
A5: pv_ground
A6: pv_roof_com
A7: pv_roof_indiv
A8: river
A9: marine
A10: waste
A11: biomass_coge
A12: geothermal_coge
A13: ocgt_coge
... A18: h2_ccgt
A19: lake | B19: 3819.3 | C19: =100*exist_cap!C19 -> 1170 | D19: =100*exist_cap!D19 -> 900 | E19: =100*exist_cap!E19 -> 790 | F19: =100*exist_cap!F19 -> 40 | G19: =100*exist_cap!G19 -> 0 | H19: =100*exist_cap!H19 -> 0 | I19: =100*exist_cap!I19 -> 0 | J19: =100*exist_cap!J19 -> 0 | K19: =100*exist_cap!K19 -> 280
A20: phs | B20: 101 | C20: =20*exist_cap!C20 -> 128 | D20: =20*exist_cap!D20 -> 144.4 | E20: =20*exist_cap!E20 -> 62.4 | F20: =20*exist_cap!F20 -> 130 | G20: =20*exist_cap!G20 -> 26 | H20: =20*exist_cap!H20 -> 56 | I20: =20*exist_cap!I20 -> 0 | J20: =20*exist_cap!J20 -> 0 | K20: =20*exist_cap!K20 -> 94
A21: battery_1h
A22: battery_2h
A23: battery_4h
A24: battery_8h
A25: methanization
A26: pyrogazification
A27: biogas_import
A28: H2_import
A29: natural_gas
A30: electrolysis
A31: methanation
A32: h2_saltcavern
... A36: lost_load

Sheet min_cap
A1: tech | B1: FR | C1: ES | D1: IT | E1: CH | F1: DE | G1: BE | H1: UK | I1: NL | J1: IE | K1: PT
A2: offshore_float | B2: =max_cap!B2 -> 29.2981 | C2: =max_cap!C2 -> 6.7 | D2: =max_cap!D2 -> 8.6 | E2: =max_cap!E2 -> 0 | F2: =max_cap!F2 -> 40.4 | G2: =max_cap!G2 -> 5 | H2: =max_cap!H2 -> 54.6 | I2: =max_cap!I2 -> 37.2 | ... K2: =max_cap!K2 -> 4.5
A3: offshore_ground | B3: =max_cap!B3 -> 18.49108 | C3: =max_cap!C3 -> 4.1 | D3: =max_cap!D3 -> 5.3 | E3: =max_cap!E3 -> 0 | F3: =max_cap!F3 -> 24.7 | G3: =max_cap!G3 -> 3 | H3: =max_cap!H3 -> 33.4 | I3: =max_cap!I3 -> 22.8 | ... K3: =max_cap!K3 -> 2.7
A4: onshore | B4: =max_cap!B4 -> 80.65538 | C4: =max_cap!C4 -> 89.4 | D4: =max_cap!D4 -> 67.6 | E4: =max_cap!E4 -> 11.7 | F4: =max_cap!F4 -> 129.6 | G4: =max_cap!G4 -> 11.6 | H4: =max_cap!H4 -> 61.1 | I4: =max_cap!I4 -> 12 | ... K4: =max_cap!K4 -> 17
A5: pv_ground | B5: =max_cap!B5 -> 69.27483 | C5: =max_cap!C5 -> 50.1 | D5: =max_cap!D5 -> 62.37 | E5: =max_cap!E5 -> 13.6 | F5: =max_cap!F5 -> 125.8 | G5: =max_cap!G5 -> 17 | H5: =max_cap!H5 -> 36.2 | I5: =max_cap!I5 -> 24.2 | ... K5: =max_cap!K5 -> 10.9
A6: pv_roof_com | B6: =max_cap!B6 -> 85.9395 | C6: =max_cap!C6 -> 70.9 | D6: =max_cap!D6 -> 88.83 | E6: =max_cap!E6 -> 19.4 | F6: =max_cap!F6 -> 179.1 | G6: =max_cap!G6 -> 24.2 | H6: =max_cap!H6 -> 51.5 | I6: =max_cap!I6 -> 34.5 | ... K6: =max_cap!K6 -> 15.6
A7: pv_roof_indiv | B7: =max_cap!B7 -> 41.81914 | C7: =max_cap!C7 -> 30.6 | D7: =max_cap!D7 -> 37.8 | E7: =max_cap!E7 -> 8.2 | F7: =max_cap!F7 -> 76.2 | G7: =max_cap!G7 -> 10.3 | H7: =max_cap!H7 -> 21.9 | I7: =max_cap!I7 -> 14.7 | ... K7: =max_cap!K7 -> 6.6
A8: river | B8: =max_cap!B8 -> 7.6 | C8: =max_cap!C8 -> 4.5 | D8: =max_cap!D8 -> 13 | E8: =max_cap!E8 -> 8.2 | F8: =max_cap!F8 -> 4.29 | G8: =max_cap!G8 -> 0.1 | H8: =max_cap!H8 -> 2.2 | I8: =max_cap!I8 -> 0.04 | ... K8: =max_cap!K8 -> 0.8
A9: marine | B9: =max_cap!B9 -> 1.39303 | C9: =max_cap!C9 -> 3.7 | D9: =max_cap!D9 -> 0 | E9: =max_cap!E9 -> 0 | F9: =max_cap!F9 -> 0 | G9: =max_cap!G9 -> 0 | H9: =max_cap!H9 -> 0 | I9: =max_cap!I9 -> 0 | ... K9: =max_cap!K9 -> 0
A10: waste | B10: =max_cap!B10 -> 2.841377 | C10: =max_cap!C10 -> 0.26 | D10: =max_cap!D10 -> 0.79 | E10: =max_cap!E10 -> 0 | F10: =max_cap!F10 -> 0 | G10: =max_cap!G10 -> 0.66 | H10: =max_cap!H10 -> 0 | I10: =max_cap!I10 -> 0 | ... K10: =max_cap!K10 -> 0
A11: biomass_coge | B11: =max_cap!B11 -> 0 | C11: =max_cap!C11 -> 0.23 | D11: =max_cap!D11 -> 0.57 | E11: =max_cap!E11 -> 0 | F11: =max_cap!F11 -> 0.4 | G11: =max_cap!G11 -> 0.37 | H11: =max_cap!H11 -> 0.26 | I11: =max_cap!I11 -> 0.15 | ... K11: =max_cap!K11 -> 0.46
A12: geothermal_coge | B12: =max_cap!B12 -> 0.135 | C12: =max_cap!C12 -> 1.43 | D12: =max_cap!D12 -> 1.3 | E12: =max_cap!E12 -> 0 | F12: =max_cap!F12 -> 0.05 | G12: =max_cap!G12 -> 0 | H12: =max_cap!H12 -> 0 | I12: =max_cap!I12 -> 0 | ... K12: =max_cap!K12 -> 0
A13: ocgt_coge
A14: nuclear | B14: =max_cap!B14 -> 2.0957143 | C14: =max_cap!C14 -> 0 | D14: =max_cap!D14 -> 0 | E14: =max_cap!E14 -> 0 | F14: =max_cap!F14 -> 0 | G14: =max_cap!G14 -> 0 | H14: =max_cap!H14 -> 0 | I14: =max_cap!I14 -> 0 | ... K14: =max_cap!K14 -> 0
A15: coal
A16: ch4_ocgt
A17: ch4_ccgt
A18: h2_ccgt
A19: lake | B19: =max_cap!B19 -> 13.03119 | C19: =max_cap!C19 -> 11.7 | D19: =max_cap!D19 -> 9 | E19: =max_cap!E19 -> 7.9 | F19: =max_cap!F19 -> 0.4 | G19: =max_cap!G19 -> 0 | H19: =max_cap!H19 -> 0 | I19: =max_cap!I19 -> 0 | ... K19: =max_cap!K19 -> 2.8
A20: phs | B20: 5 | C20: =max_cap!C20 -> 6.4 | D20: =max_cap!D20 -> 7.22 | E20: =max_cap!E20 -> 3.12 | F20: =max_cap!F20 -> 6.5 | G20: =max_cap!G20 -> 1.3 | H20: =max_cap!H20 -> 2.8 | I20: =max_cap!I20 -> 0 | J20: =max_cap!J20 -> 0 | K20: =max_cap!K20 -> 4.7
A21: battery_1h
A22: battery_2h
A23: battery_4h
A24: battery_8h
A25: methanization
A26: pyrogazification
A27: biogas_import
A28: H2_import
A29: natural_gas
A30: electrolysis
A31: methanation
A32: h2_saltcavern
A33: ch4_reservoir | B33: =max_cap!B33 -> 88.417
A34: str_dummy | B34: =max_cap!B34 -> 0 | C34: =max_cap!C34 -> 0 | D34: =max_cap!D34 -> 0 | E34: =max_cap!E34 -> 0 | F34: =max_cap!F34 -> 0 | G34: =max_cap!G34 -> 0 | H34: =max_cap!H34 -> 0 | I34: =max_cap!I34 -> 0 | ... K34: =max_cap!K34 -> 0
A35: rsv_dummy | B35: =max_cap!B35 -> 0 | C35: =max_cap!C35 -> 0 | D35: =max_cap!D35 -> 0 | E35: =max_cap!E35 -> 0 | F35: =max_cap!F35 -> 0 | G35: =max_cap!G35 -> 0 | H35: =max_cap!H35 -> 0 | I35: =max_cap!I35 -> 0 | ... K35: =max_cap!K35 -> 0
A36: lost_load

Sheet min_en_cap
A1: tech | B1: FR | C1: ES | D1: IT | E1: CH | F1: DE | G1: BE | H1: UK | I1: NL | J1: IE | K1: PT
A2: offshore_float
A3: offshore_ground
A4: onshore
A5: pv_ground
A6: pv_roof_com
A7: pv_roof_indiv
A8: river
A9: marine
A10: waste
A11: biomass_coge
A12: geothermal_coge
A13: ocgt_coge
... A18: h2_ccgt
A19: lake | B19: 3819.3 | C19: =100*exist_cap!C19 -> 1170 | D19: =100*exist_cap!D19 -> 900 | E19: =100*exist_cap!E19 -> 790 | F19: =100*exist_cap!F19 -> 40 | G19: =100*exist_cap!G19 -> 0 | H19: =100*exist_cap!H19 -> 0 | I19: =100*exist_cap!I19 -> 0 | J19: =100*exist_cap!J19 -> 0 | K19: =100*exist_cap!K19 -> 280
A20: phs | B20: =20*min_cap!B20 -> 100 | C20: =20*exist_cap!C20 -> 128 | D20: =20*exist_cap!D20 -> 144.4 | E20: =20*exist_cap!E20 -> 62.4 | F20: =20*exist_cap!F20 -> 130 | G20: =20*exist_cap!G20 -> 26 | H20: =20*exist_cap!H20 -> 56 | I20: =20*exist_cap!I20 -> 0 | J20: =20*exist_cap!J20 -> 0 | K20: =20*exist_cap!K20 -> 94
A21: battery_1h
A22: battery_2h
A23: battery_4h
A24: battery_8h
A25: methanization
A26: pyrogazification
A27: biogas_import
A28: H2_import
A29: natural_gas
A30: electrolysis
A31: methanation
A32: h2_saltcavern
A33: ch4_reservoir | B33: 118900 | C33: 0 | D33: 0 | E33: 0 | F33: 0 | G33: 0 | H33: 0 | I33: 0 | J33: 0 | K33: 0
A34: str_dummy
A35: rsv_dummy
A36: lost_load

Sheet fix_cap
A1: tech | B1: FR | C1: ES | D1: IT | E1: CH | F1: DE | G1: BE | H1: UK
A2: offshore_float
A3: offshore_ground
A4: onshore
A5: pv_ground
A6: pv_roof_com
A7: pv_roof_indiv
A8: river | B8: 7.7 | C8: 13.7 | D8: 15.53 | E8: 13.43 | F8: 4.3 | G8: 0.1 | H8: 2.2
A9: marine
A10: waste
A11: biomass_coge
A12: geothermal_coge
A13: ocgt_coge
A14: nuclear
A15: coal
A16: ch4_ocgt
A17: ch4_ccgt
A18: h2_ccgt
A19: lake | B19: 13.1
A20: phs
A21: battery_1h
A22: battery_2h
A23: battery_4h
A24: battery_8h
A25: methanization
A26: pyrogazification
A27: natural_gas
A28: electrolysis
A29: methanation
A30: h2_saltcavern
A31: ch4_reservoir | B31: 88.417
A32: str_dummy
A33: rsv_dummy

Sheet fix_en_cap
A1: tech | B1: FR | C1: ES | D1: IT | E1: CH | F1: DE | G1: BE | H1: UK
A2: offshore_float
A3: offshore_ground
A4: onshore
A5: pv_ground
A6: pv_roof_com
A7: pv_roof_indiv
A8: river
A9: marine
A10: waste
A11: biomass_coge
A12: geothermal_coge
A13: ocgt_coge
... A18: h2_ccgt
A19: lake | B19: 3819.3
A20: phs
A21: battery_1h
A22: battery_2h
A23: battery_4h
A24: battery_8h
A25: methanization
A26: pyrogazification
A27: biogas_import
A28: natural_gas
A29: electrolysis
A30: methanation
A31: h2_saltcavern
A32: ch4_reservoir | B32: 118900
A33: str_dummy
A34: rsv_dummy

Sheet biogas_potential
A1: tech | B1: FR | C1: ES | D1: IT | E1: CH | F1: DE | G1: BE | H1: UK | I1: NL | J1: IE | K1: PT
A2: methanization | B2: {=INDEX(Data_EOLES!$J$1:$EK$191,MATCH("biomass_potential_"&$A2,Data_EOLES!$C:$C,0),MATCH(year_simulated,VALUE(Data_EOLES!$J$1:$EK$1),0))} -> 162.51201 | C2: 56 | D2: 37 | E2: 4 | F2: 90 | G2: 8 | H2: 36 | I2: 10 | J2: 14 | K2: 5
A3: pyrogazification | B3: {=INDEX(Data_EOLES!$J$1:$EK$191,MATCH("biomass_potential_"&$A3,Data_EOLES!$C:$C,0),MATCH(year_simulated,VALUE(Data_EOLES!$J$1:$EK$1),0))} -> 8.11635 | C3: 16 | D3: 37 | E3: 4 | F3: 25 | G3: 0 | H3: 20 | I3: 0 | J3: 2 | K3: 9
A4: biogas_import | B4: 0 | C4: 15 | D4: 44 | E4: 0 | F4: 1 | G4: 37 | H4: 57 | I4: 75 | J4: 0 | K4: 0
A5: H2_import | B5: 0 | C5: 0 | D5: 0 | E5: 0 | F5: 0 | G5: 0 | H5: 0 | I5: 0 | J5: 0 | K5: 0

Sheet max_cap
A1: tech | B1: FR | C1: ES | D1: IT | E1: CH | F1: DE | G1: BE | H1: UK | I1: NL | J1: IE | K1: PT
A2: offshore_float | B2: {=INDEX(Data_EOLES!$J$1:$EK$191,MATCH("max_cap"&"_"&$A2,Data_EOLES!$C:$C,0),MATCH(year_simulated,VALUE(Data_EOLES!$J$1:$EK$1),0))} -> 29.2981 | C2: =6.7 -> 6.7 | D2: =8.6 -> 8.6 | E2: =0 -> 0 | F2: =40.4 -> 40.4 | G2: =5 -> 5 | H2: =54.6 -> 54.6 | I2: =37.2 -> 37.2 | J2: =16.4 -> 16.4 | K2: =4.5 -> 4.5
A3: offshore_ground | B3: {=INDEX(Data_EOLES!$J$1:$EK$191,MATCH("max_cap"&"_"&$A3,Data_EOLES!$C:$C,0),MATCH(year_simulated,VALUE(Data_EOLES!$J$1:$EK$1),0))} -> 18.49108 | C3: =4.1 -> 4.1 | D3: =5.3 -> 5.3 | E3: =0 -> 0 | F3: =24.7 -> 24.7 | G3: =3 -> 3 | H3: =33.4 -> 33.4 | I3: =22.8 -> 22.8 | J3: =10 -> 10 | K3: =2.7 -> 2.7
A4: onshore | B4: {=INDEX(Data_EOLES!$J$1:$EK$191,MATCH("max_cap"&"_"&$A4,Data_EOLES!$C:$C,0),MATCH(year_simulated,VALUE(Data_EOLES!$J$1:$EK$1),0))} -> 80.65538 | C4: =89.4 -> 89.4 | D4: =67.6 -> 67.6 | E4: =11.7 -> 11.7 | F4: =129.6 -> 129.6 | G4: =11.6 -> 11.6 | H4: =61.1 -> 61.1 | I4: =12 -> 12 | J4: =18.4 -> 18.4 | K4: =17 -> 17
A5: pv_ground | B5: {=INDEX(Data_EOLES!$J$1:$EK$191,MATCH("max_cap"&"_"&$A5,Data_EOLES!$C:$C,0),MATCH(year_simulated,VALUE(Data_EOLES!$J$1:$EK$1),0))} -> 69.27483 | C5: =50.1 -> 50.1 | D5: =1.05*59.4 -> 62.37 | E5: =13.6 -> 13.6 | F5: =125.8 -> 125.8 | G5: =17 -> 17 | H5: =36.2 -> 36.2 | I5: =24.2 -> 24.2 | J5: =5.9 -> 5.9 | K5: =10.9 -> 10.9
A6: pv_roof_com | B6: {=INDEX(Data_EOLES!$J$1:$EK$191,MATCH("max_cap"&"_"&$A6,Data_EOLES!$C:$C,0),MATCH(year_simulated,VALUE(Data_EOLES!$J$1:$EK$1),0))} -> 85.9395 | C6: =70.9 -> 70.9 | D6: =1.05*84.6 -> 88.83 | E6: =19.4 -> 19.4 | F6: =179.1 -> 179.1 | G6: =24.2 -> 24.2 | H6: =51.5 -> 51.5 | I6: =34.5 -> 34.5 | J6: =8.4 -> 8.4 | K6: =15.6 -> 15.6
A7: pv_roof_indiv | B7: {=INDEX(Data_EOLES!$J$1:$EK$191,MATCH("max_cap"&"_"&$A7,Data_EOLES!$C:$C,0),MATCH(year_simulated,VALUE(Data_EOLES!$J$1:$EK$1),0))} -> 41.81914 | C7: =30.6 -> 30.6 | D7: =1.05*36 -> 37.8 | E7: =8.2 -> 8.2 | F7: =76.2 -> 76.2 | G7: =10.3 -> 10.3 | H7: =21.9 -> 21.9 | I7: =14.7 -> 14.7 | J7: =3.6 -> 3.6 | K7: =6.6 -> 6.6
A8: river | B8: {=INDEX(Data_EOLES!$J$1:$EK$191,MATCH("max_cap"&"_"&$A8,Data_EOLES!$C:$C,0),MATCH(year_simulated,VALUE(Data_EOLES!$J$1:$EK$1),0))} -> 7.6 | C8: =4.5 -> 4.5 | D8: =13 -> 13 | E8: =8.2 -> 8.2 | F8: =1.1*3.9 -> 4.29 | G8: =0.1 -> 0.1 | H8: =2.2 -> 2.2 | I8: =0.04 -> 0.04 | J8: =0.2 -> 0.2 | K8: =0.8 -> 0.8
A9: marine | B9: {=INDEX(Data_EOLES!$J$1:$EK$191,MATCH("max_cap"&"_"&$A9,Data_EOLES!$C:$C,0),MATCH(year_simulated,VALUE(Data_EOLES!$J$1:$EK$1),0))} -> 1.39303 | C9: =3.7 -> 3.7 | D9: =0 -> 0 | E9: =0 -> 0 | F9: =0 -> 0 | G9: =0 -> 0 | H9: =0 -> 0 | I9: =0 -> 0 | J9: =0 -> 0 | K9: =0 -> 0
A10: waste | B10: =INDEX(traitement_nW_EOLES!$C:$C,MATCH("annual_production_"&A10,traitement_nW_EOLES!$A:$A,0))/INDEX(tech_parameters!$A$1:$CA$301, MATCH($A10,tech_parameters!$A$1:$A$301,0), MATCH("capacity_factor",tech_parameters!$A$1:$CA$1,0))/8.76 -> 2.841377 | C10: =0.26 -> 0.26 | D10: =0.79 -> 0.79 | E10: =0 -> 0 | F10: =0 -> 0 | G10: =0.66 -> 0.66 | H10: =0 -> 0 | I10: =0 -> 0 | J10: =0 -> 0 | K10: =0 -> 0
A11: biomass_coge | B11: {=INDEX(Data_EOLES!$J$1:$EK$191,MATCH("annual_production"&"_"&$A11,Data_EOLES!$C:$C,0),MATCH(year_simulated,VALUE(Data_EOLES!$J$1:$EK$1),0))/INDEX(tech_parameters!$A$1:$CA$301, MATCH($A11,tech_parameters!$A$1:$A$301,0), MATCH("capacity_factor",tech_parameters!$A$1:$CA$1,0))/8.76} -> 0 | C11: =0.23 -> 0.23 | D11: =0.57 -> 0.57 | E11: =0 -> 0 | F11: =0.4 -> 0.4 | G11: =0.37 -> 0.37 | H11: =0.26 -> 0.26 | I11: =0.15 -> 0.15 | J11: =0.03 -> 0.03 | K11: =0.46 -> 0.46
A12: geothermal_coge | B12: {=INDEX(Data_EOLES!$J$1:$EK$191,MATCH("max_cap"&"_"&$A12,Data_EOLES!$C:$C,0),MATCH(year_simulated,VALUE(Data_EOLES!$J$1:$EK$1),0))} -> 0.135 | C12: =1.43 -> 1.43 | D12: =1.3 -> 1.3 | E12: =0 -> 0 | F12: =0.05 -> 0.05 | G12: =0 -> 0 | H12: =0 -> 0 | I12: =0 -> 0 | J12: =0 -> 0 | K12: =0 -> 0
A13: ocgt_coge | B13: =INDEX(traitement_nW_EOLES!$C:$C,MATCH("annual_production_"&A13,traitement_nW_EOLES!$A:$A,0))/INDEX(tech_parameters!$A$1:$CA$301, MATCH($A13,tech_parameters!$A$1:$A$301,0), MATCH("capacity_factor",tech_parameters!$A$1:$CA$1,0))/8.76 -> 1.9711363 | C13: =0 -> 0 | D13: =9.4/8.76/0.13 -> 8.2543028 | E13: =0 -> 0 | F13: =0 -> 0 | G13: =4.82 -> 4.82 | H13: =5 -> 5 | I13: =2.4/0.13/8.76 -> 2.1074816 | J13: =0.3 -> 0.3 | K13: =0 -> 0
A14: nuclear | B14: {=INDEX(Data_EOLES!$J$1:$EK$191,MATCH("annual_production"&"_"&$A14,Data_EOLES!$C:$C,0),MATCH(year_simulated,VALUE(Data_EOLES!$J$1:$EK$1),0))/INDEX(tech_parameters!$A$1:$CA$301, MATCH($A14,tech_parameters!$A$1:$A$301,0), MATCH("capacity_factor",tech_parameters!$A$1:$CA$1,0))/8.76} -> 2.0957143 | C14: =0 -> 0 | D14: =0 -> 0 | E14: =0 -> 0 | F14: =0 -> 0 | G14: =0 -> 0 | H14: =0 -> 0 | I14: =0 -> 0 | J14: =0 -> 0 | K14: =0 -> 0
A15: coal | B15: =0 -> 0 | C15: =0 -> 0 | D15: =0 -> 0 | E15: =0 -> 0 | F15: =0 -> 0 | G15: =0 -> 0 | H15: =0 -> 0 | I15: =0 -> 0 | ... K15: =0 -> 0
A16: ch4_ocgt
A17: ch4_ccgt
A18: h2_ccgt
A19: lake | B19: {=INDEX(Data_EOLES!$J$1:$EK$191,MATCH("max_cap"&"_"&$A19,Data_EOLES!$C:$C,0),MATCH(year_simulated,VALUE(Data_EOLES!$J$1:$EK$1),0))} -> 13.03119 | C19: =11.7 -> 11.7 | D19: =9 -> 9 | E19: =7.9 -> 7.9 | F19: =0.4 -> 0.4 | G19: =0 -> 0 | H19: =0 -> 0 | I19: =0 -> 0 | J19: =0 -> 0 | K19: =2.8 -> 2.8
A20: phs | B20: 7 | C20: 6.4 | D20: 7.22 | E20: 3.12 | F20: 6.5 | G20: 1.3 | H20: 2.8 | I20: 0 | J20: 0 | K20: 4.7
A21: battery_1h
A22: battery_2h
A23: battery_4h
A24: battery_8h
A25: methanization
A26: pyrogazification
A27: biogas_import
A28: H2_import
A29: natural_gas | B29: {=INDEX(Data_EOLES!$J$1:$EK$191,MATCH("annual_production"&"_"&$A29,Data_EOLES!$C:$C,0),MATCH(year_simulated,VALUE(Data_EOLES!$J$1:$EK$1),0))} -> 0
A30: electrolysis
A31: methanation
A32: h2_saltcavern
A33: ch4_reservoir | B33: 88.417
A34: str_dummy | B34: 0 | C34: 0 | D34: 0 | E34: 0 | F34: 0 | G34: 0 | H34: 0 | I34: 0 | J34: 0 | K34: 0
A35: rsv_dummy | B35: 0 | C35: 0 | D35: 0 | E35: 0 | F35: 0 | G35: 0 | H35: 0 | I35: 0 | J35: 0 | K35: 0
A36: lost_load | B36: 0 | C36: 0 | D36: 0 | E36: 0 | F36: 0 | G36: 0 | H36: 0 | I36: 0 | J36: 0 | K36: 0

Sheet max_en_cap
A1: tech | B1: FR | C1: ES | D1: IT | E1: CH | F1: DE | G1: BE | H1: UK | I1: NL | J1: IE | K1: PT
A2: offshore_float
A3: offshore_ground
A4: onshore
A5: pv_ground
A6: pv_roof_com
A7: pv_roof_indiv
A8: river
A9: marine
A10: waste
A11: biomass_coge
A12: geothermal_coge
A13: ocgt_coge
... A18: h2_ccgt
A19: lake | B19: 3819.3 | C19: =100*exist_cap!C19 -> 1170 | D19: =100*exist_cap!D19 -> 900 | E19: =100*exist_cap!E19 -> 790 | F19: =100*exist_cap!F19 -> 40 | G19: =100*exist_cap!G19 -> 0 | H19: =100*exist_cap!H19 -> 0 | I19: =100*exist_cap!I19 -> 0 | J19: =100*exist_cap!J19 -> 0 | K19: =100*exist_cap!K19 -> 280
A20: phs | B20: =20*max_cap!B20 -> 140 | C20: =20*exist_cap!C20 -> 128 | D20: =20*exist_cap!D20 -> 144.4 | E20: =20*exist_cap!E20 -> 62.4 | F20: =20*exist_cap!F20 -> 130 | G20: =20*exist_cap!G20 -> 26 | H20: =20*exist_cap!H20 -> 56 | I20: =20*exist_cap!I20 -> 0 | J20: =20*exist_cap!J20 -> 0 | K20: =20*exist_cap!K20 -> 94
A21: battery_1h
A22: battery_2h
A23: battery_4h
A24: battery_8h
A25: methanization
A26: pyrogazification
A27: biogas_import
A28: H2_import
A29: natural_gas
A30: electrolysis
A31: methanation
A32: h2_saltcavern | B32: 4000
A33: ch4_reservoir | B33: 118900
A34: str_dummy
A35: rsv_dummy
A36: lost_load

Sheet links
A1: exporter | B1: FR | C1: BE | D1: DE | E1: CH | F1: IT | G1: ES | H1: UK | I1: NL | J1: IE | K1: PT
A2: FR | D2: 12.6 | E2: 3.3 | F2: 3.1 | G2: 10.2 | H2: 9.8
A3: BE | D3: 100
A4: DE | B4: 11 | C4: 100 | I4: 100
A5: CH | B5: 2
A6: IT | B6: 3.1
A7: ES | B7: 9.5 | K7: 100
A8: UK | B8: 9.5 | J8: 100
A9: NL | D9: 100
A10: IE | H10: 100
A11: PT | G11: 100

Sheet demande_EU
A1: demande | B1: FR | C1: ES | D1: IT | E1: CH | F1: DE | G1: BE | H1: UK | I1: NL | J1: IE | K1: PT
A2: CH4 | B2: 139 | C2: =84 -> 84 | D2: =94+1+1+3 -> 99 | E2: 7 | F2: =102+10 -> 112 | G2: =38+3 -> 41 | H2: =79+1+7 -> 87 | I2: =72+3 -> 75 | J2: =7+1 -> 8 | K2: 12
A3: H2 | B3: 40 | C3: 58.6 | D3: 30.3 | E3: 5.5 | F3: 148.4 | G3: 25.9 | H3: 56.3 | I3: 44.4 | J3: 19.2 | K3: 7.4
A4: elec | B4: 467 | C4: =307+27+1 -> 335 | D4: =378+28+2 -> 408 | E4: 70 | F4: =588+40+18 -> 646 | G4: =103+11 -> 114 | H4: =477+50+3 -> 530 | I4: =193+8+2 -> 203 | J4: =41+4 -> 45 | K4: =64+9 -> 73
A5: heating_factor | C5: =calculs_intermédiaires!F51 -> 1.6727273 | D5: =calculs_intermédiaires!G51 -> 2.06 | E5: =calculs_intermédiaires!H51 -> 1.8292683 | F5: =calculs_intermédiaires!I51 -> 3.2533333 | G5: =calculs_intermédiaires!J51 -> 1.6511628 | H5: =calculs_intermédiaires!K51 -> 4.3867403 | I5: =calculs_intermédiaires!L51 -> 12.0625 | J5: =calculs_intermédiaires!M51 -> 10.714286 | K5: =calculs_intermédiaires!N51 -> 0.8

Sheet calculs_intermédiaires
A1: répartition entre technologies | E1: FR | F1: ES | G1: IT | H1: CH | I1: DE | J1: BE | K1: UK | L1: NL | M1: IE | N1: PT
D2: offshore | E2: 41.5 | F2: 10.8 | G2: 9.3 | H2: 0 | I2: 70 | J2: 8 | K2: 80 | L2: 60 | M2: 22 | N2: 7.2
A3: solaire | B3: part des installations | D3: solar | E3: 153.8 | F3: 109 | G3: 180 | H3: 40 | I3: 370 | J3: 50 | K3: 90 | L3: 67.4 | M3: 16 | N3: 26.4
A4: ground | B4: 0.33
A5: roof_com | B5: 0.47 | D5: offshore_float | E5: =$B10*E2 -> 25.73 | F5: =$B10*F2 -> 6.696 | G5: =$B10*G2 -> 5.766 | H5: =$B10*H2 -> 0 | I5: =$B10*I2 -> 43.4 | J5: =$B10*J2 -> 4.96 | K5: =$B10*K2 -> 49.6 | L5: =$B10*L2 -> 37.2 | ... N5: =$B10*N2 -> 4.464
A6: roof_indiv | B6: 0.2 | D6: offshore_ground | E6: =$B9*E2 -> 15.77 | F6: =$B9*F2 -> 4.104 | G6: =$B9*G2 -> 3.534 | H6: =$B9*H2 -> 0 | I6: =$B9*I2 -> 26.6 | J6: =$B9*J2 -> 3.04 | K6: =$B9*K2 -> 30.4 | L6: =$B9*L2 -> 22.8 | ... N6: =$B9*N2 -> 2.736
A8: éolien | B8: part des installations | D8: solar_ground | E8: =$B4*E$3 -> 50.754 | F8: =$B4*F$3 -> 35.97 | G8: =$B4*G$3 -> 59.4 | H8: =$B4*H$3 -> 13.2 | I8: =$B4*I$3 -> 122.1 | J8: =$B4*J$3 -> 16.5 | K8: =$B4*K$3 -> 29.7 | L8: =$B4*L$3 -> 22.242 | ... N8: =$B4*N$3 -> 8.712
A9: ground | B9: 0.38 | D9: solar_roof_com | E9: =$B5*E$3 -> 72.286 | F9: =$B5*F$3 -> 51.23 | G9: =$B5*G$3 -> 84.6 | H9: =$B5*H$3 -> 18.8 | I9: =$B5*I$3 -> 173.9 | J9: =$B5*J$3 -> 23.5 | K9: =$B5*K$3 -> 42.3 | L9: =$B5*L$3 -> 31.678 | ... N9: =$B5*N$3 -> 12.408
A10: float | B10: 0.62 | D10: solar_roof_indiv | E10: =$B6*E$3 -> 30.76 | F10: =$B6*F$3 -> 21.8 | G10: =$B6*G$3 -> 36 | H10: =$B6*H$3 -> 8 | I10: =$B6*I$3 -> 74 | J10: =$B6*J$3 -> 10 | K10: =$B6*K$3 -> 18 | L10: =$B6*L$3 -> 13.48 | ... N10: =$B6*N$3 -> 5.28
D12: CF CLEVER | E12: FR | F12: ES | G12: IT | H12: CH | I12: DE | J12: BE | K12: UK | L12: NL | M12: IE | N12: PT
D13: solar | L13: 0.11 | M13: 0.1 | N13: 0.19
D14: onshore | F14: 0.32 | G14: 0.35 | H14: 0.28 | I14: 0.27 | J14: 0.31 | K14: 0.37 | L14: 0.34 | M14: 0.45 | N14: 0.31
D15: offshore | F15: 0.3 | G15: 0.4 | I15: 0.42 | J15: 0.41 | K15: 0.49 | L15: 0.47 | M15: 0.53 | N15: 0.34
D17: CF PECD | E17: FR | F17: ES | G17: IT | H17: CH | I17: DE | J17: BE | K17: UK | L17: NL | M17: IE | N17: PT
D18: solar
D19: onshore | F19: 0.25 | G19: 0.23 | H19: 0.2 | I19: 0.29 | J19: 0.34 | K19: 0.41 | L19: 0.34 | M19: 0.44 | N19: 0.25
D20: offshore | F20: 0.29 | G20: 0.26 | I20: 0.45 | J20: 0.42 | K20: 0.45 | L20: 0.46 | M20: 0.43 | N20: 0.38
B22: on change si au-delà de 0,9-1,1 | D22: ratio CF
D23: solar
D24: onshore | F24: =F14/F19 -> 1.28 | G24: =G14/G19 -> 1.5217391 | H24: =H14/H19 -> 1.4 | I24: =I14/I19 -> 0.93103448 | J24: =J14/J19 -> 0.91176471 | K24: =K14/K19 -> 0.90243902 | L24: =L14/L19 -> 1 | M24: =M14/M19 -> 1.0227273 | N24: =N14/N19 -> 1.24
D25: offshore | F25: =F15/F20 -> 1.0344828 | G25: =G15/G20 -> 1.5384615 | H25: =H15/H20 -> #DIV/0! | I25: =I15/I20 -> 0.93333333 | J25: =J15/J20 -> 0.97619048 | K25: =K15/K20 -> 1.0888889 | L25: =L15/L20 -> 1.0217391 | M25: =M15/M20 -> 1.2325581 | N25: =N15/N20 -> 0.89473684
A28: PRODUCTION RENOUVELABLE CLEVER vs EOLES
B29: FR | C29: EOLES | D29: ES | E29: EOLES | F29: DE | G29: EOLES | H29: UK | I29: EOLES | J29: IT | K29: EOLES | L29: CH | M29: EOLES | N29: BE | O29: EOLES | P29: NL | Q29: EOLES | R29: PT | S29: EOLES | T29: IE | U29: EOLES
A30: offshore | B30: 177 | D30: 28 | E30: 29 | F30: 258 | G30: 298 | H30: 341 | I30: 379 | J30: 32 | K30: 33 | L30: 0 | M30: 0 | N30: 29 | O30: 33 | P30: 246 | Q30: 267 | R30: 21 | T30: 102 | U30: 114
A31: onshore | B31: 213 | D31: 188 | E31: 183 | F31: 319 | G31: 384 | H31: 208 | I31: 235 | J31: 128 | K31: 128 | L31: 17 | M31: 16 | N31: 33 | O31: 41 | P31: 34 | Q31: 38 | R31: 35 | T31: 68 | U31: 80
A32: solar | B32: 234 | D32: 201 | E32: 198 | F32: 344 | G32: 279* | H32: 88 | I32: 58* | J32: 206 | K32: 232 | L32: 43 | M32: 35* | N32: 46 | O32: 37* | P32: 64 | Q32: 48* | R32: 44 | T32: 14 | U32: 10*
A33: hydro | B33: 54 | D33: 34 | E33: 38 | F33: 21 | G33: 16 | H33: 6 | I33: 4 | J33: 54 | K33: 45 | L33: 40 | M33: 38 | N33: 1 | O33: 0 | P33: 0 | Q33: 0 | R33: 12 | T33: 1 | U33: 0
A36: Modifications
A37: CH | B37: x1,4 onshore | C37: x1,5 river
A38: IT | B38: x10 river | C38: x2 capa + | D38: x5 CF curve
A39: Es | B39: x 1,3 solar | C39: x2 river
A40: PT | B40: x 1,1 solar | C40: x1,2 onshore
E45: FR | F45: ES | G45: IT | H45: CH | I45: DE | J45: BE | K45: UK | L45: NL | M45: IE | N45: PT
D46: heating res 2020 | F46: 5.5 | G46: 10 | H46: 4.1 | I46: 7.5 | J46: 4.3 | K46: 18.1 | L46: 1.6 | M46: 0.7 | N46: 1
D47: heating res 2050 | F47: 9.2 | G47: 20.6 | H47: 7.5 | I47: 24.4 | J47: 7.1 | K47: 79.4 | L47: 19.3 | M47: 7.5 | N47: 0.8
D48: cooling_res 2020
D49: cooling_res 2050
D51: factor heating | F51: =F47/F46 -> 1.6727273 | G51: =G47/G46 -> 2.06 | H51: =H47/H46 -> 1.8292683 | I51: =I47/I46 -> 3.2533333 | J51: =J47/J46 -> 1.6511628 | K51: =K47/K46 -> 4.3867403 | L51: =L47/L46 -> 12.0625 | M51: =M47/M46 -> 10.714286 | N51: =N47/N46 -> 0.8
B54: soldes imports | D54: CH4 | E54: FR | F54: ES | G54: IT | H54: CH | I54: DE | J54: BE | K54: UK | L54: NL | M54: IE | N54: PT | O54: somme
D55: demande CLEVER | F55: 84 | G55: 94 | H55: 0 | I55: 102 | J55: 38 | K55: 80 | L55: 72 | M55: 7 | N55: 12
D56: demande CIRED | F56: =84 -> 84 | G56: =94+1+1+3 -> 99 | H56: 7 | I56: =102+10 -> 112 | J56: =38+3 -> 41 | K56: =79+1+7 -> 87 | L56: =72+3 -> 75 | M56: =7+1 -> 8 | N56: 12
D57: diff | F57: =F55-F56 -> 0 | G57: =G55-G56 -> -5 | H57: =H55-H56 -> -7 | I57: =I55-I56 -> -10 | J57: =J55-J56 -> -3 | K57: =K55-K56 -> -7 | L57: =L55-L56 -> -3 | M57: =M55-M56 -> -1 | N57: =N55-N56 -> 0
D59: CLEVER | E59: -22 | F59: 15 | G59: 39 | H59: -1 | I59: -29 | J59: 34 | K59: 50 | L59: 72 | M59: -9 | N59: -4 | O59: =SUM(E59:N59) -> 145 | P59: large déficit
D60: CLEVER-CIRED | E60: -22 | F60: =F59-F57 -> 15 | G60: =G59-G57 -> 44 | H60: =H59-H57 -> 6 | I60: =I59-I57 -> -19 | J60: =J59-J57 -> 37 | K60: =K59-K57 -> 57 | L60: =L59-L57 -> 75 | M60: =M59-M57 -> -8 | N60: =N59-N57 -> -4 | O60: =SUM(E60:N60) -> 181 | P60: large déficit
D63: elec | E63: FR | F63: ES | G63: IT | H63: CH | I63: DE | J63: BE | K63: UK | L63: NL | M63: IE | N63: PT | O63: somme
D64: demande CLEVER
D65: demande CIRED
D66: CLEVER
D67: CLEVER-CIRED
D70: H2 | E70: FR | F70: ES | G70: IT | H70: CH | I70: DE | J70: BE | K70: UK | L70: NL | M70: IE | N70: PT | O70: somme
D71: demande CLEVER | F71: 55 | G71: =47+5 -> 52 | H71: 6 | I71: =193+10 -> 203 | J71: =41+2 -> 43 | K71: =48+6 -> 54 | L71: =66+2 -> 68 | M71: =4 -> 4 | N71: 6
D72: demande CLEVER-EOLES | F72: 58.6 | G72: 30.3 | H72: 5.5 | I72: 148.4 | J72: 25.9 | K72: 56.3 | L72: 44.4 | M72: 19.2 | N72: 7.4
D73: diff | F73: =F71-F72 -> -3.6 | G73: =G71-G72 -> 21.7 | H73: =H71-H72 -> 0.5 | I73: =I71-I72 -> 54.6 | J73: =J71-J72 -> 17.1 | K73: =K71-K72 -> -2.3 | L73: =L71-L72 -> 23.6 | M73: =M71-M72 -> -15.2 | N73: =N71-N72 -> -1.4
D74: diff NT | F74: 17 | G74: 16.7 | H74: 3.2 | I74: 76.4 | J74: 19.6 | K74: 15.6 | L74: 34.3 | M74: 1.1 | N74: 2
D76: CLEVER | E76: 3 | F76: -3 | G76: 33 | H76: -3 | I76: 80 | J76: 48 | K76: -4 | L76: -6 | M76: -62 | N76: -15 | O76: =SUM(E76:N76) -> 71 | P76: large déficit
B77: import = valeur positive | D77: CLEVER-EOLES | E77: 3 | F77: =F$76-F73 -> 0.6 | G77: =G$76-G73 -> 11.3 | H77: =H$76-H73 -> -3.5 | I77: =I$76-I73 -> 25.4 | J77: =J$76-J73 -> 30.9 | K77: =K$76-K73 -> -1.7 | L77: =L$76-L73 -> -29.6 | M77: =M$76-M73 -> -46.8 | N77: =N$76-N73 -> -13.6 | O77: =SUM(E77:N77) -> -24 | P77: large excès en UE
D78: CLEVER-EOLES NT | E78: 3 | F78: =F$76-F74 -> -20 | G78: =G$76-G74 -> 16.3 | H78: =H$76-H74 -> -6.2 | I78: =I$76-I74 -> 3.6 | J78: =J$76-J74 -> 28.4 | K78: =K$76-K74 -> -19.6 | L78: =L$76-L74 -> -40.3 | M78: =M$76-M74 -> -63.1 | N78: =N$76-N74 -> -17 | O78: =SUM(E78:N78) -> -114.9

Sheet bilans
D2: ajout de la conso chaleur anciennement H2 | G2: différence sur les imports | I2: non modifié
B3: Bilan des imports | C3: CH4 CLEVER-base | D3: CH4 CLEVER-update | E3: CH4 EOLES | F3: H2 CLEVER-base | G3: H2 CLEVER-update | H3: H2 EOLES | I3: Elec CLEVER | J3: Elec EOLES | L3: année de référence : 2053
B4: FR | C4: 17 | D4: 17 | E4: 0 | F4: 4 | G4: 4 | H4: 29 | I4: 49 | J4: 21.4
B5: ES | C5: -15 | D5: =C5 -> -15 | E5: -15 | F5: 3 | G5: =F5+17 -> 20 | H5: 0 | I5: 10 | J5: 0.7
B6: IT | C6: -39 | D6: =C6-5 -> -44 | E6: -44 | F6: -33 | G6: =F6+16.7 -> -16.3 | H6: -27 | I6: -17 | J6: -6.2
B7: CH | C7: 1 | D7: 1 | E7: -6 | F7: 3 | G7: =F7+3.2 -> 6.2 | H7: 18 | I7: 12 | J7: -4.5 | K7: erreur dans les données
B8: DE | C8: 9 | D8: =C8-10 -> -1 | E8: 0 | F8: -80 | G8: =F8+76.4 -> -3.6 | H8: -30 | I8: 29 | J8: 16.5
B9: BE | C9: -34 | D9: =C9-2.4 -> -36.4 | E9: -37 | F9: -48 | G9: =F9+19.6 -> -28.4 | H9: -29 | I9: -13 | J9: -14.5
B10: UK | C10: -50 | D10: =C10-6.5 -> -56.5 | E10: -57 | F10: 4 | G10: =F10+15.6 -> 19.6 | H10: -43 | I10: -24 | J10: -23.9
B11: NL | C11: -72 | D11: =C11-2.7 -> -74.7 | E11: -75 | F11: 6 | G11: =F11+34.3 -> 40.3 | H11: 15 | I11: 9 | J11: -2.9
B12: IE | C12: 9 | D12: =C12-0.4 -> 8.6 | E12: 0 | F12: 62 | G12: =F12+1.1 -> 63.1 | H12: 54 | I12: 21 | J12: 21.3
B13: PT | C13: 4 | D13: 4 | E13: 0 | F13: 15 | G13: =F13+2 -> 17 | H13: 12 | I13: 5 | J13: -0.2
B14: Somme (TWh/an) | C14: =SUM(C4:C13) -> -170 | D14: =SUM(D4:D13) -> -197 | E14: =SUM(E4:E13) -> -234 | F14: =SUM(F4:F13) -> -64 | G14: =SUM(G4:G13) -> 121.9 | H14: =SUM(H4:H13) -> -1 | I14: =SUM(I4:I13) -> 81 | J14: =SUM(J4:J13) -> 7.7
B15: Commentaire | C15: fort déficit sur la zone | D15: fort déficit | E15: =D14-E14 -> 37 | F15: déficit | G15: fort excès | H15: =G14-H14 -> 122.9 | I15: excès | J15: =I14 -> 81
J16: différence liée aux pertes de transmissions
B17: positif si export
B18: France : négaWatt 27
B21: Comparaison prod EnR | C21: CLEVER | G21: EOLES
C22: solaire | D22: solaire | E22: onshore | F22: onshore | G22: offshore | H22: offshore | I22: hydro | J22: hydro | K22: diff prod primaire (TWh/an) | L22: Commentaires
B23: FR | C23: 183 | D23: 159 | E23: 177 | F23: 179 | G23: 144 | H23: 140 | I23: 58 | J23: 51 | K23: =C23+E23+G23+I23-D23-F23-H23-J23 -> 33
B24: ES | C24: 201 | D24: 198 | E24: 188 | F24: 177 | G24: 28 | H24: 15 | I24: 34 | J24: 27 | K24: =C24+E24+G24+I24-D24-F24-H24-J24 -> 34 | L24: 50% de l'offshore en moyenne
B25: IT | C25: 206 | D25: 233 | E25: 128 | F25: 124 | G25: 32 | H25: 31 | I25: 54 | J25: 46 | K25: =C25+E25+G25+I25-D25-F25-H25-J25 -> -14 | L25: toujours full
B26: CH | C26: 43 | D26: 32 | E26: 17 | F26: 14 | G26: 0 | H26: 0 | I26: 40 | J26: 39 | K26: =C26+E26+G26+I26-D26-F26-H26-J26 -> 15 | L26: 90% du solaire
B27: DE | C27: 344 | D27: 288 | E27: 319 | F27: 349 | G27: 258 | H27: 276 | I27: 21 | J27: 16 | K27: =C27+E27+G27+I27-D27-F27-H27-J27 -> 13 | L27: 82% du solaire en moyenne
B28: BE | C28: 46 | D28: 40 | E28: 33 | F28: 36 | G28: 29 | H28: 24 | I28: 1 | J28: 0.2 | K28: =C28+E28+G28+I28-D28-F28-H28-J28 -> 8.8 | L28: 90% du solaire, 80% offshore
B29: UK | C29: 88 | D29: 65 | E29: 208 | F29: 208 | G29: 341 | H29: 337 | I29: 6 | J29: 3.6 | K29: =C29+E29+G29+I29-D29-F29-H29-J29 -> 29.4 | L29: 95% offshore, 85% solaire
B30: NL | C30: 64 | D30: 49 | E30: 34 | F30: 33 | G30: 246 | H30: 242 | I30: 0 | J30: 0.1 | K30: =C30+E30+G30+I30-D30-F30-H30-J30 -> 19.9 | L30: 85% solaire
B31: IE | C31: 14 | D31: 11 | E31: 68 | F31: 68 | G31: 102 | H31: 81 | I31: 1 | J31: 0.3 | K31: =C31+E31+G31+I31-D31-F31-H31-J31 -> 24.7 | L31: 85% solaire et offshore
B32: PT | C32: 44 | D32: 41 | E32: 35 | F32: 34 | G32: 21 | H32: 24 | I32: 12 | J32: 7 | K32: =C32+E32+G32+I32-D32-F32-H32-J32 -> 6
B36: Bilan des exports nets | C36: CH4 CLEVER-base | D36: CH4 CLEVER-update | E36: CH4 EOLES | F36: H2 CLEVER-base | G36: H2 CLEVER-update | H36: H2 EOLES | I36: Elec CLEVER | J36: Elec EOLES
B37: FR | C37: 17 | D37: 17 | E37: 2.4 | F37: 4 | G37: 4 | H37: 5.6 | I37: 49 | J37: 21.3
B38: ES | C38: -15 | D38: =C38 -> -15 | E38: -1.6 | F38: 3 | G38: =F38+17 -> 20 | H38: 2.1 | I38: 10 | J38: 6.5
B39: IT | C39: -39 | D39: =C39-5 -> -44 | E39: -44 | F39: -33 | G39: =F39+16.7 -> -16.3 | H39: -35.9 | I39: -17 | J39: -11.4
B40: CH | C40: 1 | D40: 1 | E40: 3.4 | F40: 3 | G40: =F40+3.2 -> 6.2 | H40: 12.1 | I40: 12 | J40: -4.5
B41: DE | C41: 9 | D41: =C41-10 -> -1 | E41: 32.7 | F41: -80 | G41: =F41+76.4 -> -3.6 | H41: -5.5 | I41: 29 | J41: 22.8
B42: BE | C42: -34 | D42: =C42-2.4 -> -36.4 | E42: -37 | F42: -48 | G42: =F42+19.6 -> -28.4 | H42: -29.3 | I42: -13 | J42: -25.2
B43: UK | C43: -50 | D43: =C43-6.5 -> -56.5 | E43: -45.8 | F43: 4 | G43: =F43+15.6 -> 19.6 | H43: -4.6 | I43: -24 | J43: -21.9
B44: NL | C44: -72 | D44: =C44-2.7 -> -74.7 | E44: -52.9 | F44: 6 | G44: =F44+34.3 -> 40.3 | H44: 6.8 | I44: 9 | J44: -2.9
B45: IE | C45: 9 | D45: =C45-0.4 -> 8.6 | E45: 24.3 | F45: 62 | G45: =F45+1.1 -> 63.1 | H45: 35.8 | I45: 21 | J45: 16.2
B46: PT | C46: 4 | D46: 4 | E46: 3 | F46: 15 | G46: =F46+2 -> 17 | H46: 12 | I46: 5 | J46: -0.8
B47: Somme (TWh/an) | C47: =SUM(C37:C46) -> -170 | D47: =SUM(D37:D46) -> -197 | E47: =SUM(E37:E46) -> -115.5 | F47: =SUM(F37:F46) -> -64 | G47: =SUM(G37:G46) -> 121.9 | H47: =SUM(H37:H46) -> -0.9 | I47: =SUM(I37:I46) -> 81 | J47: =SUM(J37:J46) -> 0.1
B48: Commentaire | C48: fort déficit sur la zone | D48: fort déficit | E48: =D47-E47 -> -81.5 | F48: déficit | G48: fort excès | H48: =G47-H47 -> 122.8 | I48: excès | J48: =I47 -> 81
B52: Comparaison prod EnR
C53: solaire | D53: solaire | E53: onshore | F53: onshore | G53: offshore | H53: offshore | I53: hydro | J53: hydro | K53: diff prod primaire (TWh/an) | L53: diff prod primaire( %)
B54: FR | C54: 183 | D54: =72.2+110.3 -> 182.5 | E54: 177 | F54: 178.9 | G54: 144 | H54: 146.4 | I54: 58 | J54: 55.9 | K54: =C54+E54+G54+I54-D54-F54-H54-J54 -> -1.7 | L54: =-K54/(I54+G54+E54+C54) -> 0.003024911
B55: ES | C55: 201 | D55: =127.9+69.9 -> 197.8 | E55: 188 | F55: 191 | G55: 28 | H55: 27.5 | I55: 34 | J55: 43.5 | K55: =C55+E55+G55+I55-D55-F55-H55-J55 -> -8.8 | L55: =-K55/(I55+G55+E55+C55) -> 0.019512195
B56: IT | C56: 206 | D56: =150.4+82.3 -> 232.7 | E56: 128 | F56: 124.3 | G56: 32 | H56: 31.4 | I56: 54 | J56: 46.2 | K56: =C56+E56+G56+I56-D56-F56-H56-J56 -> -14.6 | L56: =-K56/(I56+G56+E56+C56) -> 0.034761905
B57: CH | C57: 43 | D57: =15.5+28.3 -> 43.8 | E57: 17 | F57: =17.2 -> 17.2 | G57: 0 | H57: 0 | I57: 40 | J57: 39.1 | K57: =C57+E57+G57+I57-D57-F57-H57-J57 -> -0.1 | L57: =-K57/(I57+G57+E57+C57) -> 0.001
B58: DE | C58: 344 | D58: =228.2+124.1 -> 352.3 | E58: 319 | F58: 349 | G58: 258 | H58: 277 | I58: 21 | J58: 16 | K58: =C58+E58+G58+I58-D58-F58-H58-J58 -> -52.3 | L58: =-K58/(I58+G58+E58+C58) -> 0.05552017
B59: BE | C59: 46 | D59: =30.5+16.6 -> 47.1 | E59: 33 | F59: 35.6 | G59: 29 | H59: 29.8 | I59: 1 | J59: 0.2 | K59: =C59+E59+G59+I59-D59-F59-H59-J59 -> -3.7 | L59: =-K59/(I59+G59+E59+C59) -> 0.033944954
B60: UK | C60: 88 | D60: =57+31.2 -> 88.2 | E60: 208 | F60: 208.5 | G60: 341 | H60: 345.1 | I60: 6 | J60: 3.6 | K60: =C60+E60+G60+I60-D60-F60-H60-J60 -> -2.4 | L60: =-K60/(I60+G60+E60+C60) -> 0.0037325039
B61: NL | C61: 64 | D61: =40+21.8 -> 61.8 | E61: 34 | F61: 33.4 | G61: 246 | H61: 242.6 | I61: 0 | J61: 0.1 | K61: =C61+E61+G61+I61-D61-F61-H61-J61 -> 6.1 | L61: =-K61/(I61+G61+E61+C61) -> -0.017732558
B62: IE | C62: 14 | D62: =8.5+4.6 -> 13.1 | E62: 68 | F62: 68.2 | G62: 102 | H62: 100.7 | I62: 1 | J62: 0.3 | K62: =C62+E62+G62+I62-D62-F62-H62-J62 -> 2.7 | L62: =-K62/(I62+G62+E62+C62) -> -0.014594595
B63: PT | C63: 44 | D63: =14.3+26.3 -> 40.6 | E63: 35 | F63: 33.8 | G63: 21 | H63: 24.1 | I63: 12 | J63: 6.4 | K63: =C63+E63+G63+I63-D63-F63-H63-J63 -> 7.1 | L63: =-K63/(I63+G63+E63+C63) -> -0.063392857
K64: =SUM(K54:K63) -> -67.7 | L64: Excès de 68 TWh de production renouvelable en moyenne par rapport à CLEVER
B66: Comparaison prod EnR
C67: solaire | D67: solaire | E67: onshore | F67: onshore | G67: offshore | H67: offshore | I67: hydro | J67: hydro
B68: FR | C68: 183 | D68: =C68*1.05 -> 192.15 | E68: 177 | F68: =E68*1.05 -> 185.85 | G68: 144 | H68: 146.4 | I68: 58 | J68: 55.9
B69: ES | C69: 201 | D69: =C69*1.05 -> 211.05 | E69: 188 | F69: =E69*1.05 -> 197.4 | G69: 28 | H69: 27.5 | I69: 34 | J69: 43.5
B70: IT | C70: 206 | D70: =C70*1.05 -> 216.3 | E70: 128 | F70: =E70*1.05 -> 134.4 | G70: 32 | H70: 31.4 | I70: 54 | J70: 46.2
B71: CH | C71: 43 | D71: =C71*1.05 -> 45.15 | E71: 17 | F71: =E71*1.05 -> 17.85 | G71: 0 | H71: 0 | I71: 40 | J71: 39.1
B72: DE | C72: 344 | D72: =C72*1.05 -> 361.2 | E72: 319 | F72: =E72*1.05 -> 334.95 | G72: 258 | H72: 258 | I72: 21 | J72: 16
B73: BE | C73: 46 | D73: =C73*1.05 -> 48.3 | E73: 33 | F73: =E73*1.05 -> 34.65 | G73: 29 | H73: 29.8 | I73: 1 | J73: 0.2
B74: UK | C74: 88 | D74: =C74*1.05 -> 92.4 | E74: 208 | F74: =E74*1.05 -> 218.4 | G74: 341 | H74: 345.1 | I74: 6 | J74: 3.6
B75: NL | C75: 64 | D75: =C75*1.05 -> 67.2 | E75: 34 | F75: =E75*1.05 -> 35.7 | G75: 246 | H75: 242.6 | I75: 0 | J75: 0.1
B76: IE | C76: 14 | D76: =C76*1.05 -> 14.7 | E76: 68 | F76: =E76*1.05 -> 71.4 | G76: 102 | H76: 100.7 | I76: 1 | J76: 0.3
B77: PT | C77: 44 | D77: =C77*1.05 -> 46.2 | E77: 35 | F77: =E77*1.05 -> 36.75 | G77: 21 | H77: 24.1 | I77: 12 | J77: 6.4
B79: facteurs correctifs | C79: FR | D79: =D68/D54 -> 1.0528767 | F79: =F68/F54 -> 1.0388485
C80: ES | D80: =D69/D55 -> 1.0669869 | F80: =F69/F55 -> 1.0335079
C81: IT | D81: =D70/D56 -> 0.92952299 | F81: =F70/F56 -> 1.081255
C82: CH | D82: =D71/D57 -> 1.0308219 | F82: =F71/F57 -> 1.0377907
C83: DE | D83: =D72/D58 -> 1.0252626 | F83: =F72/F58 -> 0.95974212 | H83: =H72/H58 -> 0.93140794
C84: BE | D84: =D73/D59 -> 1.0254777 | F84: =F73/F59 -> 0.97331461
C85: UK | D85: =D74/D60 -> 1.047619 | F85: =F74/F60 -> 1.047482
C86: NL | D86: =D75/D61 -> 1.0873786 | F86: =F75/F61 -> 1.0688623
C87: IE | D87: =D76/D62 -> 1.1221374 | F87: =F76/F62 -> 1.0469208
C88: PT | D88: =D77/D63 -> 1.137931 | F88: =F77/F63 -> 1.0872781
B90: Comparaison prod EnR après modif
C91: solaire | D91: solaire | E91: diff | F91: onshore | G91: onshore | H91: diff | I91: offshore | J91: offshore | K91: diff | L91: hydro | M91: hydro | N91: diff
B92: FR | C92: 183 | D92: =72.2+110.3 -> 182.5 | E92: =D92/C92-1 -> -0.0027322404 | F92: 177 | G92: 178.9 | H92: =G92/F92-1 -> 0.010734463 | I92: 144 | J92: 146.4 | K92: =J92/I92-1 -> 0.016666667 | L92: 58 | M92: 55.9 | N92: =M92/L92-1 -> -0.036206897
B93: ES | C93: 201 | D93: =136.8+74.8 -> 211.6 | E93: =D93/C93-1 -> 0.052736318 | F93: 188 | G93: 196.8 | H93: =G93/F93-1 -> 0.046808511 | I93: 28 | J93: 27.5 | K93: =J93/I93-1 -> -0.017857143 | L93: 34 | M93: 43.5
B94: IT | C94: 206 | D94: =150.4+82.3 -> 232.7 | E94: =D94/C94-1 -> 0.12961165 | F94: 128 | G94: 134.2 | H94: =G94/F94-1 -> 0.0484375 | I94: 32 | J94: 31.4 | K94: =J94/I94-1 -> -0.01875 | L94: 54 | M94: 46.2
B95: CH | C95: 43 | D95: =29.1+16 -> 45.1 | E95: =D95/C95-1 -> 0.048837209 | F95: 17 | G95: =17.9 -> 17.9 | H95: =G95/F95-1 -> 0.052941176 | I95: 0 | J95: 0 | L95: 40 | M95: 39.1
B96: DE | C96: 344 | D96: =235+128 -> 363 | E96: =D96/C96-1 -> 0.055232558 | F96: 319 | G96: 335.2 | H96: =G96/F96-1 -> 0.050783699 | I96: 258 | J96: 257.6 | K96: =J96/I96-1 -> -0.0015503876 | L96: 21 | M96: 16
B97: BE | C97: 46 | D97: =31.4+17.1 -> 48.5 | E97: =D97/C97-1 -> 0.054347826 | F97: 33 | G97: =34.6 -> 34.6 | H97: =G97/F97-1 -> 0.048484848 | I97: 29 | J97: 29.8 | K97: =J97/I97-1 -> 0.027586207 | L97: 1 | M97: 0.2
B98: UK | C98: 88 | D98: =60+32 -> 92 | E98: =D98/C98-1 -> 0.045454545 | F98: 208 | G98: =218.9 -> 218.9 | H98: =G98/F98-1 -> 0.052403846 | I98: 341 | J98: 345.1 | K98: =J98/I98-1 -> 0.01202346 | L98: 6 | M98: 3.6
B99: NL | C99: 64 | D99: =67.5 -> 67.5 | E99: =D99/C99-1 -> 0.0546875 | F99: 34 | G99: 35.8 | H99: =G99/F99-1 -> 0.052941176 | I99: 246 | J99: 242.6 | K99: =J99/I99-1 -> -0.013821138 | L99: 0 | M99: 0.1
B100: IE | C100: 14 | D100: =C100*1.05 -> 14.7 | E100: =D100/C100-1 -> 0.05 | F100: 68 | G100: 71.6 | H100: =G100/F100-1 -> 0.052941176 | I100: 102 | J100: 100.7 | K100: =J100/I100-1 -> -0.012745098 | L100: 1 | M100: 0.3
B101: PT | C101: 44 | D101: 46.3 | E101: =D101/C101-1 -> 0.052272727 | F101: 35 | G101: 36.8 | H101: =G101/F101-1 -> 0.051428571 | I101: 21 | J101: 24.1 | K101: =J101/I101-1 -> 0.14761905 | L101: 12 | M101: 6.4
B105: Bilan des exports nets | C105: CH4 CLEVER-base | D105: CH4 CLEVER-update | E105: CH4 EOLES | F105: H2 CLEVER-base | G105: H2 CLEVER-update | H105: H2 EOLES | I105: Elec CLEVER | J105: Elec EOLES
B106: FR | C106: 17 | D106: 17 | E106: 22.09 | F106: 4 | G106: 4 | H106: 6.36 | I106: 49 | J106: 27.23
B107: ES | C107: -15 | D107: =C107 -> -15 | E107: 4.37 | F107: 3 | G107: =F107+17 -> 20 | H107: 4.98 | I107: 10 | J107: 5.95
B108: IT | C108: -39 | D108: =C108-5 -> -44 | E108: -44 | F108: -33 | G108: =F108+16.7 -> -16.3 | H108: -29.67 | I108: -17 | J108: -8.86
B109: CH | C109: 1 | D109: 1 | E109: 4.05 | F109: 3 | G109: =F109+3.2 -> 6.2 | H109: 12.31 | I109: 12 | J109: -5.2
B110: DE | C110: 9 | D110: =C110-10 -> -1 | E110: 30.34 | F110: -80 | G110: =F110+76.4 -> -3.6 | H110: -18.26 | I110: 29 | J110: 18.09
B111: BE | C111: -34 | D111: =C111-2.4 -> -36.4 | E111: -37 | F111: -48 | G111: =F111+19.6 -> -28.4 | H111: -31.02 | I111: -13 | J111: -24.09
B112: UK | C112: -50 | D112: =C112-6.5 -> -56.5 | E112: -40.93 | F112: 4 | G112: =F112+15.6 -> 19.6 | H112: -2.99 | I112: -24 | J112: -20.49
B113: NL | C113: -72 | D113: =C113-2.7 -> -74.7 | E113: -47.68 | F113: 6 | G113: =F113+34.3 -> 40.3 | H113: 6.64 | I113: 9 | J113: -4.28
B114: IE | C114: 9 | D114: =C114-0.4 -> 8.6 | E114: 29.05 | F114: 62 | G114: =F114+1.1 -> 63.1 | H114: 35.93 | I114: 21 | J114: 12.67
B115: PT | C115: 4 | D115: 4 | E115: 4.12 | F115: 15 | G115: =F115+2 -> 17 | H115: 15.72 | I115: 5 | J115: -0.96
...
